<?xml version="1.0" encoding="utf-8"?>
<OdfBody DocumentCode="GL0000000" FeedFlag="P" Source="IDS" Serial="22" Time="061847960" CompetitionCode="OG2016" Date="2016-08-10" LogicalDate="2016-08-10" DocumentType="DT_CODES" Version="4" DocumentSubtype="RECORD" ><Competition Code="OG2016"><CodeSet Event="070" Gender="M" Order="1" Discipline="AR" Code="ARM0700000"><Language Description="Men 72 Arrows 70m Round" Language="ENG"></Language><Language Description="Tour de 70 m, 72 flèches - hommes" Language="FRA"></Language><Language Description="Rodada de 70m, 72 flechas - homens" Language="POR"></Language><Language Description="Ronda de 70m, 72 flechas - masculino" Language="SPA"></Language></CodeSet><CodeSet Event="470" Gender="M" Order="2" Discipline="AR" Code="ARM4700005"><Language Description="Men 216 Arrows 70m Round" Language="ENG"></Language><Language Description="Tour de 70 m, 216 flèches - hommes" Language="FRA"></Language><Language Description="Rodada de 70m, 216 flechas - homens" Language="POR"></Language><Language Description="Ronda de 70m, 216 flechas - masculino" Language="SPA"></Language></CodeSet><CodeSet Event="070" Gender="W" Order="3" Discipline="AR" Code="ARW0700000"><Language Description="Women 72 Arrows 70m Round" Language="ENG"></Language><Language Description="Tour de 70 m, 72 flèches - femmes" Language="FRA"></Language><Language Description="Rodada de 70m, 72 flechas - mulheres" Language="POR"></Language><Language Description="Ronda de 70m, 72 flechas - femenino" Language="SPA"></Language></CodeSet><CodeSet Event="470" Gender="W" Order="4" Discipline="AR" Code="ARW4700005"><Language Description="Women 216 Arrows 70m Round" Language="ENG"></Language><Language Description="Tour de 70 m, 216 flèches - femmes" Language="FRA"></Language><Language Description="Rodada de 70m, 216 flechas - mulheres" Language="POR"></Language><Language Description="Ronda de 70m, 216 flechas - femenino" Language="SPA"></Language></CodeSet><CodeSet Event="001" Gender="M" Order="1" Discipline="AT" Code="ATM001000"><Language Description="Men's 100m" Language="ENG"></Language><Language Description="100 m - hommes" Language="FRA"></Language><Language Description="100m rasos masculino" Language="POR"></Language><Language Description="100m masculino" Language="SPA"></Language></CodeSet><CodeSet Event="002" Gender="M" Order="2" Discipline="AT" Code="ATM002000"><Language Description="Men's 200m" Language="ENG"></Language><Language Description="200 m - hommes" Language="FRA"></Language><Language Description="200m rasos masculino" Language="POR"></Language><Language Description="200m masculino" Language="SPA"></Language></CodeSet><CodeSet Event="004" Gender="M" Order="3" Discipline="AT" Code="ATM004000"><Language Description="Men's 400m" Language="ENG"></Language><Language Description="400 m - hommes" Language="FRA"></Language><Language Description="400m rasos masculino" Language="POR"></Language><Language Description="400m masculino" Language="SPA"></Language></CodeSet><CodeSet Event="008" Gender="M" Order="4" Discipline="AT" Code="ATM008000"><Language Description="Men's 800m" Language="ENG"></Language><Language Description="800 m - hommes" Language="FRA"></Language><Language Description="800m rasos masculino" Language="POR"></Language><Language Description="800m masculino" Language="SPA"></Language></CodeSet><CodeSet Event="012" Gender="M" Order="5" Discipline="AT" Code="ATM012000"><Language Description="Men's 110m Hurdles" Language="ENG"></Language><Language Description="110 m haies - hommes" Language="FRA"></Language><Language Description="110m com barreiras masculino" Language="POR"></Language><Language Description="110m con vallas masculino" Language="SPA"></Language></CodeSet><CodeSet Event="015" Gender="M" Order="6" Discipline="AT" Code="ATM015000"><Language Description="Men's 1500m" Language="ENG"></Language><Language Description="1 500 m - hommes" Language="FRA"></Language><Language Description="1.500m rasos masculino" Language="POR"></Language><Language Description="1500m masculino" Language="SPA"></Language></CodeSet><CodeSet Event="033" Gender="M" Order="7" Discipline="AT" Code="ATM033000"><Language Description="Men's 3000m Steeplechase" Language="ENG"></Language><Language Description="3 000 m steeple - hommes" Language="FRA"></Language><Language Description="3.000m com obstáculos masculino" Language="POR"></Language><Language Description="3000m con obstáculos masculino" Language="SPA"></Language></CodeSet><CodeSet Event="044" Gender="M" Order="8" Discipline="AT" Code="ATM044000"><Language Description="Men's 400m Hurdles" Language="ENG"></Language><Language Description="400 m haies - hommes" Language="FRA"></Language><Language Description="400m com barreiras masculino" Language="POR"></Language><Language Description="400m con vallas masculino" Language="SPA"></Language></CodeSet><CodeSet Event="050" Gender="M" Order="9" Discipline="AT" Code="ATM050000"><Language Description="Men's 5000m" Language="ENG"></Language><Language Description="5 000 m - hommes" Language="FRA"></Language><Language Description="5.000m rasos masculino" Language="POR"></Language><Language Description="5000m masculino" Language="SPA"></Language></CodeSet><CodeSet Event="051" Gender="M" Order="10" Discipline="AT" Code="ATM051000"><Language Description="Men's Shot Put" Language="ENG"></Language><Language Description="Lancer de poids - hommes" Language="FRA"></Language><Language Description="Arremesso do peso masculino" Language="POR"></Language><Language Description="Lanzamiento de bala masculino" Language="SPA"></Language></CodeSet><CodeSet Event="052" Gender="M" Order="11" Discipline="AT" Code="ATM052000"><Language Description="Men's Discus Throw" Language="ENG"></Language><Language Description="Lancer de disque - hommes" Language="FRA"></Language><Language Description="Lançamento do disco masculino" Language="POR"></Language><Language Description="Lanzamiento de disco masculino" Language="SPA"></Language></CodeSet><CodeSet Event="053" Gender="M" Order="12" Discipline="AT" Code="ATM053000"><Language Description="Men's Javelin Throw" Language="ENG"></Language><Language Description="Lancer de javelot - hommes" Language="FRA"></Language><Language Description="Lançamento do dardo masculino" Language="POR"></Language><Language Description="Lanzamiento de jabalina masculino" Language="SPA"></Language></CodeSet><CodeSet Event="054" Gender="M" Order="13" Discipline="AT" Code="ATM054000"><Language Description="Men's Hammer Throw" Language="ENG"></Language><Language Description="Lancer de marteau - hommes" Language="FRA"></Language><Language Description="Lançamento do martelo masculino" Language="POR"></Language><Language Description="Lanzamiento de martillo masculino" Language="SPA"></Language></CodeSet><CodeSet Event="061" Gender="M" Order="14" Discipline="AT" Code="ATM061000"><Language Description="Men's Long Jump" Language="ENG"></Language><Language Description="Saut en longueur - hommes" Language="FRA"></Language><Language Description="Salto em distância masculino" Language="POR"></Language><Language Description="Salto de longitud masculino" Language="SPA"></Language></CodeSet><CodeSet Event="062" Gender="M" Order="15" Discipline="AT" Code="ATM062000"><Language Description="Men's Triple Jump" Language="ENG"></Language><Language Description="Triple saut - hommes" Language="FRA"></Language><Language Description="Salto triplo masculino" Language="POR"></Language><Language Description="Salto triple masculino" Language="SPA"></Language></CodeSet><CodeSet Event="071" Gender="M" Order="16" Discipline="AT" Code="ATM071000"><Language Description="Men's High Jump" Language="ENG"></Language><Language Description="Saut en hauteur - hommes" Language="FRA"></Language><Language Description="Salto em altura masculino" Language="POR"></Language><Language Description="Salto de altura masculino" Language="SPA"></Language></CodeSet><CodeSet Event="072" Gender="M" Order="17" Discipline="AT" Code="ATM072000"><Language Description="Men's Pole Vault" Language="ENG"></Language><Language Description="Saut à la perche - hommes" Language="FRA"></Language><Language Description="Salto com vara masculino" Language="POR"></Language><Language Description="Salto con garrocha masculino" Language="SPA"></Language></CodeSet><CodeSet Event="092" Gender="M" Order="18" Discipline="AT" Code="ATM092000"><Language Description="Men's 20km Race Walk" Language="ENG"></Language><Language Description="20 km marche - hommes" Language="FRA"></Language><Language Description="Marcha atlética 20km masculina" Language="POR"></Language><Language Description="Marcha atlética 20km masculina" Language="SPA"></Language></CodeSet><CodeSet Event="095" Gender="M" Order="19" Discipline="AT" Code="ATM095000"><Language Description="Men's 50km Race Walk" Language="ENG"></Language><Language Description="50 km marche - hommes" Language="FRA"></Language><Language Description="Marcha atlética 50km masculina" Language="POR"></Language><Language Description="Marcha atlética 50km masculina" Language="SPA"></Language></CodeSet><CodeSet Event="099" Gender="M" Order="20" Discipline="AT" Code="ATM099000"><Language Description="Men's Marathon" Language="ENG"></Language><Language Description="Marathon - hommes" Language="FRA"></Language><Language Description="Maratona masculina" Language="POR"></Language><Language Description="Maratón masculino" Language="SPA"></Language></CodeSet><CodeSet Event="100" Gender="M" Order="21" Discipline="AT" Code="ATM100000"><Language Description="Men's 10,000m" Language="ENG"></Language><Language Description="10 000 m - hommes" Language="FRA"></Language><Language Description="10.000m rasos masculino" Language="POR"></Language><Language Description="10.000m masculino" Language="SPA"></Language></CodeSet><CodeSet Event="401" Gender="M" Order="22" Discipline="AT" Code="ATM401000"><Language Description="Men's 4 x 100m Relay" Language="ENG"></Language><Language Description="Relais 4 x 100 m - hommes" Language="FRA"></Language><Language Description="Revezamento 4x100m masculino" Language="POR"></Language><Language Description="Relevo 4x100m masculino" Language="SPA"></Language></CodeSet><CodeSet Event="404" Gender="M" Order="23" Discipline="AT" Code="ATM404000"><Language Description="Men's 4 x 400m Relay" Language="ENG"></Language><Language Description="Relais 4 x 400 m - hommes" Language="FRA"></Language><Language Description="Revezamento 4x400m masculino" Language="POR"></Language><Language Description="Relevo 4x400m masculino" Language="SPA"></Language></CodeSet><CodeSet Event="900" Gender="M" Order="24" Discipline="AT" Code="ATM900000"><Language Description="Men's Decathlon" Language="ENG"></Language><Language Description="Décathlon - hommes" Language="FRA"></Language><Language Description="Decatlo masculino" Language="POR"></Language><Language Description="Decatlón masculino" Language="SPA"></Language></CodeSet><CodeSet Event="900" Gender="M" Order="25" Discipline="AT" Code="ATM900A00"><Language Description="Men's Decathlon 100m" Language="ENG"></Language><Language Description="Décathlon - hommes, 100 m" Language="FRA"></Language><Language Description="Decatlo - 100m rasos masculino" Language="POR"></Language><Language Description="Decatlón - 100m masculino" Language="SPA"></Language></CodeSet><CodeSet Event="900" Gender="M" Order="26" Discipline="AT" Code="ATM900B00"><Language Description="Men's Decathlon Long Jump" Language="ENG"></Language><Language Description="Décathlon - saut en longueur, hommes" Language="FRA"></Language><Language Description="Decatlo - salto em distância masculino" Language="POR"></Language><Language Description="Decatlón - salto de longitud masculino" Language="SPA"></Language></CodeSet><CodeSet Event="900" Gender="M" Order="27" Discipline="AT" Code="ATM900C00"><Language Description="Men's Decathlon Shot Put" Language="ENG"></Language><Language Description="Décathlon - lancer de poids, hommes" Language="FRA"></Language><Language Description="Decatlo - arremesso do peso masculino" Language="POR"></Language><Language Description="Decatlón - lanzamiento de bala masculino" Language="SPA"></Language></CodeSet><CodeSet Event="900" Gender="M" Order="28" Discipline="AT" Code="ATM900D00"><Language Description="Men's Decathlon High Jump" Language="ENG"></Language><Language Description="Décathlon - saut en hauteur, hommes" Language="FRA"></Language><Language Description="Decatlo - salto em altura masculino" Language="POR"></Language><Language Description="Decatlón - salto de altura masculino" Language="SPA"></Language></CodeSet><CodeSet Event="900" Gender="M" Order="29" Discipline="AT" Code="ATM900E00"><Language Description="Men's Decathlon 400m" Language="ENG"></Language><Language Description="Décathlon - 400 m, hommes" Language="FRA"></Language><Language Description="Decatlo - 400m rasos masculino" Language="POR"></Language><Language Description="Decatlón - 400m masculino" Language="SPA"></Language></CodeSet><CodeSet Event="900" Gender="M" Order="30" Discipline="AT" Code="ATM900F00"><Language Description="Men's Decathlon 110m Hurdles" Language="ENG"></Language><Language Description="Décathlon - 110 m haies, hommes" Language="FRA"></Language><Language Description="Decatlo - 110m com barreiras masculino" Language="POR"></Language><Language Description="Decatlón - 110m con vallas masculino" Language="SPA"></Language></CodeSet><CodeSet Event="900" Gender="M" Order="31" Discipline="AT" Code="ATM900G00"><Language Description="Men's Decathlon Discus Throw" Language="ENG"></Language><Language Description="Décathlon - lancer de disque, hommes" Language="FRA"></Language><Language Description="Decatlo - lançamento do disco masculino" Language="POR"></Language><Language Description="Decatlón - lanzamiento disco masculino" Language="SPA"></Language></CodeSet><CodeSet Event="900" Gender="M" Order="32" Discipline="AT" Code="ATM900H00"><Language Description="Men's Decathlon Pole Vault" Language="ENG"></Language><Language Description="Décathlon - saut à la perche, hommes" Language="FRA"></Language><Language Description="Decatlo - salto com vara masculino" Language="POR"></Language><Language Description="Decatlón - salto con garrocha masculino" Language="SPA"></Language></CodeSet><CodeSet Event="900" Gender="M" Order="33" Discipline="AT" Code="ATM900I00"><Language Description="Men's Decathlon Javelin Throw" Language="ENG"></Language><Language Description="Décathlon - lancer de javelot, hommes" Language="FRA"></Language><Language Description="Decatlo - lançamento do dardo masculino" Language="POR"></Language><Language Description="Decatlón -lanzamiento jabalina masculino" Language="SPA"></Language></CodeSet><CodeSet Event="900" Gender="M" Order="34" Discipline="AT" Code="ATM900J00"><Language Description="Men's Decathlon 1500m" Language="ENG"></Language><Language Description="Décathlon - 1 500 m, hommes" Language="FRA"></Language><Language Description="Decatlo - 1.500m rasos masculino" Language="POR"></Language><Language Description="Decatlón - 1500m masculino" Language="SPA"></Language></CodeSet><CodeSet Event="001" Gender="W" Order="35" Discipline="AT" Code="ATW001000"><Language Description="Women's 100m" Language="ENG"></Language><Language Description="100 m - femmes" Language="FRA"></Language><Language Description="100m rasos feminino" Language="POR"></Language><Language Description="100m femenino" Language="SPA"></Language></CodeSet><CodeSet Event="002" Gender="W" Order="36" Discipline="AT" Code="ATW002000"><Language Description="Women's 200m" Language="ENG"></Language><Language Description="200 m - femmes" Language="FRA"></Language><Language Description="200m rasos feminino" Language="POR"></Language><Language Description="200m femenino" Language="SPA"></Language></CodeSet><CodeSet Event="004" Gender="W" Order="37" Discipline="AT" Code="ATW004000"><Language Description="Women's 400m" Language="ENG"></Language><Language Description="400 m - femmes" Language="FRA"></Language><Language Description="400m rasos feminino" Language="POR"></Language><Language Description="400m femenino" Language="SPA"></Language></CodeSet><CodeSet Event="008" Gender="W" Order="38" Discipline="AT" Code="ATW008000"><Language Description="Women's 800m" Language="ENG"></Language><Language Description="800 m - femmes" Language="FRA"></Language><Language Description="800m rasos feminino" Language="POR"></Language><Language Description="800m femenino" Language="SPA"></Language></CodeSet><CodeSet Event="011" Gender="W" Order="39" Discipline="AT" Code="ATW011000"><Language Description="Women's 100m Hurdles" Language="ENG"></Language><Language Description="100 m haies - femmes" Language="FRA"></Language><Language Description="100m com barreiras feminino" Language="POR"></Language><Language Description="100m con vallas femenino" Language="SPA"></Language></CodeSet><CodeSet Event="015" Gender="W" Order="40" Discipline="AT" Code="ATW015000"><Language Description="Women's 1500m" Language="ENG"></Language><Language Description="1 500 m - femmes" Language="FRA"></Language><Language Description="1.500m rasos feminino" Language="POR"></Language><Language Description="1500m femenino" Language="SPA"></Language></CodeSet><CodeSet Event="033" Gender="W" Order="41" Discipline="AT" Code="ATW033000"><Language Description="Women's 3000m Steeplechase" Language="ENG"></Language><Language Description="3 000 m steeple - femmes" Language="FRA"></Language><Language Description="3.000m com obstáculos feminino" Language="POR"></Language><Language Description="3000m con obstáculos femenino" Language="SPA"></Language></CodeSet><CodeSet Event="044" Gender="W" Order="42" Discipline="AT" Code="ATW044000"><Language Description="Women's 400m Hurdles" Language="ENG"></Language><Language Description="400 m haies - femmes" Language="FRA"></Language><Language Description="400m com barreiras feminino" Language="POR"></Language><Language Description="400m con vallas femenino" Language="SPA"></Language></CodeSet><CodeSet Event="050" Gender="W" Order="43" Discipline="AT" Code="ATW050000"><Language Description="Women's 5000m" Language="ENG"></Language><Language Description="5 000 m - femmes" Language="FRA"></Language><Language Description="5.000m rasos feminino" Language="POR"></Language><Language Description="5000m femenino" Language="SPA"></Language></CodeSet><CodeSet Event="051" Gender="W" Order="44" Discipline="AT" Code="ATW051000"><Language Description="Women's Shot Put" Language="ENG"></Language><Language Description="Lancer de poids - femmes" Language="FRA"></Language><Language Description="Arremesso do peso feminino" Language="POR"></Language><Language Description="Lanzamiento de bala femenino" Language="SPA"></Language></CodeSet><CodeSet Event="052" Gender="W" Order="45" Discipline="AT" Code="ATW052000"><Language Description="Women's Discus Throw" Language="ENG"></Language><Language Description="Lancer de disque - femmes" Language="FRA"></Language><Language Description="Lançamento do disco feminino" Language="POR"></Language><Language Description="Lanzamiento de disco femenino" Language="SPA"></Language></CodeSet><CodeSet Event="053" Gender="W" Order="46" Discipline="AT" Code="ATW053000"><Language Description="Women's Javelin Throw" Language="ENG"></Language><Language Description="Lancer de javelot - femmes" Language="FRA"></Language><Language Description="Lançamento do dardo feminino" Language="POR"></Language><Language Description="Lanzamiento de jabalina femenino" Language="SPA"></Language></CodeSet><CodeSet Event="054" Gender="W" Order="47" Discipline="AT" Code="ATW054000"><Language Description="Women's Hammer Throw" Language="ENG"></Language><Language Description="Lancer de marteau - femmes" Language="FRA"></Language><Language Description="Lançamento do martelo feminino" Language="POR"></Language><Language Description="Lanzamiento de martillo femenino" Language="SPA"></Language></CodeSet><CodeSet Event="061" Gender="W" Order="48" Discipline="AT" Code="ATW061000"><Language Description="Women's Long Jump" Language="ENG"></Language><Language Description="Saut en longueur - femmes" Language="FRA"></Language><Language Description="Salto em distância feminino" Language="POR"></Language><Language Description="Salto de longitud femenino" Language="SPA"></Language></CodeSet><CodeSet Event="062" Gender="W" Order="49" Discipline="AT" Code="ATW062000"><Language Description="Women's Triple Jump" Language="ENG"></Language><Language Description="Triple saut - femmes" Language="FRA"></Language><Language Description="Salto triplo feminino" Language="POR"></Language><Language Description="Salto triple femenino" Language="SPA"></Language></CodeSet><CodeSet Event="071" Gender="W" Order="50" Discipline="AT" Code="ATW071000"><Language Description="Women's High Jump" Language="ENG"></Language><Language Description="Saut en hauteur - femmes" Language="FRA"></Language><Language Description="Salto em altura feminino" Language="POR"></Language><Language Description="Salto de altura femenino" Language="SPA"></Language></CodeSet><CodeSet Event="072" Gender="W" Order="51" Discipline="AT" Code="ATW072000"><Language Description="Women's Pole Vault" Language="ENG"></Language><Language Description="Saut à la perche - femmes" Language="FRA"></Language><Language Description="Salto com vara feminino" Language="POR"></Language><Language Description="Salto con garrocha femenino" Language="SPA"></Language></CodeSet><CodeSet Event="092" Gender="W" Order="52" Discipline="AT" Code="ATW092000"><Language Description="Women's 20km Race Walk" Language="ENG"></Language><Language Description="20 km marche - femmes" Language="FRA"></Language><Language Description="Marcha atlética 20km feminina" Language="POR"></Language><Language Description="Marcha atlética 20km femenina" Language="SPA"></Language></CodeSet><CodeSet Event="099" Gender="W" Order="53" Discipline="AT" Code="ATW099000"><Language Description="Women's Marathon" Language="ENG"></Language><Language Description="Marathon - femmes" Language="FRA"></Language><Language Description="Maratona feminina" Language="POR"></Language><Language Description="Maratón femenino" Language="SPA"></Language></CodeSet><CodeSet Event="100" Gender="W" Order="54" Discipline="AT" Code="ATW100000"><Language Description="Women's 10,000m" Language="ENG"></Language><Language Description="10 000 m - femmes" Language="FRA"></Language><Language Description="10.000m rasos feminino" Language="POR"></Language><Language Description="10.000m femenino" Language="SPA"></Language></CodeSet><CodeSet Event="401" Gender="W" Order="55" Discipline="AT" Code="ATW401000"><Language Description="Women's 4 x 100m Relay" Language="ENG"></Language><Language Description="Relais 4 x 100 m - femmes" Language="FRA"></Language><Language Description="Revezamento 4x100m feminino" Language="POR"></Language><Language Description="Relevo 4x100m femenino" Language="SPA"></Language></CodeSet><CodeSet Event="404" Gender="W" Order="56" Discipline="AT" Code="ATW404000"><Language Description="Women's 4 x 400m Relay" Language="ENG"></Language><Language Description="Relais 4 x 400 m - femmes" Language="FRA"></Language><Language Description="Revezamento 4x400m feminino" Language="POR"></Language><Language Description="Relevo 4x400m femenino" Language="SPA"></Language></CodeSet><CodeSet Event="700" Gender="W" Order="57" Discipline="AT" Code="ATW700000"><Language Description="Women's Heptathlon" Language="ENG"></Language><Language Description="Heptathlon - femmes" Language="FRA"></Language><Language Description="Heptatlo feminino" Language="POR"></Language><Language Description="Heptatlón femenino" Language="SPA"></Language></CodeSet><CodeSet Event="700" Gender="W" Order="58" Discipline="AT" Code="ATW700A00"><Language Description="Women's Heptathlon 100m Hurdles" Language="ENG"></Language><Language Description="Heptathlon - 100 m haies, femmes" Language="FRA"></Language><Language Description="Heptatlo - 100m rasos feminino" Language="POR"></Language><Language Description="Heptatlón - 100m con vallas femenino" Language="SPA"></Language></CodeSet><CodeSet Event="700" Gender="W" Order="59" Discipline="AT" Code="ATW700B00"><Language Description="Women's Heptathlon High Jump" Language="ENG"></Language><Language Description="Heptathlon - saut en hauteur, femmes" Language="FRA"></Language><Language Description="Heptatlo - salto em altura feminino" Language="POR"></Language><Language Description="Heptatlón - salto de altura femenino" Language="SPA"></Language></CodeSet><CodeSet Event="700" Gender="W" Order="60" Discipline="AT" Code="ATW700C00"><Language Description="Women's Heptathlon Shot Put" Language="ENG"></Language><Language Description="Heptathlon - lancer de poids, femmes" Language="FRA"></Language><Language Description="Heptatlo - arremesso do peso feminino" Language="POR"></Language><Language Description="Heptatlón - lanzamiento de bala femenino" Language="SPA"></Language></CodeSet><CodeSet Event="700" Gender="W" Order="61" Discipline="AT" Code="ATW700D00"><Language Description="Women's Heptathlon 200m" Language="ENG"></Language><Language Description="Heptathlon - 200 m, femmes" Language="FRA"></Language><Language Description="Heptatlo - 200m rasos feminino" Language="POR"></Language><Language Description="Heptatlón - 200m femenino" Language="SPA"></Language></CodeSet><CodeSet Event="700" Gender="W" Order="62" Discipline="AT" Code="ATW700E00"><Language Description="Women's Heptathlon Long Jump" Language="ENG"></Language><Language Description="Heptathlon - saut en longueur, femmes" Language="FRA"></Language><Language Description="Heptatlo - salto em distância feminino" Language="POR"></Language><Language Description="Heptatlón - salto de longitud femenino" Language="SPA"></Language></CodeSet><CodeSet Event="700" Gender="W" Order="63" Discipline="AT" Code="ATW700F00"><Language Description="Women's Heptathlon Javelin Throw" Language="ENG"></Language><Language Description="Heptathlon - lancer de javelot, femmes" Language="FRA"></Language><Language Description="Heptatlo - lançamento do dardo feminino" Language="POR"></Language><Language Description="Heptatlón -lanzamiento jabalina femenino" Language="SPA"></Language></CodeSet><CodeSet Event="700" Gender="W" Order="64" Discipline="AT" Code="ATW700G00"><Language Description="Women's Heptathlon 800m" Language="ENG"></Language><Language Description="Heptathlon - 800 m, femmes" Language="FRA"></Language><Language Description="Heptatlo - 800m rasos feminino" Language="POR"></Language><Language Description="Heptatlón - 800m femenino" Language="SPA"></Language></CodeSet><CodeSet Event="111" Gender="M" Order="2" Discipline="CF" Code="CFM111000"><Language Description="Men's Kayak Single 1000m" Language="ENG"></Language><Language Description="Kayak monoplace (K1) 1 000 m - hommes" Language="FRA"></Language><Language Description="Caiaque individual (K1) 1.000m masculino" Language="POR"></Language><Language Description="Kayak individual (K1) 1000m masculino" Language="SPA"></Language></CodeSet><CodeSet Event="112" Gender="M" Order="1" Discipline="CF" Code="CFM112000"><Language Description="Men's Kayak Single 200m" Language="ENG"></Language><Language Description="Kayak monoplace (K1) 200 m - hommes" Language="FRA"></Language><Language Description="Caiaque individual (K1) 200m masculino" Language="POR"></Language><Language Description="Kayak individual (K1) 200m masculino" Language="SPA"></Language></CodeSet><CodeSet Event="121" Gender="M" Order="4" Discipline="CF" Code="CFM121000"><Language Description="Men's Kayak Double 1000m" Language="ENG"></Language><Language Description="Kayak biplace (K2) 1 000 m - hommes" Language="FRA"></Language><Language Description="Caiaque duplo (K2) 1.000m masculino" Language="POR"></Language><Language Description="Kayak doble (K2) 1000m masculino" Language="SPA"></Language></CodeSet><CodeSet Event="122" Gender="M" Order="3" Discipline="CF" Code="CFM122000"><Language Description="Men's Kayak Double 200m" Language="ENG"></Language><Language Description="Kayak biplace (K2) 200 m - hommes" Language="FRA"></Language><Language Description="Caiaque duplo (K2) 200m masculino" Language="POR"></Language><Language Description="Kayak doble (K2) 200m masculino" Language="SPA"></Language></CodeSet><CodeSet Event="141" Gender="M" Order="5" Discipline="CF" Code="CFM141000"><Language Description="Men's Kayak Four 1000m" Language="ENG"></Language><Language Description="Kayak à quatre (K4) 1 000 m - hommes" Language="FRA"></Language><Language Description="Caiaque quádruplo (K4) 1.000m masculino" Language="POR"></Language><Language Description="Kayak cuádruple (K4) 1000m masculino" Language="SPA"></Language></CodeSet><CodeSet Event="211" Gender="M" Order="7" Discipline="CF" Code="CFM211000"><Language Description="Men's Canoe Single 1000m" Language="ENG"></Language><Language Description="Canoë monoplace (C1) 1 000 m - hommes" Language="FRA"></Language><Language Description="Canoa individual (C1) 1.000m masculina" Language="POR"></Language><Language Description="Canoa individual (C1) 1000m masculina" Language="SPA"></Language></CodeSet><CodeSet Event="212" Gender="M" Order="6" Discipline="CF" Code="CFM212000"><Language Description="Men's Canoe Single 200m" Language="ENG"></Language><Language Description="Canoë monoplace (C1) 200 m - hommes" Language="FRA"></Language><Language Description="Canoa individual (C1) 200m masculina" Language="POR"></Language><Language Description="Canoa individual (C1) 200m masculina" Language="SPA"></Language></CodeSet><CodeSet Event="221" Gender="M" Order="8" Discipline="CF" Code="CFM221000"><Language Description="Men's Canoe Double 1000m" Language="ENG"></Language><Language Description="Canoë biplace (C2) 1 000 m - hommes" Language="FRA"></Language><Language Description="Canoa dupla (C2) 1.000m masculina" Language="POR"></Language><Language Description="Canoa doble (C2) 1000m masculina" Language="SPA"></Language></CodeSet><CodeSet Event="112" Gender="W" Order="9" Discipline="CF" Code="CFW112000"><Language Description="Women's Kayak Single 200m" Language="ENG"></Language><Language Description="Kayak monoplace (K1) 200 m - femmes" Language="FRA"></Language><Language Description="Caiaque individual (K1) 200m feminino" Language="POR"></Language><Language Description="Kayak individual (K1) 200m femenino" Language="SPA"></Language></CodeSet><CodeSet Event="115" Gender="W" Order="10" Discipline="CF" Code="CFW115000"><Language Description="Women's Kayak Single 500m" Language="ENG"></Language><Language Description="Kayak monoplace (K1) 500 m - femmes" Language="FRA"></Language><Language Description="Caiaque individual (K1) 500m feminino" Language="POR"></Language><Language Description="Kayak individual (K1) 500m femenino" Language="SPA"></Language></CodeSet><CodeSet Event="125" Gender="W" Order="11" Discipline="CF" Code="CFW125000"><Language Description="Women's Kayak Double 500m" Language="ENG"></Language><Language Description="Kayak biplace (K2) 500 m - femmes" Language="FRA"></Language><Language Description="Caiaque duplo (K2) 500m feminino" Language="POR"></Language><Language Description="Kayak doble (K2) 500m femenino" Language="SPA"></Language></CodeSet><CodeSet Event="145" Gender="W" Order="12" Discipline="CF" Code="CFW145000"><Language Description="Women's Kayak Four 500m" Language="ENG"></Language><Language Description="Kayak à quatre (K4) 500 m - femmes" Language="FRA"></Language><Language Description="Caiaque quádruplo (K4) 500m feminino" Language="POR"></Language><Language Description="Kayak cuádruple (K4) 500m femenino" Language="SPA"></Language></CodeSet><CodeSet Event="001" Gender="M" Order="1" Discipline="CT" Code="CTM001900"><Language Description="Men's 200m Flying Start" Language="ENG"></Language><Language Description="Vitesse départ lancé - hommes" Language="FRA"></Language><Language Description="Velocidade masculina" Language="POR"></Language><Language Description="Masculino, 200m salida lanzada" Language="SPA"></Language></CodeSet><CodeSet Event="010" Gender="M" Order="2" Discipline="CT" Code="CTM010300"><Language Description="Men's 1km Time Trial" Language="ENG"></Language><Language Description="Hom., contre-la-montre (1 km)" Language="FRA"></Language><Language Description="Omnium masculino, contrarrelógio de 1km" Language="POR"></Language><Language Description="Masculino, 1km contrarreloj" Language="SPA"></Language></CodeSet><CodeSet Event="010" Gender="M" Order="3" Discipline="CT" Code="CTM010500"><Language Description="Men's 4km Individual Pursuit" Language="ENG"></Language><Language Description="Hom., poursuite ind. (4 km)" Language="FRA"></Language><Language Description="Perseguição individual masculina (4km)" Language="POR"></Language><Language Description="Masculino, 4km persecución individual" Language="SPA"></Language></CodeSet><CodeSet Event="401" Gender="M" Order="4" Discipline="CT" Code="CTM401000"><Language Description="Men's Team Sprint" Language="ENG"></Language><Language Description="Vitesse par équipes - hommes" Language="FRA"></Language><Language Description="Velocidade por equipes masculina" Language="POR"></Language><Language Description="Velocidad por equipos masculino" Language="SPA"></Language></CodeSet><CodeSet Event="402" Gender="M" Order="5" Discipline="CT" Code="CTM402000"><Language Description="Men's Team Pursuit" Language="ENG"></Language><Language Description="Poursuite par équipes - hommes" Language="FRA"></Language><Language Description="Perseguição por equipes masculina" Language="POR"></Language><Language Description="Persecución por equipos masculino" Language="SPA"></Language></CodeSet><CodeSet Event="001" Gender="W" Order="6" Discipline="CT" Code="CTW001900"><Language Description="Women's 200m Flying Start" Language="ENG"></Language><Language Description="Vitesse départ lancé - femmes" Language="FRA"></Language><Language Description="Velocidade feminina" Language="POR"></Language><Language Description="Femenino, 200m salida lanzada" Language="SPA"></Language></CodeSet><CodeSet Event="010" Gender="W" Order="7" Discipline="CT" Code="CTW010300"><Language Description="Women's 500m Time Trial" Language="ENG"></Language><Language Description="Fem., contre-la-montre (500 m)" Language="FRA"></Language><Language Description="Omnium feminino, contrarrelógio de 500m" Language="POR"></Language><Language Description="Femenino, 500m contrarreloj" Language="SPA"></Language></CodeSet><CodeSet Event="010" Gender="W" Order="8" Discipline="CT" Code="CTW010500"><Language Description="Women's 3km Individual Pursuit" Language="ENG"></Language><Language Description="Fem., poursuite ind. (3 km)" Language="FRA"></Language><Language Description="Perseguição individual feminina (3km)" Language="POR"></Language><Language Description="Femenino, 3km persecución individual" Language="SPA"></Language></CodeSet><CodeSet Event="401" Gender="W" Order="9" Discipline="CT" Code="CTW401000"><Language Description="Women's Team Sprint" Language="ENG"></Language><Language Description="Vitesse par équipes - femmes" Language="FRA"></Language><Language Description="Velocidade por equipes feminina" Language="POR"></Language><Language Description="Velocidad por equipos femenino" Language="SPA"></Language></CodeSet><CodeSet Event="402" Gender="W" Order="10" Discipline="CT" Code="CTW402000"><Language Description="Women's Team Pursuit" Language="ENG"></Language><Language Description="Poursuite par équipes - femmes" Language="FRA"></Language><Language Description="Perseguição por equipes feminina" Language="POR"></Language><Language Description="Persecución por equipos femenino" Language="SPA"></Language></CodeSet><CodeSet Event="001" Gender="M" Order="1" Discipline="FE" Code="FEM001000"><Language Description="Men's Foil Individual" Language="ENG"></Language><Language Description="Fleuret individuel - hommes" Language="FRA"></Language><Language Description="Florete individual masculino" Language="POR"></Language><Language Description="Florete individual masculino" Language="SPA"></Language></CodeSet><CodeSet Event="002" Gender="M" Order="2" Discipline="FE" Code="FEM002000"><Language Description="Men's Épée Individual" Language="ENG"></Language><Language Description="Épée individuelle - hommes" Language="FRA"></Language><Language Description="Espada individual masculina" Language="POR"></Language><Language Description="Espada individual masculina" Language="SPA"></Language></CodeSet><CodeSet Event="003" Gender="M" Order="3" Discipline="FE" Code="FEM003000"><Language Description="Men's Sabre Individual" Language="ENG"></Language><Language Description="Sabre individuel - hommes" Language="FRA"></Language><Language Description="Sabre individual masculino" Language="POR"></Language><Language Description="Sable individual masculino" Language="SPA"></Language></CodeSet><CodeSet Event="401" Gender="M" Order="4" Discipline="FE" Code="FEM401000"><Language Description="Men's Foil Team" Language="ENG"></Language><Language Description="Fleuret par équipes - hommes" Language="FRA"></Language><Language Description="Florete por equipes masculino" Language="POR"></Language><Language Description="Florete por equipos masculino" Language="SPA"></Language></CodeSet><CodeSet Event="402" Gender="M" Order="5" Discipline="FE" Code="FEM402000"><Language Description="Men's Épée Team" Language="ENG"></Language><Language Description="Épée par équipes - hommes" Language="FRA"></Language><Language Description="Espada por equipes masculina" Language="POR"></Language><Language Description="Espada por equipos masculina" Language="SPA"></Language></CodeSet><CodeSet Event="001" Gender="W" Order="6" Discipline="FE" Code="FEW001000"><Language Description="Women's Foil Individual" Language="ENG"></Language><Language Description="Fleuret individuel - femmes" Language="FRA"></Language><Language Description="Florete individual feminino" Language="POR"></Language><Language Description="Florete individual femenino" Language="SPA"></Language></CodeSet><CodeSet Event="002" Gender="W" Order="7" Discipline="FE" Code="FEW002000"><Language Description="Women's Épée Individual" Language="ENG"></Language><Language Description="Épée individuelle - femmes" Language="FRA"></Language><Language Description="Espada individual feminina" Language="POR"></Language><Language Description="Espada individual femenina" Language="SPA"></Language></CodeSet><CodeSet Event="003" Gender="W" Order="8" Discipline="FE" Code="FEW003000"><Language Description="Women's Sabre Individual" Language="ENG"></Language><Language Description="Sabre individuel - femmes" Language="FRA"></Language><Language Description="Sabre individual feminino" Language="POR"></Language><Language Description="Sable individual femenino" Language="SPA"></Language></CodeSet><CodeSet Event="402" Gender="W" Order="9" Discipline="FE" Code="FEW402000"><Language Description="Women's Épée Team" Language="ENG"></Language><Language Description="Épée par équipes - femmes" Language="FRA"></Language><Language Description="Espada por equipes feminino" Language="POR"></Language><Language Description="Espada por equipos femenina" Language="SPA"></Language></CodeSet><CodeSet Event="403" Gender="W" Order="10" Discipline="FE" Code="FEW403000"><Language Description="Women's Sabre Team" Language="ENG"></Language><Language Description="Sabre par équipes - femmes" Language="FRA"></Language><Language Description="Sabre por equipes feminino" Language="POR"></Language><Language Description="Sable por equipos femenino" Language="SPA"></Language></CodeSet><CodeSet Event="001" Gender="M" Order="2" Discipline="MP" Code="MPM0010000"><Language Description="Men's Overall Points" Language="ENG"></Language><Language Description="Hommes global" Language="FRA"></Language><Language Description="Masculino geral" Language="POR"></Language><Language Description="Masculino general" Language="SPA"></Language></CodeSet><CodeSet Event="001" Gender="M" Order="4" Discipline="MP" Code="MPM001A000"><Language Description="Men's Fencing Record" Language="ENG"></Language><Language Description="Épreuve d'escrime - hommes" Language="FRA"></Language><Language Description="Prova de esgrima masculina" Language="POR"></Language><Language Description="Récord Prueba de esgrima masculina" Language="SPA"></Language></CodeSet><CodeSet Event="001" Gender="M" Order="6" Discipline="MP" Code="MPM001B001"><Language Description="Men's Swimming 25m Pool" Language="ENG"></Language><Language Description="Natation piscine 25m - hommes" Language="FRA"></Language><Language Description="Natação piscina 25m masculina" Language="POR"></Language><Language Description="Natación piscina de 25m - masculino" Language="SPA"></Language></CodeSet><CodeSet Event="001" Gender="M" Order="8" Discipline="MP" Code="MPM001B002"><Language Description="Men's Swimming 50m Pool" Language="ENG"></Language><Language Description="Natation piscine 50m - hommes" Language="FRA"></Language><Language Description="Natação piscina 50m masculina" Language="POR"></Language><Language Description="Natación piscina de 50m - masculino" Language="SPA"></Language></CodeSet><CodeSet Event="001" Gender="M" Order="10" Discipline="MP" Code="MPM001D000"><Language Description="Men's Combined Running/Shooting Record" Language="ENG"></Language><Language Description="Épreuve combinée - hommes" Language="FRA"></Language><Language Description="Prova combinada masculina" Language="POR"></Language><Language Description="Récord Prueba combinada masculina" Language="SPA"></Language></CodeSet><CodeSet Event="001" Gender="W" Order="1" Discipline="MP" Code="MPW0010000"><Language Description="Women's Overall Points" Language="ENG"></Language><Language Description="Femmes global" Language="FRA"></Language><Language Description="Feminino geral" Language="POR"></Language><Language Description="Femenino general" Language="SPA"></Language></CodeSet><CodeSet Event="001" Gender="W" Order="3" Discipline="MP" Code="MPW001A000"><Language Description="Women's Fencing Record" Language="ENG"></Language><Language Description="Épreuve d'escrime - femmes" Language="FRA"></Language><Language Description="Prova de esgrima feminino" Language="POR"></Language><Language Description="Récord Prueba de esgrima femenina" Language="SPA"></Language></CodeSet><CodeSet Event="001" Gender="W" Order="5" Discipline="MP" Code="MPW001B001"><Language Description="Women's Swimming 25m Pool" Language="ENG"></Language><Language Description="Natation piscine 25m - femmes" Language="FRA"></Language><Language Description="Natação piscina 25m feminina" Language="POR"></Language><Language Description="Natación piscina de 25m - femenino" Language="SPA"></Language></CodeSet><CodeSet Event="001" Gender="W" Order="7" Discipline="MP" Code="MPW001B002"><Language Description="Women's Swimming 50m Pool" Language="ENG"></Language><Language Description="Natation piscine 50m - femmes" Language="FRA"></Language><Language Description="Natação piscina 50m feminina" Language="POR"></Language><Language Description="Natación piscina de 50m - femenino" Language="SPA"></Language></CodeSet><CodeSet Event="001" Gender="W" Order="9" Discipline="MP" Code="MPW001D000"><Language Description="Women's Combined Running/Shooting Record" Language="ENG"></Language><Language Description="Épreuve combinée - femmes" Language="FRA"></Language><Language Description="Prova combinada - feminino" Language="POR"></Language><Language Description="Récord Prueba combinada femenina" Language="SPA"></Language></CodeSet><CodeSet Event="012" Gender="M" Order="7" Discipline="RO" Code="ROM012000"><Language Description="Men's Single Sculls" Language="ENG"></Language><Language Description="Un rameur, skiff - hommes" Language="FRA"></Language><Language Description="Single-skiff masculino" Language="POR"></Language><Language Description="Un par de remos cortos masculino" Language="SPA"></Language></CodeSet><CodeSet Event="021" Gender="M" Order="2" Discipline="RO" Code="ROM021000"><Language Description="Men's Pair" Language="ENG"></Language><Language Description="Deux en pointe - hommes" Language="FRA"></Language><Language Description="Dois sem masculino" Language="POR"></Language><Language Description="Dos sin timonel masculino" Language="SPA"></Language></CodeSet><CodeSet Event="022" Gender="M" Order="4" Discipline="RO" Code="ROM022000"><Language Description="Men's Double Sculls" Language="ENG"></Language><Language Description="Deux en couple - hommes" Language="FRA"></Language><Language Description="Double-skiff masculino" Language="POR"></Language><Language Description="Doble par de remos cortos masculino" Language="SPA"></Language></CodeSet><CodeSet Event="041" Gender="M" Order="5" Discipline="RO" Code="ROM041000"><Language Description="Men's Four" Language="ENG"></Language><Language Description="Quatre en pointe - hommes" Language="FRA"></Language><Language Description="Quatro sem masculino" Language="POR"></Language><Language Description="Cuatro sin timonel masculino" Language="SPA"></Language></CodeSet><CodeSet Event="042" Gender="M" Order="12" Discipline="RO" Code="ROM042000"><Language Description="Men's Quadruple Sculls" Language="ENG"></Language><Language Description="Quatre en couple - hommes" Language="FRA"></Language><Language Description="Four-skiff masculino" Language="POR"></Language><Language Description="Cuatro pares de remos cortos masculino" Language="SPA"></Language></CodeSet><CodeSet Event="083" Gender="M" Order="14" Discipline="RO" Code="ROM083000"><Language Description="Men's Eight" Language="ENG"></Language><Language Description="Huit en pointe - hommes" Language="FRA"></Language><Language Description="Oito com masculino" Language="POR"></Language><Language Description="Ocho con timonel masculino" Language="SPA"></Language></CodeSet><CodeSet Event="122" Gender="M" Order="9" Discipline="RO" Code="ROM122000"><Language Description="Lightweight Men's Double Sculls" Language="ENG"></Language><Language Description="Deux en couple poids légers - hommes" Language="FRA"></Language><Language Description="Double-skiff peso leve masculino" Language="POR"></Language><Language Description="Doble par remos cortos ligero masculino" Language="SPA"></Language></CodeSet><CodeSet Event="141" Gender="M" Order="10" Discipline="RO" Code="ROM141000"><Language Description="Lightweight Men's Four" Language="ENG"></Language><Language Description="Quatre en pointe poids légers - hommes" Language="FRA"></Language><Language Description="Quatro sem peso leve masculino" Language="POR"></Language><Language Description="Cuatro sin timonel ligero masculino" Language="SPA"></Language></CodeSet><CodeSet Event="012" Gender="W" Order="6" Discipline="RO" Code="ROW012000"><Language Description="Women's Single Sculls" Language="ENG"></Language><Language Description="Un rameur, skiff - femmes" Language="FRA"></Language><Language Description="Single-skiff feminino" Language="POR"></Language><Language Description="Un par de remos cortos femenino" Language="SPA"></Language></CodeSet><CodeSet Event="021" Gender="W" Order="1" Discipline="RO" Code="ROW021000"><Language Description="Women's Pair" Language="ENG"></Language><Language Description="Deux en pointe - femmes" Language="FRA"></Language><Language Description="Dois sem feminino" Language="POR"></Language><Language Description="Dos sin timonel femenino" Language="SPA"></Language></CodeSet><CodeSet Event="022" Gender="W" Order="3" Discipline="RO" Code="ROW022000"><Language Description="Women's Double Sculls" Language="ENG"></Language><Language Description="Deux en couple - femmes" Language="FRA"></Language><Language Description="Double-skiff feminino" Language="POR"></Language><Language Description="Doble par de remos cortos femenino" Language="SPA"></Language></CodeSet><CodeSet Event="042" Gender="W" Order="11" Discipline="RO" Code="ROW042000"><Language Description="Women's Quadruple Sculls" Language="ENG"></Language><Language Description="Quatre en couple - femmes" Language="FRA"></Language><Language Description="Four-skiff feminino" Language="POR"></Language><Language Description="Cuatro pares de remos cortos femenino" Language="SPA"></Language></CodeSet><CodeSet Event="083" Gender="W" Order="13" Discipline="RO" Code="ROW083000"><Language Description="Women's Eight" Language="ENG"></Language><Language Description="Huit en pointe - femmes" Language="FRA"></Language><Language Description="Oito com feminino" Language="POR"></Language><Language Description="Ocho con timonel femenino" Language="SPA"></Language></CodeSet><CodeSet Event="122" Gender="W" Order="8" Discipline="RO" Code="ROW122000"><Language Description="Lightweight Women's Double Sculls" Language="ENG"></Language><Language Description="Deux en couple poids légers - femmes" Language="FRA"></Language><Language Description="Double-skiff peso leve feminino" Language="POR"></Language><Language Description="Doble par remos cortos ligero femenino" Language="SPA"></Language></CodeSet><CodeSet Event="101" Gender="M" Order="5" Discipline="SH" Code="SHM101000"><Language Description="10m Air Rifle Men" Language="ENG"></Language><Language Description="10 m rifle à air - hommes" Language="FRA"></Language><Language Description="Carabina de ar 10m masculina" Language="POR"></Language><Language Description="10m rifle de aire masculino" Language="SPA"></Language></CodeSet><CodeSet Event="101" Gender="M" Order="6" Discipline="SH" Code="SHM101100"><Language Description="10m Air Rifle Men's Finals" Language="ENG"></Language><Language Description="10 m rifle à air - hommes, finale" Language="FRA"></Language><Language Description="Carabina de ar 10m masculina, finais" Language="POR"></Language><Language Description="10m rifle de aire masc, finales" Language="SPA"></Language></CodeSet><CodeSet Event="103" Gender="M" Order="3" Discipline="SH" Code="SHM103000"><Language Description="50m Rifle Prone Men" Language="ENG"></Language><Language Description="50 m rifle couché - hommes" Language="FRA"></Language><Language Description="Carabina deitado 50m masculina" Language="POR"></Language><Language Description="50m rifle tendido masculino" Language="SPA"></Language></CodeSet><CodeSet Event="103" Gender="M" Order="4" Discipline="SH" Code="SHM103100"><Language Description="50m Rifle Prone Men's Finals" Language="ENG"></Language><Language Description="50 m rifle couché - hommes, finale" Language="FRA"></Language><Language Description="Carabina deitado 50m masculina, finais" Language="POR"></Language><Language Description="50m rifle tendido masc, finales" Language="SPA"></Language></CodeSet><CodeSet Event="104" Gender="M" Order="1" Discipline="SH" Code="SHM104000"><Language Description="50m Rifle 3 Positions Men" Language="ENG"></Language><Language Description="50 m rifle 3 positions - hommes" Language="FRA"></Language><Language Description="Carabina três posições 50m masculina" Language="POR"></Language><Language Description="50m rifle 3 posiciones masculino" Language="SPA"></Language></CodeSet><CodeSet Event="104" Gender="M" Order="2" Discipline="SH" Code="SHM104100"><Language Description="50m Rifle 3 Positions Men's Finals" Language="ENG"></Language><Language Description="50 m rifle 3 positions - hommes, finale" Language="FRA"></Language><Language Description="Carabina três posições 50m masculina, fi" Language="POR"></Language><Language Description="50m rifle 3 pos. masc, finales" Language="SPA"></Language></CodeSet><CodeSet Event="201" Gender="M" Order="7" Discipline="SH" Code="SHM201000"><Language Description="50m Pistol Men" Language="ENG"></Language><Language Description="50 m pistolet - hommes" Language="FRA"></Language><Language Description="Pistola 50m masculina" Language="POR"></Language><Language Description="50m pistola masculino" Language="SPA"></Language></CodeSet><CodeSet Event="201" Gender="M" Order="8" Discipline="SH" Code="SHM201100"><Language Description="50m Pistol Men's Finals" Language="ENG"></Language><Language Description="50 m pistolet - hommes, finale" Language="FRA"></Language><Language Description="Pistola 50m masculina, finais" Language="POR"></Language><Language Description="50m pistola masculino, finales" Language="SPA"></Language></CodeSet><CodeSet Event="202" Gender="M" Order="9" Discipline="SH" Code="SHM202000"><Language Description="25m Rapid Fire Pistol Men" Language="ENG"></Language><Language Description="25 m pistolet feu rapide - hommes" Language="FRA"></Language><Language Description="Pistola de tiro rápido 25m masculina" Language="POR"></Language><Language Description="25m pistola tiro rápido masculino" Language="SPA"></Language></CodeSet><CodeSet Event="202" Gender="M" Order="10" Discipline="SH" Code="SHM202100"><Language Description="25m Rapid Fire Pistol Men's Finals" Language="ENG"></Language><Language Description="25 m pistolet feu rapide - hom., finale" Language="FRA"></Language><Language Description="Pistola de tiro rápido 25m masculina, fi" Language="POR"></Language><Language Description="25m pist tiro rápido masc, finales" Language="SPA"></Language></CodeSet><CodeSet Event="203" Gender="M" Order="11" Discipline="SH" Code="SHM203000"><Language Description="10m Air Pistol Men" Language="ENG"></Language><Language Description="10 m pistolet à air - hommes" Language="FRA"></Language><Language Description="Pistola de ar 10m masculina" Language="POR"></Language><Language Description="10m pistola de aire masculino" Language="SPA"></Language></CodeSet><CodeSet Event="203" Gender="M" Order="12" Discipline="SH" Code="SHM203100"><Language Description="10m Air Pistol Men's Finals" Language="ENG"></Language><Language Description="10 m pistolet à air - hommes, finale" Language="FRA"></Language><Language Description="Pistola de ar 10m masculina, finais" Language="POR"></Language><Language Description="10m pistola de aire masc, finales" Language="SPA"></Language></CodeSet><CodeSet Event="401" Gender="M" Order="13" Discipline="SH" Code="SHM401000"><Language Description="Trap Men" Language="ENG"></Language><Language Description="Fosse olympique - hommes" Language="FRA"></Language><Language Description="Fossa olímpica masculina" Language="POR"></Language><Language Description="Fosa masculino" Language="SPA"></Language></CodeSet><CodeSet Event="402" Gender="M" Order="14" Discipline="SH" Code="SHM402000"><Language Description="Double Trap Men" Language="ENG"></Language><Language Description="Double trap - hommes" Language="FRA"></Language><Language Description="Fossa double masculina" Language="POR"></Language><Language Description="Doble fosa masculino" Language="SPA"></Language></CodeSet><CodeSet Event="403" Gender="M" Order="15" Discipline="SH" Code="SHM403000"><Language Description="Skeet Men" Language="ENG"></Language><Language Description="Skeet - hommes" Language="FRA"></Language><Language Description="Skeet masculino" Language="POR"></Language><Language Description="Skeet masculino" Language="SPA"></Language></CodeSet><CodeSet Event="101" Gender="W" Order="18" Discipline="SH" Code="SHW101000"><Language Description="10m Air Rifle Women" Language="ENG"></Language><Language Description="10 m rifle à air - femmes" Language="FRA"></Language><Language Description="Carabina de ar 10m feminina" Language="POR"></Language><Language Description="10m rifle de aire femenino" Language="SPA"></Language></CodeSet><CodeSet Event="101" Gender="W" Order="19" Discipline="SH" Code="SHW101100"><Language Description="10m Air Rifle Women's Finals" Language="ENG"></Language><Language Description="10 m rifle à air - femmes, finale" Language="FRA"></Language><Language Description="Carabina de ar 10m feminina, finais" Language="POR"></Language><Language Description="10m rifle de aire fem, finales" Language="SPA"></Language></CodeSet><CodeSet Event="104" Gender="W" Order="16" Discipline="SH" Code="SHW104000"><Language Description="50m Rifle 3 Positions Women" Language="ENG"></Language><Language Description="50 m rifle 3 positions - femmes" Language="FRA"></Language><Language Description="Carabina três posições 50m feminina" Language="POR"></Language><Language Description="50m rifle 3 posiciones femenino" Language="SPA"></Language></CodeSet><CodeSet Event="104" Gender="W" Order="17" Discipline="SH" Code="SHW104100"><Language Description="50m Rifle 3 Positions Women's Finals" Language="ENG"></Language><Language Description="50 m rifle 3 positions - femmes, finale" Language="FRA"></Language><Language Description="Carabina três posições 50m feminina, fin" Language="POR"></Language><Language Description="50m rifle 3 pos. fem, finales" Language="SPA"></Language></CodeSet><CodeSet Event="203" Gender="W" Order="21" Discipline="SH" Code="SHW203000"><Language Description="10m Air Pistol Women" Language="ENG"></Language><Language Description="10 m pistolet à air - femmes" Language="FRA"></Language><Language Description="Pistola de ar 10m feminina" Language="POR"></Language><Language Description="10m pistola de aire femenino" Language="SPA"></Language></CodeSet><CodeSet Event="203" Gender="W" Order="22" Discipline="SH" Code="SHW203100"><Language Description="10m Air Pistol Women's Finals" Language="ENG"></Language><Language Description="10 m pistolet à air - femmes, finale" Language="FRA"></Language><Language Description="Pistola de ar 10m feminina, final" Language="POR"></Language><Language Description="10m pistola de aire fem, finales" Language="SPA"></Language></CodeSet><CodeSet Event="204" Gender="W" Order="20" Discipline="SH" Code="SHW204000"><Language Description="25m Pistol Women" Language="ENG"></Language><Language Description="25 m pistolet - femmes" Language="FRA"></Language><Language Description="Pistola 25m feminina" Language="POR"></Language><Language Description="25m pistola femenino" Language="SPA"></Language></CodeSet><CodeSet Event="401" Gender="W" Order="23" Discipline="SH" Code="SHW401000"><Language Description="Trap Women" Language="ENG"></Language><Language Description="Trap - femmes" Language="FRA"></Language><Language Description="Fossa olímpica feminina" Language="POR"></Language><Language Description="Fosa femenino" Language="SPA"></Language></CodeSet><CodeSet Event="403" Gender="W" Order="24" Discipline="SH" Code="SHW403000"><Language Description="Skeet Women" Language="ENG"></Language><Language Description="Skeet - femmes" Language="FRA"></Language><Language Description="Skeet feminino" Language="POR"></Language><Language Description="Skeet femenino" Language="SPA"></Language></CodeSet><CodeSet Event="010" Gender="M" Order="20" Discipline="SW" Code="SWM010000"><Language Description="Men's 50m Freestyle" Language="ENG"></Language><Language Description="50 m nage libre - hommes" Language="FRA"></Language><Language Description="50m livre masculino" Language="POR"></Language><Language Description="50m estilo libre masculino" Language="SPA"></Language></CodeSet><CodeSet Event="011" Gender="M" Order="21" Discipline="SW" Code="SWM011000"><Language Description="Men's 100m Freestyle" Language="ENG"></Language><Language Description="100 m nage libre - hommes" Language="FRA"></Language><Language Description="100m livre masculino" Language="POR"></Language><Language Description="100m estilo libre masculino" Language="SPA"></Language></CodeSet><CodeSet Event="012" Gender="M" Order="22" Discipline="SW" Code="SWM012000"><Language Description="Men's 200m Freestyle" Language="ENG"></Language><Language Description="200 m nage libre - hommes" Language="FRA"></Language><Language Description="200m livre masculino" Language="POR"></Language><Language Description="200m estilo libre masculino" Language="SPA"></Language></CodeSet><CodeSet Event="014" Gender="M" Order="23" Discipline="SW" Code="SWM014000"><Language Description="Men's 400m Freestyle" Language="ENG"></Language><Language Description="400 m nage libre - hommes" Language="FRA"></Language><Language Description="400m livre masculino" Language="POR"></Language><Language Description="400m estilo libre masculino" Language="SPA"></Language></CodeSet><CodeSet Event="015" Gender="M" Order="25" Discipline="SW" Code="SWM015000"><Language Description="Men's 1500m Freestyle" Language="ENG"></Language><Language Description="1 500 m nage libre - hommes" Language="FRA"></Language><Language Description="1.500m livre masculino" Language="POR"></Language><Language Description="1500m estilo libre masculino" Language="SPA"></Language></CodeSet><CodeSet Event="015" Gender="M" Order="24" Discipline="SW" Code="SWM018000"><Language Description="Men's 800m Freestyle" Language="ENG"></Language><Language Description="800 m nage libre - hommes" Language="FRA"></Language><Language Description="800m livre masculino" Language="POR"></Language><Language Description="800m estilo libre masculino" Language="SPA"></Language></CodeSet><CodeSet Event="021" Gender="M" Order="32" Discipline="SW" Code="SWM020000"><Language Description="Men's 50m Butterfly" Language="ENG"></Language><Language Description="50 m papillon - hommes" Language="FRA"></Language><Language Description="50m borboleta masculino" Language="POR"></Language><Language Description="50m mariposa masculino" Language="SPA"></Language></CodeSet><CodeSet Event="021" Gender="M" Order="33" Discipline="SW" Code="SWM021000"><Language Description="Men's 100m Butterfly" Language="ENG"></Language><Language Description="100 m papillon - hommes" Language="FRA"></Language><Language Description="100m borboleta masculino" Language="POR"></Language><Language Description="100m mariposa masculino" Language="SPA"></Language></CodeSet><CodeSet Event="022" Gender="M" Order="34" Discipline="SW" Code="SWM022000"><Language Description="Men's 200m Butterfly" Language="ENG"></Language><Language Description="200 m papillon - hommes" Language="FRA"></Language><Language Description="200m borboleta masculino" Language="POR"></Language><Language Description="200m mariposa masculino" Language="SPA"></Language></CodeSet><CodeSet Event="031" Gender="M" Order="29" Discipline="SW" Code="SWM030000"><Language Description="Men's 50m Breaststroke" Language="ENG"></Language><Language Description="50 m brasse - hommes" Language="FRA"></Language><Language Description="50m peito masculino" Language="POR"></Language><Language Description="50m braza masculino" Language="SPA"></Language></CodeSet><CodeSet Event="031" Gender="M" Order="30" Discipline="SW" Code="SWM031000"><Language Description="Men's 100m Breaststroke" Language="ENG"></Language><Language Description="100 m brasse - hommes" Language="FRA"></Language><Language Description="100m peito masculino" Language="POR"></Language><Language Description="100m braza masculino" Language="SPA"></Language></CodeSet><CodeSet Event="032" Gender="M" Order="31" Discipline="SW" Code="SWM032000"><Language Description="Men's 200m Breaststroke" Language="ENG"></Language><Language Description="200 m brasse - hommes" Language="FRA"></Language><Language Description="200m peito masculino" Language="POR"></Language><Language Description="200m braza masculino" Language="SPA"></Language></CodeSet><CodeSet Event="041" Gender="M" Order="26" Discipline="SW" Code="SWM040000"><Language Description="Men's 50m Backstroke" Language="ENG"></Language><Language Description="50 m dos - hommes" Language="FRA"></Language><Language Description="50m costas masculino" Language="POR"></Language><Language Description="50m espalda masculino" Language="SPA"></Language></CodeSet><CodeSet Event="041" Gender="M" Order="27" Discipline="SW" Code="SWM041000"><Language Description="Men's 100m Backstroke" Language="ENG"></Language><Language Description="100 m dos - hommes" Language="FRA"></Language><Language Description="100m costas masculino" Language="POR"></Language><Language Description="100m espalda masculino" Language="SPA"></Language></CodeSet><CodeSet Event="042" Gender="M" Order="28" Discipline="SW" Code="SWM042000"><Language Description="Men's 200m Backstroke" Language="ENG"></Language><Language Description="200 m dos - hommes" Language="FRA"></Language><Language Description="200m costas masculino" Language="POR"></Language><Language Description="200m espalda masculino" Language="SPA"></Language></CodeSet><CodeSet Event="052" Gender="M" Order="35" Discipline="SW" Code="SWM052000"><Language Description="Men's 200m Individual Medley" Language="ENG"></Language><Language Description="200 m quatre nages individuel - hommes" Language="FRA"></Language><Language Description="200m medley masculino" Language="POR"></Language><Language Description="200m combinado individual masculino" Language="SPA"></Language></CodeSet><CodeSet Event="054" Gender="M" Order="36" Discipline="SW" Code="SWM054000"><Language Description="Men's 400m Individual Medley" Language="ENG"></Language><Language Description="400 m quatre nages individuel - hommes" Language="FRA"></Language><Language Description="400m medley masculino" Language="POR"></Language><Language Description="400m combinado individual masculino" Language="SPA"></Language></CodeSet><CodeSet Event="411" Gender="M" Order="37" Discipline="SW" Code="SWM411000"><Language Description="Men's 4 x 100m Freestyle Relay" Language="ENG"></Language><Language Description="Relais 4x100 m nage libre - hommes" Language="FRA"></Language><Language Description="Revezamento 4x100m livre masculino" Language="POR"></Language><Language Description="Relevo 4x100m estilo libre masculino" Language="SPA"></Language></CodeSet><CodeSet Event="412" Gender="M" Order="38" Discipline="SW" Code="SWM412000"><Language Description="Men's 4 x 200m Freestyle Relay" Language="ENG"></Language><Language Description="Relais 4x200 m nage libre - hommes" Language="FRA"></Language><Language Description="Revezamento 4x200m livre masculino" Language="POR"></Language><Language Description="Relevo 4x200m estilo libre masculino" Language="SPA"></Language></CodeSet><CodeSet Event="451" Gender="M" Order="39" Discipline="SW" Code="SWM451000"><Language Description="Men's 4 x 100m Medley Relay" Language="ENG"></Language><Language Description="Relais 4x100 m quatre nages - hommes" Language="FRA"></Language><Language Description="Revezamento 4x100m medley masculino" Language="POR"></Language><Language Description="Relevo 4x100m combinado masculino" Language="SPA"></Language></CodeSet><CodeSet Event="010" Gender="W" Order="1" Discipline="SW" Code="SWW010000"><Language Description="Women's 50m Freestyle" Language="ENG"></Language><Language Description="50 m nage libre - femmes" Language="FRA"></Language><Language Description="50m livre feminino" Language="POR"></Language><Language Description="50m estilo libre femenino" Language="SPA"></Language></CodeSet><CodeSet Event="011" Gender="W" Order="2" Discipline="SW" Code="SWW011000"><Language Description="Women's 100m Freestyle" Language="ENG"></Language><Language Description="100 m nage libre - femmes" Language="FRA"></Language><Language Description="100m livre feminino" Language="POR"></Language><Language Description="100m estilo libre femenino" Language="SPA"></Language></CodeSet><CodeSet Event="012" Gender="W" Order="3" Discipline="SW" Code="SWW012000"><Language Description="Women's 200m Freestyle" Language="ENG"></Language><Language Description="200 m nage libre - femmes" Language="FRA"></Language><Language Description="200m livre feminino" Language="POR"></Language><Language Description="200m estilo libre femenino" Language="SPA"></Language></CodeSet><CodeSet Event="014" Gender="W" Order="4" Discipline="SW" Code="SWW014000"><Language Description="Women's 400m Freestyle" Language="ENG"></Language><Language Description="400 m nage libre - femmes" Language="FRA"></Language><Language Description="400m livre feminino" Language="POR"></Language><Language Description="400m estilo libre femenino" Language="SPA"></Language></CodeSet><CodeSet Event="018" Gender="W" Order="5" Discipline="SW" Code="SWW018000"><Language Description="Women's 800m Freestyle" Language="ENG"></Language><Language Description="800 m nage libre - femmes" Language="FRA"></Language><Language Description="800m livre feminino" Language="POR"></Language><Language Description="800m estilo libre femenino" Language="SPA"></Language></CodeSet><CodeSet Event="021" Gender="W" Order="12" Discipline="SW" Code="SWW020000"><Language Description="Women's 50m Butterfly" Language="ENG"></Language><Language Description="50 m papillon - femmes" Language="FRA"></Language><Language Description="50m borboleta feminino" Language="POR"></Language><Language Description="50m mariposa femenino" Language="SPA"></Language></CodeSet><CodeSet Event="021" Gender="W" Order="13" Discipline="SW" Code="SWW021000"><Language Description="Women's 100m Butterfly" Language="ENG"></Language><Language Description="100 m papillon - femmes" Language="FRA"></Language><Language Description="100m borboleta feminino" Language="POR"></Language><Language Description="100m mariposa femenino" Language="SPA"></Language></CodeSet><CodeSet Event="022" Gender="W" Order="14" Discipline="SW" Code="SWW022000"><Language Description="Women's 200m Butterfly" Language="ENG"></Language><Language Description="200 m papillon - femmes" Language="FRA"></Language><Language Description="200m borboleta feminino" Language="POR"></Language><Language Description="200m mariposa femenino" Language="SPA"></Language></CodeSet><CodeSet Event="031" Gender="W" Order="9" Discipline="SW" Code="SWW030000"><Language Description="Women's 50m Breaststroke" Language="ENG"></Language><Language Description="50 m brasse - femmes" Language="FRA"></Language><Language Description="50m peito feminino" Language="POR"></Language><Language Description="50m braza femenino" Language="SPA"></Language></CodeSet><CodeSet Event="031" Gender="W" Order="10" Discipline="SW" Code="SWW031000"><Language Description="Women's 100m Breaststroke" Language="ENG"></Language><Language Description="100 m brasse - femmes" Language="FRA"></Language><Language Description="100m peito feminino" Language="POR"></Language><Language Description="100m braza femenino" Language="SPA"></Language></CodeSet><CodeSet Event="032" Gender="W" Order="11" Discipline="SW" Code="SWW032000"><Language Description="Women's 200m Breaststroke" Language="ENG"></Language><Language Description="200 m brasse - femmes" Language="FRA"></Language><Language Description="200m peito feminino" Language="POR"></Language><Language Description="200m braza femenino" Language="SPA"></Language></CodeSet><CodeSet Event="041" Gender="W" Order="6" Discipline="SW" Code="SWW040000"><Language Description="Women's 50m Backstroke" Language="ENG"></Language><Language Description="50 m dos - femmes" Language="FRA"></Language><Language Description="50m costas feminino" Language="POR"></Language><Language Description="50m espalda femenino" Language="SPA"></Language></CodeSet><CodeSet Event="041" Gender="W" Order="7" Discipline="SW" Code="SWW041000"><Language Description="Women's 100m Backstroke" Language="ENG"></Language><Language Description="100 m dos - femmes" Language="FRA"></Language><Language Description="100m costas feminino" Language="POR"></Language><Language Description="100m espalda femenino" Language="SPA"></Language></CodeSet><CodeSet Event="042" Gender="W" Order="8" Discipline="SW" Code="SWW042000"><Language Description="Women's 200m Backstroke" Language="ENG"></Language><Language Description="200 m dos - femmes" Language="FRA"></Language><Language Description="200m costas feminino" Language="POR"></Language><Language Description="200m espalda femenino" Language="SPA"></Language></CodeSet><CodeSet Event="052" Gender="W" Order="15" Discipline="SW" Code="SWW052000"><Language Description="Women's 200m Individual Medley" Language="ENG"></Language><Language Description="200 m 4 nages individuel - femmes" Language="FRA"></Language><Language Description="200m medley feminino" Language="POR"></Language><Language Description="200m combinado individual femenino" Language="SPA"></Language></CodeSet><CodeSet Event="054" Gender="W" Order="16" Discipline="SW" Code="SWW054000"><Language Description="Women's 400m Individual Medley" Language="ENG"></Language><Language Description="400 m 4 nages individuel - femmes" Language="FRA"></Language><Language Description="400m medley feminino" Language="POR"></Language><Language Description="400m combinado individual femenino" Language="SPA"></Language></CodeSet><CodeSet Event="411" Gender="W" Order="17" Discipline="SW" Code="SWW411000"><Language Description="Women's 4 x 100m Freestyle Relay" Language="ENG"></Language><Language Description="Relais 4x100 m nage libre - femmes" Language="FRA"></Language><Language Description="Revezamento 4x100m livre feminino" Language="POR"></Language><Language Description="Relevo 4x100m estilo libre femenino" Language="SPA"></Language></CodeSet><CodeSet Event="412" Gender="W" Order="18" Discipline="SW" Code="SWW412000"><Language Description="Women's 4 x 200m Freestyle Relay" Language="ENG"></Language><Language Description="Relais 4x200 m nage libre - femmes" Language="FRA"></Language><Language Description="Revezamento 4x200m livre feminino" Language="POR"></Language><Language Description="Relevo 4x200m estilo libre femenino" Language="SPA"></Language></CodeSet><CodeSet Event="451" Gender="W" Order="19" Discipline="SW" Code="SWW451000"><Language Description="Women's 4 x 100m Medley Relay" Language="ENG"></Language><Language Description="Relais 4x100 m quatre nages - femmes" Language="FRA"></Language><Language Description="Revezamento 4x100m medley feminino" Language="POR"></Language><Language Description="Relevo 4x100m combinado femenino" Language="SPA"></Language></CodeSet><CodeSet Event="005" Gender="M" Order="42" Discipline="WL" Code="WLM005000"><Language Description="Men's 105kg - Total" Language="ENG"></Language><Language Description="Jusqu'à 105 kg - hommes, total" Language="FRA"></Language><Language Description="Até 105kg masculino, total" Language="POR"></Language><Language Description="105kg masculino, total" Language="SPA"></Language></CodeSet><CodeSet Event="025" Gender="M" Order="45" Discipline="WL" Code="WLM025000"><Language Description="Men's +105kg - Total" Language="ENG"></Language><Language Description="+105 kg - hommes, total" Language="FRA"></Language><Language Description="Acima de 105kg masculino, total" Language="POR"></Language><Language Description="+105kg masculino, total" Language="SPA"></Language></CodeSet><CodeSet Event="056" Gender="M" Order="24" Discipline="WL" Code="WLM056000"><Language Description="Men's 56kg - Total" Language="ENG"></Language><Language Description="Jusqu'à 56 kg - hommes, total" Language="FRA"></Language><Language Description="Até 56kg masculino, total" Language="POR"></Language><Language Description="56kg masculino, total" Language="SPA"></Language></CodeSet><CodeSet Event="062" Gender="M" Order="27" Discipline="WL" Code="WLM062000"><Language Description="Men's 62kg - Total" Language="ENG"></Language><Language Description="Jusqu'à 62 kg - hommes, total" Language="FRA"></Language><Language Description="Até 62kg masculino, total" Language="POR"></Language><Language Description="62kg masculino, total" Language="SPA"></Language></CodeSet><CodeSet Event="069" Gender="M" Order="30" Discipline="WL" Code="WLM069000"><Language Description="Men's 69kg - Total" Language="ENG"></Language><Language Description="Jusqu'à 69 kg - hommes, total" Language="FRA"></Language><Language Description="Até 69kg masculino, total" Language="POR"></Language><Language Description="69kg masculino, total" Language="SPA"></Language></CodeSet><CodeSet Event="077" Gender="M" Order="33" Discipline="WL" Code="WLM077000"><Language Description="Men's 77kg - Total" Language="ENG"></Language><Language Description="Jusqu'à 77 kg - hommes, total" Language="FRA"></Language><Language Description="Até 77kg masculino, total" Language="POR"></Language><Language Description="77kg masculino, total" Language="SPA"></Language></CodeSet><CodeSet Event="085" Gender="M" Order="36" Discipline="WL" Code="WLM085000"><Language Description="Men's 85kg - Total" Language="ENG"></Language><Language Description="Jusqu'à 85 kg - hommes, total" Language="FRA"></Language><Language Description="Até 85kg masculino, total" Language="POR"></Language><Language Description="85kg masculino, total" Language="SPA"></Language></CodeSet><CodeSet Event="094" Gender="M" Order="39" Discipline="WL" Code="WLM094000"><Language Description="Men's 94kg - Total" Language="ENG"></Language><Language Description="Jusqu'à 94 kg - hommes, total" Language="FRA"></Language><Language Description="Até 94kg masculino, total" Language="POR"></Language><Language Description="94kg masculino, total" Language="SPA"></Language></CodeSet><CodeSet Event="005" Gender="M" Order="40" Discipline="WL" Code="WLM105000"><Language Description="Men's 105kg - Snatch" Language="ENG"></Language><Language Description="Jusqu'à 105 kg - hommes, arraché" Language="FRA"></Language><Language Description="Até 105kg masculino, arranco" Language="POR"></Language><Language Description="105kg masculino, arrancada" Language="SPA"></Language></CodeSet><CodeSet Event="025" Gender="M" Order="43" Discipline="WL" Code="WLM125000"><Language Description="Men's +105kg - Snatch" Language="ENG"></Language><Language Description="+105 kg - hommes, arraché" Language="FRA"></Language><Language Description="Acima de 105kg masculino, arranco" Language="POR"></Language><Language Description="+105kg masculino, arrancada" Language="SPA"></Language></CodeSet><CodeSet Event="056" Gender="M" Order="22" Discipline="WL" Code="WLM156000"><Language Description="Men's 56kg - Snatch" Language="ENG"></Language><Language Description="Jusqu'à 56 kg - hommes, arraché" Language="FRA"></Language><Language Description="Até 56kg masculino, arranco" Language="POR"></Language><Language Description="56kg masculino, arrancada" Language="SPA"></Language></CodeSet><CodeSet Event="062" Gender="M" Order="25" Discipline="WL" Code="WLM162000"><Language Description="Men's 62kg - Snatch" Language="ENG"></Language><Language Description="Jusqu'à 62 kg - hommes, arraché" Language="FRA"></Language><Language Description="Até 62kg masculino, arranco" Language="POR"></Language><Language Description="62kg masculino, arrancada" Language="SPA"></Language></CodeSet><CodeSet Event="069" Gender="M" Order="28" Discipline="WL" Code="WLM169000"><Language Description="Men's 69kg - Snatch" Language="ENG"></Language><Language Description="Jusqu'à 69 kg - hommes, arraché" Language="FRA"></Language><Language Description="Até 69kg masculino, arranco" Language="POR"></Language><Language Description="69kg masculino, arrancada" Language="SPA"></Language></CodeSet><CodeSet Event="077" Gender="M" Order="31" Discipline="WL" Code="WLM177000"><Language Description="Men's 77kg - Snatch" Language="ENG"></Language><Language Description="Jusqu'à 77 kg - hommes, arraché" Language="FRA"></Language><Language Description="Até 77kg masculino, arranco" Language="POR"></Language><Language Description="77kg masculino, arrancada" Language="SPA"></Language></CodeSet><CodeSet Event="085" Gender="M" Order="34" Discipline="WL" Code="WLM185000"><Language Description="Men's 85kg - Snatch" Language="ENG"></Language><Language Description="Jusqu'à 85 kg - hommes, arraché" Language="FRA"></Language><Language Description="Até 85kg masculino, arranco" Language="POR"></Language><Language Description="85kg masculino, arrancada" Language="SPA"></Language></CodeSet><CodeSet Event="094" Gender="M" Order="37" Discipline="WL" Code="WLM194000"><Language Description="Men's 94kg - Snatch" Language="ENG"></Language><Language Description="Jusqu'à 94 kg - hommes, arraché" Language="FRA"></Language><Language Description="Até 94kg masculino, arranco" Language="POR"></Language><Language Description="94kg masculino, arrancada" Language="SPA"></Language></CodeSet><CodeSet Event="005" Gender="M" Order="41" Discipline="WL" Code="WLM205000"><Language Description="Men's 105kg - Clean &amp; Jerk" Language="ENG"></Language><Language Description="Jusqu'à 105 kg - hommes, épaulé-jeté" Language="FRA"></Language><Language Description="Até 105kg masculino, arremesso" Language="POR"></Language><Language Description="105kg masculino, dos tiempos" Language="SPA"></Language></CodeSet><CodeSet Event="025" Gender="M" Order="44" Discipline="WL" Code="WLM225000"><Language Description="Men's +105kg - Clean &amp; Jerk" Language="ENG"></Language><Language Description="+105 kg - hommes, épaulé-jeté" Language="FRA"></Language><Language Description="Acima de 105kg masculino, arremesso" Language="POR"></Language><Language Description="+105kg masculino, dos tiempos" Language="SPA"></Language></CodeSet><CodeSet Event="056" Gender="M" Order="23" Discipline="WL" Code="WLM256000"><Language Description="Men's 56kg - Clean &amp; Jerk" Language="ENG"></Language><Language Description="Jusqu'à 56 kg - hommes, épaulé-jeté" Language="FRA"></Language><Language Description="Até 56kg masculino, arremesso" Language="POR"></Language><Language Description="56kg masculino, dos tiempos" Language="SPA"></Language></CodeSet><CodeSet Event="062" Gender="M" Order="26" Discipline="WL" Code="WLM262000"><Language Description="Men's 62kg - Clean &amp; Jerk" Language="ENG"></Language><Language Description="Jusqu'à 62 kg - hommes, épaulé-jeté" Language="FRA"></Language><Language Description="Até 62kg masculino, arremesso" Language="POR"></Language><Language Description="62kg masculino, dos tiempos" Language="SPA"></Language></CodeSet><CodeSet Event="069" Gender="M" Order="29" Discipline="WL" Code="WLM269000"><Language Description="Men's 69kg - Clean &amp; Jerk" Language="ENG"></Language><Language Description="Jusqu'à 69 kg - hommes, épaulé-jeté" Language="FRA"></Language><Language Description="Até 69kg masculino, arremesso" Language="POR"></Language><Language Description="69kg masculino, dos tiempos" Language="SPA"></Language></CodeSet><CodeSet Event="077" Gender="M" Order="32" Discipline="WL" Code="WLM277000"><Language Description="Men's 77kg - Clean &amp; Jerk" Language="ENG"></Language><Language Description="Jusqu'à 77 kg - hommes, épaulé-jeté" Language="FRA"></Language><Language Description="Até 77kg masculino, arremesso" Language="POR"></Language><Language Description="77kg masculino, dos tiempos" Language="SPA"></Language></CodeSet><CodeSet Event="085" Gender="M" Order="35" Discipline="WL" Code="WLM285000"><Language Description="Men's 85kg - Clean &amp; Jerk" Language="ENG"></Language><Language Description="Jusqu'à 85 kg - hommes, épaulé-jeté" Language="FRA"></Language><Language Description="Até 85kg masculino, arremesso" Language="POR"></Language><Language Description="85kg masculino, dos tiempos" Language="SPA"></Language></CodeSet><CodeSet Event="094" Gender="M" Order="38" Discipline="WL" Code="WLM294000"><Language Description="Men's 94kg - Clean &amp; Jerk" Language="ENG"></Language><Language Description="Jusqu'à 94 kg - hommes, épaulé-jeté" Language="FRA"></Language><Language Description="Até 94kg masculino, arremesso" Language="POR"></Language><Language Description="94kg masculino, dos tiempos" Language="SPA"></Language></CodeSet><CodeSet Event="026" Gender="W" Order="21" Discipline="WL" Code="WLW026000"><Language Description="Women's +75kg - Total" Language="ENG"></Language><Language Description="+75 kg - femmes, total" Language="FRA"></Language><Language Description="Acima de 75kg feminino, total" Language="POR"></Language><Language Description="+75kg femenino, total" Language="SPA"></Language></CodeSet><CodeSet Event="048" Gender="W" Order="3" Discipline="WL" Code="WLW048000"><Language Description="Women's 48kg - Total" Language="ENG"></Language><Language Description="Jusqu'à 48 kg - femmes, total" Language="FRA"></Language><Language Description="Até 48kg feminino, total" Language="POR"></Language><Language Description="48kg femenino, total" Language="SPA"></Language></CodeSet><CodeSet Event="053" Gender="W" Order="6" Discipline="WL" Code="WLW053000"><Language Description="Women's 53kg - Total" Language="ENG"></Language><Language Description="Jusqu'à 53 kg - femmes, total" Language="FRA"></Language><Language Description="Até 53kg feminino, total" Language="POR"></Language><Language Description="53kg femenino, total" Language="SPA"></Language></CodeSet><CodeSet Event="058" Gender="W" Order="9" Discipline="WL" Code="WLW058000"><Language Description="Women's 58kg - Total" Language="ENG"></Language><Language Description="Jusqu'à 58 kg - femmes, total" Language="FRA"></Language><Language Description="Até 58kg feminino, total" Language="POR"></Language><Language Description="58kg femenino, total" Language="SPA"></Language></CodeSet><CodeSet Event="063" Gender="W" Order="12" Discipline="WL" Code="WLW063000"><Language Description="Women's 63kg - Total" Language="ENG"></Language><Language Description="Jusqu'à 63 kg - femmes, total" Language="FRA"></Language><Language Description="Até 63kg feminino, total" Language="POR"></Language><Language Description="63kg femenino, total" Language="SPA"></Language></CodeSet><CodeSet Event="069" Gender="W" Order="15" Discipline="WL" Code="WLW069000"><Language Description="Women's 69kg - Total" Language="ENG"></Language><Language Description="Jusqu'à 69 kg - femmes, total" Language="FRA"></Language><Language Description="Até 69kg feminino, total" Language="POR"></Language><Language Description="69kg femenino, total" Language="SPA"></Language></CodeSet><CodeSet Event="075" Gender="W" Order="18" Discipline="WL" Code="WLW075000"><Language Description="Women's 75kg - Total" Language="ENG"></Language><Language Description="Jusqu'à 75 kg - femmes, total" Language="FRA"></Language><Language Description="Até 75kg feminino, total" Language="POR"></Language><Language Description="75kg femenino, total" Language="SPA"></Language></CodeSet><CodeSet Event="026" Gender="W" Order="19" Discipline="WL" Code="WLW126000"><Language Description="Women's +75kg - Snatch" Language="ENG"></Language><Language Description="+75 kg - femmes, arraché" Language="FRA"></Language><Language Description="Acima de 75kg feminino, arranco" Language="POR"></Language><Language Description="+75kg femenino, arrancada" Language="SPA"></Language></CodeSet><CodeSet Event="048" Gender="W" Order="1" Discipline="WL" Code="WLW148000"><Language Description="Women's 48kg - Snatch" Language="ENG"></Language><Language Description="Jusqu'à 48 kg - femmes, arraché" Language="FRA"></Language><Language Description="Até 48kg feminino, arranco" Language="POR"></Language><Language Description="48kg femenino, arrancada" Language="SPA"></Language></CodeSet><CodeSet Event="053" Gender="W" Order="4" Discipline="WL" Code="WLW153000"><Language Description="Women's 53kg - Snatch" Language="ENG"></Language><Language Description="Jusqu'à 53 kg - femmes, arraché" Language="FRA"></Language><Language Description="Até 53kg feminino, arranco" Language="POR"></Language><Language Description="53kg femenino, arrancada" Language="SPA"></Language></CodeSet><CodeSet Event="058" Gender="W" Order="7" Discipline="WL" Code="WLW158000"><Language Description="Women's 58kg - Snatch" Language="ENG"></Language><Language Description="Jusqu'à 58 kg - femmes, arraché" Language="FRA"></Language><Language Description="Até 58kg feminino, arranco" Language="POR"></Language><Language Description="58kg femenino, arrancada" Language="SPA"></Language></CodeSet><CodeSet Event="063" Gender="W" Order="10" Discipline="WL" Code="WLW163000"><Language Description="Women's 63kg - Snatch" Language="ENG"></Language><Language Description="Jusqu'à 63 kg - femmes, arraché" Language="FRA"></Language><Language Description="Até 63kg feminino, arranco" Language="POR"></Language><Language Description="63kg femenino, arrancada" Language="SPA"></Language></CodeSet><CodeSet Event="069" Gender="W" Order="13" Discipline="WL" Code="WLW169000"><Language Description="Women's 69kg - Snatch" Language="ENG"></Language><Language Description="Jusqu'à 69 kg - femmes, arraché" Language="FRA"></Language><Language Description="Até 69kg feminino, arranco" Language="POR"></Language><Language Description="69kg femenino, arrancada" Language="SPA"></Language></CodeSet><CodeSet Event="075" Gender="W" Order="16" Discipline="WL" Code="WLW175000"><Language Description="Women's 75kg - Snatch" Language="ENG"></Language><Language Description="Jusqu'à 75 kg - femmes, arraché" Language="FRA"></Language><Language Description="Até 75kg feminino, arranco" Language="POR"></Language><Language Description="75kg femenino, arrancada" Language="SPA"></Language></CodeSet><CodeSet Event="026" Gender="W" Order="20" Discipline="WL" Code="WLW226000"><Language Description="Women's +75kg - Clean &amp; Jerk" Language="ENG"></Language><Language Description="+75 kg - femmes, épaulé-jeté" Language="FRA"></Language><Language Description="Acima de 75kg feminino, arremesso" Language="POR"></Language><Language Description="+75kg femenino, dos tiempos" Language="SPA"></Language></CodeSet><CodeSet Event="048" Gender="W" Order="2" Discipline="WL" Code="WLW248000"><Language Description="Women's 48kg - Clean &amp; Jerk" Language="ENG"></Language><Language Description="Jusqu'à 48 kg - femmes, épaulé-jeté" Language="FRA"></Language><Language Description="Até 48kg feminino, arremesso" Language="POR"></Language><Language Description="48kg femenino, dos tiempos" Language="SPA"></Language></CodeSet><CodeSet Event="053" Gender="W" Order="5" Discipline="WL" Code="WLW253000"><Language Description="Women's 53kg - Clean &amp; Jerk" Language="ENG"></Language><Language Description="Jusqu'à 53 kg - femmes, épaulé-jeté" Language="FRA"></Language><Language Description="Até 53kg feminino, arremesso" Language="POR"></Language><Language Description="53kg femenino, dos tiempos" Language="SPA"></Language></CodeSet><CodeSet Event="058" Gender="W" Order="8" Discipline="WL" Code="WLW258000"><Language Description="Women's 58kg - Clean &amp; Jerk" Language="ENG"></Language><Language Description="Jusqu'à 58 kg - femmes, épaulé-jeté" Language="FRA"></Language><Language Description="Até 58kg feminino, arremesso" Language="POR"></Language><Language Description="58kg femenino, dos tiempos" Language="SPA"></Language></CodeSet><CodeSet Event="063" Gender="W" Order="11" Discipline="WL" Code="WLW263000"><Language Description="Women's 63kg - Clean &amp; Jerk" Language="ENG"></Language><Language Description="Jusqu'à 63 kg - femmes, épaulé-jeté" Language="FRA"></Language><Language Description="Até 63kg feminino, arremesso" Language="POR"></Language><Language Description="63kg femenino, dos tiempos" Language="SPA"></Language></CodeSet><CodeSet Event="069" Gender="W" Order="14" Discipline="WL" Code="WLW269000"><Language Description="Women's 69kg - Clean &amp; Jerk" Language="ENG"></Language><Language Description="Jusqu'à 69 kg - femmes, épaulé-jeté" Language="FRA"></Language><Language Description="Até 69kg feminino, arremesso" Language="POR"></Language><Language Description="69kg femenino, dos tiempos" Language="SPA"></Language></CodeSet><CodeSet Event="075" Gender="W" Order="17" Discipline="WL" Code="WLW275000"><Language Description="Women's 75kg - Clean &amp; Jerk" Language="ENG"></Language><Language Description="Jusqu'à 75 kg - femmes, épaulé-jeté" Language="FRA"></Language><Language Description="Até 75kg feminino, arremesso" Language="POR"></Language><Language Description="75kg femenino, dos tiempos" Language="SPA"></Language></CodeSet></Competition></OdfBody>