[{"Discipline":"ALP","Code_Entity":"Bracket","Code":"BRN","Order":null,"Description":"Bronze (Small Final)","Note":null},{"Discipline":"ALP","Code_Entity":"Bracket","Code":"FNL","Order":null,"Description":"Finals","Note":null},{"Discipline":"ALP","Code_Entity":"BracketItems","Code":"8FNL","Order":null,"Description":"1/8 Finals","Note":null},{"Discipline":"ALP","Code_Entity":"BracketItems","Code":"FNL","Order":null,"Description":"Final","Note":null},{"Discipline":"ALP","Code_Entity":"BracketItems","Code":"QFNL","Order":null,"Description":"Quarterfinal","Note":null},{"Discipline":"ALP","Code_Entity":"BracketItems","Code":"SFNL","Order":null,"Description":"Semifinal","Note":null},{"Discipline":"ALP","Code_Entity":"ForerunnerBib","Code":"A","Order":null,"Description":"A","Note":null},{"Discipline":"ALP","Code_Entity":"ForerunnerBib","Code":"B","Order":null,"Description":"B","Note":null},{"Discipline":"ALP","Code_Entity":"ForerunnerBib","Code":"C","Order":null,"Description":"C","Note":null},{"Discipline":"ALP","Code_Entity":"ForerunnerBib","Code":"D","Order":null,"Description":"D","Note":null},{"Discipline":"ALP","Code_Entity":"ForerunnerBib","Code":"E","Order":null,"Description":"E","Note":null},{"Discipline":"ALP","Code_Entity":"ForerunnerBib","Code":"F","Order":null,"Description":"F","Note":null},{"Discipline":"ALP","Code_Entity":"ForerunnerBib","Code":"G","Order":null,"Description":"G","Note":null},{"Discipline":"ALP","Code_Entity":"ForerunnerBib","Code":"H","Order":null,"Description":"H","Note":null},{"Discipline":"ALP","Code_Entity":"ForerunnerBib","Code":"I","Order":null,"Description":"I","Note":null},{"Discipline":"ALP","Code_Entity":"ForerunnerBib","Code":"J","Order":null,"Description":"J","Note":null},{"Discipline":"ALP","Code_Entity":"ForerunnerBib","Code":"K","Order":null,"Description":"K","Note":null},{"Discipline":"ALP","Code_Entity":"ForerunnerBib","Code":"L","Order":null,"Description":"L","Note":null},{"Discipline":"ALP","Code_Entity":"ForerunnerBib","Code":"M","Order":null,"Description":"M","Note":null},{"Discipline":"ALP","Code_Entity":"ForerunnerBib","Code":"N","Order":null,"Description":"N","Note":null},{"Discipline":"ALP","Code_Entity":"ForerunnerBib","Code":"O","Order":null,"Description":"O","Note":null},{"Discipline":"ALP","Code_Entity":"IRM","Code":"DNF","Order":null,"Description":"Did not Finish","Note":null},{"Discipline":"ALP","Code_Entity":"IRM","Code":"DNS","Order":null,"Description":"Did not Start","Note":null},{"Discipline":"ALP","Code_Entity":"IRM","Code":"DQB","Order":null,"Description":"Disqualified (Behaviour)","Note":null},{"Discipline":"ALP","Code_Entity":"IRM","Code":"DSQ","Order":null,"Description":"Disqualified","Note":null},{"Discipline":"ALP","Code_Entity":"QualificationMark","Code":"Q","Order":null,"Description":"Team Qualified for the next round","Note":null},{"Discipline":"ALP","Code_Entity":"QualificationMark","Code":"W","Order":null,"Description":"Team won the Big Final","Note":null},{"Discipline":"ALP","Code_Entity":"QualificationMark","Code":"w","Order":null,"Description":"Team won the Small Final","Note":null},{"Discipline":"ALP","Code_Entity":"ResultType","Code":"IRM","Order":null,"Description":"Invalid Result Mark","Note":null},{"Discipline":"ALP","Code_Entity":"ResultType","Code":"POINTS","Order":null,"Description":"Points (Team Event)","Note":null},{"Discipline":"ALP","Code_Entity":"ResultType","Code":"TIME","Order":null,"Description":"Time","Note":null},{"Discipline":"ALP","Code_Entity":"WLT","Code":"L","Order":null,"Description":"Team / Athlete lost","Note":null},{"Discipline":"ALP","Code_Entity":"WLT","Code":"T","Order":null,"Description":"Team / Athlete tied","Note":null},{"Discipline":"ALP","Code_Entity":"WLT","Code":"W","Order":null,"Description":"Team / Athlete won","Note":null},{"Discipline":"BOB","Code_Entity":"IRM","Code":"DNF","Order":null,"Description":"Did not Finish","Note":null},{"Discipline":"BOB","Code_Entity":"IRM","Code":"DNS","Order":null,"Description":"Did not Start","Note":null},{"Discipline":"BOB","Code_Entity":"IRM","Code":"DQB","Order":null,"Description":"Disqualified (Behaviour)","Note":null},{"Discipline":"BOB","Code_Entity":"IRM","Code":"DSQ","Order":null,"Description":"Disqualified","Note":null},{"Discipline":"BOB","Code_Entity":"QualificationMark","Code":"Q","Order":null,"Description":"Qualified (to participate in the last heat)","Note":null},{"Discipline":"BOB","Code_Entity":"ResultType","Code":"IRM","Order":null,"Description":"Invalid Result Mark","Note":null},{"Discipline":"BOB","Code_Entity":"ResultType","Code":"TIME","Order":null,"Description":"Time","Note":null},{"Discipline":"BOB","Code_Entity":"StartText","Code":"After Heat 1","Order":null,"Description":null,"Note":null},{"Discipline":"BOB","Code_Entity":"StartText","Code":"After Heat 3","Order":null,"Description":null,"Note":null},{"Discipline":"BOB","Code_Entity":"StartText","Code":"After Heat 5","Order":null,"Description":null,"Note":null},{"Discipline":"BOB","Code_Entity":"StartText","Code":"After Training 1","Order":null,"Description":null,"Note":null},{"Discipline":"BOB","Code_Entity":"StartText","Code":"After Training 3","Order":null,"Description":null,"Note":null},{"Discipline":"BOB","Code_Entity":"StartText","Code":"After Training 5","Order":null,"Description":null,"Note":null},{"Discipline":"BOB","Code_Entity":"StartText","Code":"Followed by","Order":null,"Description":null,"Note":null},{"Discipline":"BTH","Code_Entity":"IRM","Code":"DNF","Order":null,"Description":"Did not finish","Note":null},{"Discipline":"BTH","Code_Entity":"IRM","Code":"DNS","Order":null,"Description":"Did not start","Note":null},{"Discipline":"BTH","Code_Entity":"IRM","Code":"DQB","Order":null,"Description":"Disqualified (Behaviour)","Note":null},{"Discipline":"BTH","Code_Entity":"IRM","Code":"DSQ","Order":null,"Description":"Disqualified","Note":null},{"Discipline":"BTH","Code_Entity":"IRM","Code":"LAP","Order":null,"Description":"Lapped","Note":null},{"Discipline":"BTH","Code_Entity":"MassGroup","Code":"MEDAL","Order":null,"Description":"Medal winners","Note":null},{"Discipline":"BTH","Code_Entity":"MassGroup","Code":"OG_PTS","Order":null,"Description":"Qualified by Olympic Games Points","Note":null},{"Discipline":"BTH","Code_Entity":"MassGroup","Code":"OG_PTS_RES","Order":null,"Description":"Reserve athletes qualified by Olympic Games points","Note":null},{"Discipline":"BTH","Code_Entity":"MassGroup","Code":"WCP","Order":null,"Description":"World Cup Total Score - top 10","Note":null},{"Discipline":"BTH","Code_Entity":"ResultType","Code":"IRM","Order":null,"Description":"Invalid Result Mark","Note":null},{"Discipline":"BTH","Code_Entity":"ResultType","Code":"IRM_TIME","Order":null,"Description":"For both, time and invalid result mark","Note":null},{"Discipline":"BTH","Code_Entity":"ResultType","Code":"PENALTY","Order":null,"Description":"Number of penalties","Note":null},{"Discipline":"BTH","Code_Entity":"ResultType","Code":"TIME","Order":null,"Description":"Time","Note":null},{"Discipline":"CCS","Code_Entity":"Bracket","Code":"FNL","Order":null,"Description":"Final","Note":null},{"Discipline":"CCS","Code_Entity":"BracketItems","Code":"FNL","Order":null,"Description":"Final","Note":null},{"Discipline":"CCS","Code_Entity":"BracketItems","Code":"QFNL","Order":null,"Description":"Quarterfinal","Note":null},{"Discipline":"CCS","Code_Entity":"BracketItems","Code":"SFNL","Order":null,"Description":"Semifinal","Note":null},{"Discipline":"CCS","Code_Entity":"IRM","Code":"DNF","Order":null,"Description":"Did not finish","Note":null},{"Discipline":"CCS","Code_Entity":"IRM","Code":"DNS","Order":null,"Description":"Did not start","Note":null},{"Discipline":"CCS","Code_Entity":"IRM","Code":"DQB","Order":null,"Description":"Disqualified (Behaviour)","Note":null},{"Discipline":"CCS","Code_Entity":"IRM","Code":"DSQ","Order":null,"Description":"Disqualified","Note":null},{"Discipline":"CCS","Code_Entity":"IRM","Code":"LAP","Order":null,"Description":"Lapped","Note":null},{"Discipline":"CCS","Code_Entity":"IRM","Code":"RAL","Order":null,"Description":"Ranked as Last","Note":null},{"Discipline":"CCS","Code_Entity":"QualificationMark","Code":"LL","Order":null,"Description":"Lucky Loser","Note":null},{"Discipline":"CCS","Code_Entity":"QualificationMark","Code":"Q","Order":null,"Description":"Qualified","Note":null},{"Discipline":"CCS","Code_Entity":"ResultPhase","Code":"F","Order":null,"Description":"Final","Note":null},{"Discipline":"CCS","Code_Entity":"ResultPhase","Code":"FA","Order":null,"Description":"Final A","Note":null},{"Discipline":"CCS","Code_Entity":"ResultPhase","Code":"FB","Order":null,"Description":"Final B","Note":null},{"Discipline":"CCS","Code_Entity":"ResultPhase","Code":"Q","Order":null,"Description":"Qualification","Note":null},{"Discipline":"CCS","Code_Entity":"ResultPhase","Code":"QF","Order":null,"Description":"Quarterfinal","Note":null},{"Discipline":"CCS","Code_Entity":"ResultPhase","Code":"SF","Order":null,"Description":"Semifinal","Note":null},{"Discipline":"CCS","Code_Entity":"ResultPhase","Code":"SF1","Order":null,"Description":"Semifinal 1","Note":null},{"Discipline":"CCS","Code_Entity":"ResultPhase","Code":"SF2","Order":null,"Description":"Semifinal 2","Note":null},{"Discipline":"CCS","Code_Entity":"ResultType","Code":"IRM","Order":null,"Description":"Invalid Result Mark","Note":null},{"Discipline":"CCS","Code_Entity":"ResultType","Code":"TIME","Order":null,"Description":"Time","Note":null},{"Discipline":"CCS","Code_Entity":"StartText","Code":"After Ladies Final","Order":null,"Description":null,"Note":null},{"Discipline":"CCS","Code_Entity":"StartText","Code":"After Ladies QF1","Order":null,"Description":null,"Note":null},{"Discipline":"CCS","Code_Entity":"StartText","Code":"After Ladies QF2","Order":null,"Description":null,"Note":null},{"Discipline":"CCS","Code_Entity":"StartText","Code":"After Ladies QF3","Order":null,"Description":null,"Note":null},{"Discipline":"CCS","Code_Entity":"StartText","Code":"After Ladies QF4","Order":null,"Description":null,"Note":null},{"Discipline":"CCS","Code_Entity":"StartText","Code":"After Ladies QFs","Order":null,"Description":null,"Note":null},{"Discipline":"CCS","Code_Entity":"StartText","Code":"After Ladies SF A","Order":null,"Description":null,"Note":null},{"Discipline":"CCS","Code_Entity":"StartText","Code":"After Ladies SF1","Order":null,"Description":null,"Note":null},{"Discipline":"CCS","Code_Entity":"StartText","Code":"After Ladies SFs","Order":null,"Description":null,"Note":null},{"Discipline":"CCS","Code_Entity":"StartText","Code":"After Men QF1","Order":null,"Description":null,"Note":null},{"Discipline":"CCS","Code_Entity":"StartText","Code":"After Men QF2","Order":null,"Description":null,"Note":null},{"Discipline":"CCS","Code_Entity":"StartText","Code":"After Men QF3","Order":null,"Description":null,"Note":null},{"Discipline":"CCS","Code_Entity":"StartText","Code":"After Men QF4","Order":null,"Description":null,"Note":null},{"Discipline":"CCS","Code_Entity":"StartText","Code":"After Men QFs","Order":null,"Description":null,"Note":null},{"Discipline":"CCS","Code_Entity":"StartText","Code":"After Men SF A","Order":null,"Description":null,"Note":null},{"Discipline":"CCS","Code_Entity":"StartText","Code":"After Men SF1","Order":null,"Description":null,"Note":null},{"Discipline":"CCS","Code_Entity":"StartText","Code":"After Men SFs","Order":null,"Description":null,"Note":null},{"Discipline":"CUR","Code_Entity":"AthleteStatus","Code":"DSQ","Order":null,"Description":"Disqualified","Note":null},{"Discipline":"CUR","Code_Entity":"AthleteStatus","Code":"SUS","Order":null,"Description":"Suspended","Note":null},{"Discipline":"CUR","Code_Entity":"Bracket","Code":"BRN","Order":null,"Description":"Bronze","Note":null},{"Discipline":"CUR","Code_Entity":"Bracket","Code":"FNL","Order":null,"Description":"Finals","Note":null},{"Discipline":"CUR","Code_Entity":"BracketItems","Code":"8FNL","Order":null,"Description":"Round of 16 (1/8 Final)","Note":null},{"Discipline":"CUR","Code_Entity":"BracketItems","Code":"FNL","Order":null,"Description":"Finals","Note":null},{"Discipline":"CUR","Code_Entity":"BracketItems","Code":"QFNL","Order":null,"Description":"Quarter-finals","Note":null},{"Discipline":"CUR","Code_Entity":"BracketItems","Code":"R32","Order":null,"Description":"Round of 32","Note":null},{"Discipline":"CUR","Code_Entity":"BracketItems","Code":"SFNL","Order":null,"Description":"Semi-finals","Note":null},{"Discipline":"CUR","Code_Entity":"CompetitionPlace","Code":"BYE","Order":null,"Description":"There is no competitor, pass directly to the next round","Note":null},{"Discipline":"CUR","Code_Entity":"CompetitionPlace","Code":"TBD","Order":null,"Description":"The competitor is not known yet","Note":null},{"Discipline":"CUR","Code_Entity":"Hand","Code":"B","Order":null,"Description":"Both handed","Note":null},{"Discipline":"CUR","Code_Entity":"Hand","Code":"L","Order":null,"Description":"Left handed","Note":null},{"Discipline":"CUR","Code_Entity":"Hand","Code":"R","Order":null,"Description":"Right handed","Note":null},{"Discipline":"CUR","Code_Entity":"IRM","Code":"DNS","Order":null,"Description":"Did not Start","Note":null},{"Discipline":"CUR","Code_Entity":"IRM","Code":"DQB","Order":null,"Description":"Disqualified (Behaviour)","Note":null},{"Discipline":"CUR","Code_Entity":"IRM","Code":"DSQ","Order":null,"Description":"Disqualified","Note":null},{"Discipline":"CUR","Code_Entity":"IRM","Code":"SUS","Order":null,"Description":"Suspended","Note":null},{"Discipline":"CUR","Code_Entity":"Point","Code":"0","Order":1,"Description":"0","Note":null},{"Discipline":"CUR","Code_Entity":"Point","Code":"1","Order":2,"Description":"0.25","Note":null},{"Discipline":"CUR","Code_Entity":"Point","Code":"2","Order":3,"Description":"0.5","Note":null},{"Discipline":"CUR","Code_Entity":"Point","Code":"3","Order":4,"Description":"0.75","Note":null},{"Discipline":"CUR","Code_Entity":"Point","Code":"4","Order":5,"Description":"1","Note":null},{"Discipline":"CUR","Code_Entity":"Point","Code":"X","Order":6,"Description":"Not considered","Note":null},{"Discipline":"CUR","Code_Entity":"QualificationMark","Code":"Q","Order":null,"Description":"Qualified for the play-offs","Note":null},{"Discipline":"CUR","Code_Entity":"QualificationMark","Code":"TB","Order":null,"Description":"Involved in the tie-breaker","Note":null},{"Discipline":"CUR","Code_Entity":"ResultType","Code":"IRM","Order":null,"Description":"Invalid Result Mark","Note":null},{"Discipline":"CUR","Code_Entity":"ResultType","Code":"IRM_WL","Order":null,"Description":"W or L result for a team under some specific circumstances (the result is not a score).","Note":null},{"Discipline":"CUR","Code_Entity":"ResultType","Code":"POINTS","Order":null,"Description":"Competitor’s score","Note":null},{"Discipline":"CUR","Code_Entity":"ResultType","Code":"SCORE_WL","Order":null,"Description":"W or L result for a team under some specific circumstances (the result is not a score).","Note":null},{"Discipline":"CUR","Code_Entity":"Role","Code":"S","Order":null,"Description":"Skip","Note":null},{"Discipline":"CUR","Code_Entity":"Role","Code":"V","Order":null,"Description":"Vice-Skip","Note":null},{"Discipline":"CUR","Code_Entity":"Statistics","Code":"CUM","Order":null,"Description":"Cumulative Statistics of team and individual","Note":null},{"Discipline":"CUR","Code_Entity":"Statistics","Code":"DSC","Order":null,"Description":"Ranking of the Draw Shot Challenge","Note":null},{"Discipline":"CUR","Code_Entity":"Statistics","Code":"RANKING","Order":null,"Description":"Ranking","Note":null},{"Discipline":"CUR","Code_Entity":"Statistics","Code":"TOU","Order":null,"Description":"Tournament statistics","Note":null},{"Discipline":"CUR","Code_Entity":"Task","Code":"CLEARING","Order":9,"Description":"Clearing","Note":null},{"Discipline":"CUR","Code_Entity":"Task","Code":"DOUBLE","Order":10,"Description":"Double Take-out","Note":null},{"Discipline":"CUR","Code_Entity":"Task","Code":"DRAW","Order":1,"Description":"Draw","Note":null},{"Discipline":"CUR","Code_Entity":"Task","Code":"FREEZE","Order":6,"Description":"Freeze","Note":null},{"Discipline":"CUR","Code_Entity":"Task","Code":"FRONT","Order":2,"Description":"Front","Note":null},{"Discipline":"CUR","Code_Entity":"Task","Code":"GUARD","Order":3,"Description":"Guard","Note":null},{"Discipline":"CUR","Code_Entity":"Task","Code":"HIT-ROLL","Order":8,"Description":"Hit and Roll","Note":null},{"Discipline":"CUR","Code_Entity":"Task","Code":"NO-STATISTICS","Order":14,"Description":"No statistics","Note":null},{"Discipline":"CUR","Code_Entity":"Task","Code":"NOT-PLAYED","Order":13,"Description":"Not played","Note":null},{"Discipline":"CUR","Code_Entity":"Task","Code":"PROMOTION","Order":11,"Description":"Promotion Take-out","Note":null},{"Discipline":"CUR","Code_Entity":"Task","Code":"RAISE","Order":4,"Description":"Raise","Note":null},{"Discipline":"CUR","Code_Entity":"Task","Code":"TAKE-OUT","Order":7,"Description":"Take-out","Note":null},{"Discipline":"CUR","Code_Entity":"Task","Code":"THROUGH","Order":12,"Description":"Through","Note":null},{"Discipline":"CUR","Code_Entity":"Task","Code":"WICK","Order":5,"Description":"Wick / Soft Peeling","Note":null},{"Discipline":"CUR","Code_Entity":"Turn","Code":"CCW","Order":null,"Description":"Counter-Clockwise","Note":null},{"Discipline":"CUR","Code_Entity":"Turn","Code":"CW","Order":null,"Description":"Clockwise","Note":null},{"Discipline":"CUR","Code_Entity":"WLT","Code":"L","Order":null,"Description":"Lost","Note":null},{"Discipline":"CUR","Code_Entity":"WLT","Code":"T","Order":null,"Description":"Tied","Note":null},{"Discipline":"CUR","Code_Entity":"WLT","Code":"W","Order":null,"Description":"Won","Note":null},{"Discipline":"FRS","Code_Entity":"BibColour","Code":"BLUE","Order":null,"Description":"Blue","Note":null},{"Discipline":"FRS","Code_Entity":"BibColour","Code":"GREEN","Order":null,"Description":"Green","Note":null},{"Discipline":"FRS","Code_Entity":"BibColour","Code":"RED","Order":null,"Description":"Red","Note":null},{"Discipline":"FRS","Code_Entity":"BibColour","Code":"YELLOW","Order":null,"Description":"Yellow","Note":null},{"Discipline":"FRS","Code_Entity":"Bracket","Code":"CFNL","Order":null,"Description":"Final (Small Final in SX)","Note":null},{"Discipline":"FRS","Code_Entity":"Bracket","Code":"FNL","Order":null,"Description":"Final","Note":null},{"Discipline":"FRS","Code_Entity":"BracketItems","Code":"8FNL","Order":null,"Description":"Eight Finals (Round of 16)","Note":null},{"Discipline":"FRS","Code_Entity":"BracketItems","Code":"FNL","Order":null,"Description":"Final","Note":null},{"Discipline":"FRS","Code_Entity":"BracketItems","Code":"QFNL","Order":null,"Description":"Quarterfinal","Note":null},{"Discipline":"FRS","Code_Entity":"BracketItems","Code":"SFNL","Order":null,"Description":"Semifinal","Note":null},{"Discipline":"FRS","Code_Entity":"IRM","Code":"DNF","Order":null,"Description":"Did not Finish","Note":null},{"Discipline":"FRS","Code_Entity":"IRM","Code":"DNS","Order":null,"Description":"Did not Start","Note":null},{"Discipline":"FRS","Code_Entity":"IRM","Code":"DQB","Order":null,"Description":"Disqualified (Behaviour)","Note":null},{"Discipline":"FRS","Code_Entity":"IRM","Code":"DQIC","Order":null,"Description":"Disqualified for Intentional Contact","Note":null},{"Discipline":"FRS","Code_Entity":"IRM","Code":"DQP","Order":null,"Description":"Potentially disqualified","Note":null},{"Discipline":"FRS","Code_Entity":"IRM","Code":"DSQ","Order":null,"Description":"Disqualified","Note":null},{"Discipline":"FRS","Code_Entity":"IRM","Code":"REL","Order":null,"Description":"Relegated","Note":null},{"Discipline":"FRS","Code_Entity":"JudgeType","Code":"AIR","Order":null,"Description":"Air","Note":null},{"Discipline":"FRS","Code_Entity":"JudgeType","Code":"TURN","Order":null,"Description":"Turns","Note":null},{"Discipline":"FRS","Code_Entity":"QualificationMark","Code":"FA","Order":null,"Description":"Qualified for Big Final","Note":null},{"Discipline":"FRS","Code_Entity":"QualificationMark","Code":"FB","Order":null,"Description":"Qualified for Small Final","Note":null},{"Discipline":"FRS","Code_Entity":"QualificationMark","Code":"Q","Order":null,"Description":"Qualified","Note":null},{"Discipline":"FRS","Code_Entity":"ResultType","Code":"CODE","Order":null,"Description":"Code (used in event final ranking)","Note":null},{"Discipline":"FRS","Code_Entity":"ResultType","Code":"IRM","Order":null,"Description":"Invalid Result Mark","Note":null},{"Discipline":"FRS","Code_Entity":"ResultType","Code":"POINTS","Order":null,"Description":"Points","Note":null},{"Discipline":"FRS","Code_Entity":"ResultType","Code":"RANK","Order":null,"Description":"Rank-only result used in all SBX Finals phases","Note":null},{"Discipline":"FRS","Code_Entity":"ResultType","Code":"TIME","Order":null,"Description":"Time","Note":null},{"Discipline":"FRS","Code_Entity":"StartText","Code":"After 1/8 Finals","Order":null,"Description":null,"Note":null},{"Discipline":"FRS","Code_Entity":"StartText","Code":"After Finals","Order":null,"Description":null,"Note":null},{"Discipline":"FRS","Code_Entity":"StartText","Code":"After Quarterfinals","Order":null,"Description":null,"Note":null},{"Discipline":"FRS","Code_Entity":"StartText","Code":"After Semifinals","Order":null,"Description":null,"Note":null},{"Discipline":"FSK","Code_Entity":"IRM","Code":"DQB","Order":null,"Description":"Disqualified (Behaviour)","Note":null},{"Discipline":"FSK","Code_Entity":"IRM","Code":"DSQ","Order":null,"Description":"Disqualified","Note":null},{"Discipline":"FSK","Code_Entity":"IRM","Code":"WD","Order":null,"Description":"Withdrawn","Note":null},{"Discipline":"FSK","Code_Entity":"Panel","Code":"JUDGE","Order":null,"Description":"Panel of Judges","Note":null},{"Discipline":"FSK","Code_Entity":"Panel","Code":"OPERATOR","Order":null,"Description":"Data/Replay Operators","Note":null},{"Discipline":"FSK","Code_Entity":"Panel","Code":"TECH","Order":null,"Description":"Technical Panel","Note":null},{"Discipline":"FSK","Code_Entity":"QualificationMark","Code":"Q","Order":null,"Description":"Qualified for Final","Note":null},{"Discipline":"FSK","Code_Entity":"ResultType","Code":"IRM","Order":null,"Description":"Invalid Result Mark","Note":null},{"Discipline":"FSK","Code_Entity":"ResultType","Code":"POINTS","Order":null,"Description":"Points","Note":null},{"Discipline":"FSK","Code_Entity":"TeamDiscipline","Code":"ID","Order":null,"Description":"Ice Dance","Note":null},{"Discipline":"FSK","Code_Entity":"TeamDiscipline","Code":"L","Order":null,"Description":"Ladies","Note":null},{"Discipline":"FSK","Code_Entity":"TeamDiscipline","Code":"M","Order":null,"Description":"Men","Note":null},{"Discipline":"FSK","Code_Entity":"TeamDiscipline","Code":"P","Order":null,"Description":"Pairs","Note":null},{"Discipline":"GEN","Code_Entity":"BioExt","Code":"EB_SOCIALMEDIA","Order":null,"Description":"Social Media","Note":null},{"Discipline":"GEN","Code_Entity":"CodeSet","Code":"BCK_SPORT","Order":null,"Description":"List of Background Sport","Note":null},{"Discipline":"GEN","Code_Entity":"CodeSet","Code":"BCK_TYPE","Order":null,"Description":"List of Background Report type","Note":null},{"Discipline":"GEN","Code_Entity":"CodeSet","Code":"CONTINENT","Order":null,"Description":"Continents","Note":null},{"Discipline":"GEN","Code_Entity":"CodeSet","Code":"COUNTRY","Order":null,"Description":"List of Countries","Note":null},{"Discipline":"GEN","Code_Entity":"CodeSet","Code":"DISCIPLINE","Order":null,"Description":"List of Disiplines","Note":null},{"Discipline":"GEN","Code_Entity":"CodeSet","Code":"DISCIPLINE_FUNCTION","Order":null,"Description":"List of Results Functions","Note":null},{"Discipline":"GEN","Code_Entity":"CodeSet","Code":"EVENT","Order":null,"Description":"List of Events","Note":null},{"Discipline":"GEN","Code_Entity":"CodeSet","Code":"EVENT_UNIT","Order":null,"Description":"List of Event Units","Note":null},{"Discipline":"GEN","Code_Entity":"CodeSet","Code":"HORSE_BREED","Order":null,"Description":"List of Horse Breeds","Note":null},{"Discipline":"GEN","Code_Entity":"CodeSet","Code":"HORSE_COLOUR","Order":null,"Description":"List of Horse Colours","Note":null},{"Discipline":"GEN","Code_Entity":"CodeSet","Code":"HORSE_GENDER","Order":null,"Description":"List of Horse Genders","Note":null},{"Discipline":"GEN","Code_Entity":"CodeSet","Code":"LOCATION","Order":null,"Description":"List of Locations","Note":null},{"Discipline":"GEN","Code_Entity":"CodeSet","Code":"MARITAL_STATUS","Order":null,"Description":"Marital Status","Note":null},{"Discipline":"GEN","Code_Entity":"CodeSet","Code":"NOC","Order":null,"Description":"List of National Olympic Committees","Note":null},{"Discipline":"GEN","Code_Entity":"CodeSet","Code":"NWS_SPORT","Order":null,"Description":"List of News Sport","Note":null},{"Discipline":"GEN","Code_Entity":"CodeSet","Code":"NWS_TYPE","Order":null,"Description":"List of News Report Type","Note":null},{"Discipline":"GEN","Code_Entity":"CodeSet","Code":"ODF_SPORT_CODES","Order":null,"Description":"All ODF Sport Codes","Note":null},{"Discipline":"GEN","Code_Entity":"CodeSet","Code":"ORGANISATION","Order":null,"Description":"List of Organisations","Note":null},{"Discipline":"GEN","Code_Entity":"CodeSet","Code":"PHASE","Order":null,"Description":"List of Phases","Note":null},{"Discipline":"GEN","Code_Entity":"CodeSet","Code":"POSITION","Order":null,"Description":"List of Positions","Note":null},{"Discipline":"GEN","Code_Entity":"CodeSet","Code":"RECORD","Order":null,"Description":"List of Record Events","Note":null},{"Discipline":"GEN","Code_Entity":"CodeSet","Code":"RECORD_TYPE","Order":null,"Description":"List of Record Types","Note":null},{"Discipline":"GEN","Code_Entity":"CodeSet","Code":"SPORT","Order":null,"Description":"List of Sports","Note":null},{"Discipline":"GEN","Code_Entity":"CodeSet","Code":"VENUE","Order":null,"Description":"List of Venues","Note":null},{"Discipline":"GEN","Code_Entity":"CodeSet","Code":"WTHR_CONDITION","Order":null,"Description":"List of Weather Conditions","Note":null},{"Discipline":"GEN","Code_Entity":"CodeSet","Code":"WTHR_REGION","Order":null,"Description":"List of Weather Regions","Note":null},{"Discipline":"GEN","Code_Entity":"CodeSet","Code":"WTHR_WIND_DIR","Order":null,"Description":"List of Wind Directions","Note":null},{"Discipline":"GEN","Code_Entity":"CompetitorPlace","Code":"BYE","Order":null,"Description":"There is no competitor; the other team/athlete goes directly to the next phase/round","Note":null},{"Discipline":"GEN","Code_Entity":"CompetitorPlace","Code":"NCT ","Order":null,"Description":"When both athlete are disqualified or withdraw and \"No contestant\" passes to the next round","Note":null},{"Discipline":"GEN","Code_Entity":"CompetitorPlace","Code":"TBD","Order":null,"Description":"The competitor is not known yet","Note":null},{"Discipline":"GEN","Code_Entity":"GMGNCode","Code":"DDD-----------------------VEN-----","Order":null,"Description":"DDD=Discipline, VEN=Venue","Note":null},{"Discipline":"GEN","Code_Entity":"Home","Code":"AWAY","Order":null,"Description":"Away","Note":null},{"Discipline":"GEN","Code_Entity":"Home","Code":"HOME","Order":null,"Description":"Home","Note":null},{"Discipline":"GEN","Code_Entity":"MedalSummaryType","Code":"M","Order":null,"Description":"Men events","Note":null},{"Discipline":"GEN","Code_Entity":"MedalSummaryType","Code":"TOT","Order":null,"Description":"All the events","Note":null},{"Discipline":"GEN","Code_Entity":"MedalSummaryType","Code":"W","Order":null,"Description":"Women events","Note":null},{"Discipline":"GEN","Code_Entity":"MedalSummaryType","Code":"X","Order":null,"Description":"Mixed or open events","Note":null},{"Discipline":"GEN","Code_Entity":"MedalType","Code":"ME_BRONZE","Order":null,"Description":"Bronze","Note":null},{"Discipline":"GEN","Code_Entity":"MedalType","Code":"ME_GOLD","Order":null,"Description":"Gold","Note":null},{"Discipline":"GEN","Code_Entity":"MedalType","Code":"ME_SILVER","Order":null,"Description":"Silver","Note":null},{"Discipline":"GEN","Code_Entity":"Pool","Code":1,"Order":null,"Description":"1st in Pool","Note":null},{"Discipline":"GEN","Code_Entity":"Pool","Code":2,"Order":null,"Description":"2nd in Pool","Note":null},{"Discipline":"GEN","Code_Entity":"Pool","Code":3,"Order":null,"Description":"3rd in Pool","Note":null},{"Discipline":"GEN","Code_Entity":"Pool","Code":4,"Order":null,"Description":"4th in Pool","Note":null},{"Discipline":"GEN","Code_Entity":"Pool","Code":5,"Order":null,"Description":"5th in Pool","Note":null},{"Discipline":"GEN","Code_Entity":"Pool","Code":6,"Order":null,"Description":"6th in Pool","Note":null},{"Discipline":"GEN","Code_Entity":"Pool","Code":"LL","Order":null,"Description":"Lucky Loser","Note":null},{"Discipline":"GEN","Code_Entity":"Pool","Code":"X2","Order":null,"Description":"2nd in Pool","Note":null},{"Discipline":"GEN","Code_Entity":"Pool","Code":"X2/3","Order":null,"Description":"A2/A3 (to be drawn) or B2/B3 (to be drawn)","Note":null},{"Discipline":"GEN","Code_Entity":"Pool","Code":"X3","Order":null,"Description":"Top two 3rd in Pool","Note":null},{"Discipline":"GEN","Code_Entity":"PrecipitationUnit","Code":"C","Order":null,"Description":"Centimetres","Note":null},{"Discipline":"GEN","Code_Entity":"PrecipitationUnit","Code":"I","Order":null,"Description":"Inches","Note":null},{"Discipline":"GEN","Code_Entity":"PrecipitationUnit","Code":"M","Order":null,"Description":"Milimetres","Note":null},{"Discipline":"GEN","Code_Entity":"PrecType","Code":"R","Order":null,"Description":"Rain","Note":null},{"Discipline":"GEN","Code_Entity":"PrecType","Code":"S","Order":null,"Description":"Snow","Note":null},{"Discipline":"GEN","Code_Entity":"PressureUnit","Code":"HPA","Order":null,"Description":"Hectopascal","Note":null},{"Discipline":"GEN","Code_Entity":"ProtestStatus","Code":"CLS","Order":null,"Description":"Closed","Note":null},{"Discipline":"GEN","Code_Entity":"ProtestStatus","Code":"OPN","Order":null,"Description":"Open","Note":null},{"Discipline":"GEN","Code_Entity":"ProtestStatus","Code":"PND","Order":null,"Description":"Pending","Note":null},{"Discipline":"GEN","Code_Entity":"ProtestStatus","Code":"ROPN","Order":null,"Description":"Re Open","Note":null},{"Discipline":"GEN","Code_Entity":"ResultStatus","Code":"START_LIST","Order":1,"Description":"Before competition, Start List","Note":null},{"Discipline":"GEN","Code_Entity":"ResultStatus","Code":"LIVE","Order":2,"Description":"For live updates during competition","Note":null},{"Discipline":"GEN","Code_Entity":"ResultStatus","Code":"INTERMEDIATE","Order":3,"Description":"When competition is stopped, usued at pre-defined points","Note":null},{"Discipline":"GEN","Code_Entity":"ResultStatus","Code":"UNCONFIRMED","Order":4,"Description":"When the unit is over but not yet unofficial or official.","Note":"Only used if other statuses do not come quickly, not used in all sports"},{"Discipline":"GEN","Code_Entity":"ResultStatus","Code":"UNOFFICIAL","Order":5,"Description":"Results of the competition released as soon as the event is over, not waiting any official decision of the International Federation. The correctness of data must be assured.","Note":null},{"Discipline":"GEN","Code_Entity":"ResultStatus","Code":"OFFICIAL","Order":6,"Description":"Results of the competition released as soon as the event is officially confirmed taking into account the resolution of the protests, etc.","Note":null},{"Discipline":"GEN","Code_Entity":"ResultStatus","Code":"PARTIAL","Order":7,"Description":"Incomplete list, Final Ranking. Used in PDF","Note":null},{"Discipline":"GEN","Code_Entity":"ResultStatus","Code":"PROTESTED","Order":8,"Description":"After the competition is no longer LIVE and a protest has been lodged","Note":"After all decisions on the protest are made the ResultStatus will change to UNOFFICIAL or OFFICIAL as appropriate"},{"Discipline":"GEN","Code_Entity":"ShuttleServiceType","Code":"ATH","Order":null,"Description":"Shuttle Services Athletes","Note":null},{"Discipline":"GEN","Code_Entity":"ShuttleServiceType","Code":"MEDAL","Order":null,"Description":"Shuttle Services Media","Note":null},{"Discipline":"GEN","Code_Entity":"ShuttleServiceType","Code":"OFF","Order":null,"Description":"Shuttle Services Officials","Note":null},{"Discipline":"GEN","Code_Entity":"SocialMedia","Code":"AMEBA","Order":null,"Description":"Ameba","Note":null},{"Discipline":"GEN","Code_Entity":"SocialMedia","Code":"ASKFM","Order":null,"Description":"Ask.fm","Note":null},{"Discipline":"GEN","Code_Entity":"SocialMedia","Code":"BADOO","Order":null,"Description":"Badoo","Note":null},{"Discipline":"GEN","Code_Entity":"SocialMedia","Code":"BLOG","Order":null,"Description":"Athlete Blog","Note":null},{"Discipline":"GEN","Code_Entity":"SocialMedia","Code":"COPAINSDAVANT","Order":null,"Description":"CopainsdAvant","Note":null},{"Discipline":"GEN","Code_Entity":"SocialMedia","Code":"CYWORLD","Order":null,"Description":"Cyworld","Note":null},{"Discipline":"GEN","Code_Entity":"SocialMedia","Code":"FACEBOOK","Order":null,"Description":"Facebook","Note":null},{"Discipline":"GEN","Code_Entity":"SocialMedia","Code":"FACEBOOK_PAGE","Order":null,"Description":"Facebook Page","Note":null},{"Discipline":"GEN","Code_Entity":"SocialMedia","Code":"FACEBOOK_PAGE2","Order":null,"Description":"Facebook Page 2","Note":null},{"Discipline":"GEN","Code_Entity":"SocialMedia","Code":"FACEBOOK_TEAM","Order":null,"Description":"Facebook Team","Note":null},{"Discipline":"GEN","Code_Entity":"SocialMedia","Code":"FACEBOOK2","Order":null,"Description":"Facebook Profile 2","Note":null},{"Discipline":"GEN","Code_Entity":"SocialMedia","Code":"FLICKR","Order":null,"Description":"Flickr","Note":null},{"Discipline":"GEN","Code_Entity":"SocialMedia","Code":"GOOGLEPLUS","Order":null,"Description":"Google+","Note":null},{"Discipline":"GEN","Code_Entity":"SocialMedia","Code":"INSTAGRAM","Order":null,"Description":"Instagram","Note":null},{"Discipline":"GEN","Code_Entity":"SocialMedia","Code":"LINKEDIN","Order":null,"Description":"LinkedIn","Note":null},{"Discipline":"GEN","Code_Entity":"SocialMedia","Code":"MYSPACE","Order":null,"Description":"MySpace","Note":null},{"Discipline":"GEN","Code_Entity":"SocialMedia","Code":"ODNOKLASSNIKI","Order":null,"Description":"Odnoklassniki","Note":null},{"Discipline":"GEN","Code_Entity":"SocialMedia","Code":"PINTEREST","Order":null,"Description":"Pinterest","Note":null},{"Discipline":"GEN","Code_Entity":"SocialMedia","Code":"QQ","Order":null,"Description":"QQ","Note":null},{"Discipline":"GEN","Code_Entity":"SocialMedia","Code":"STRAVA","Order":null,"Description":"Strava","Note":null},{"Discipline":"GEN","Code_Entity":"SocialMedia","Code":"TUMBLR","Order":null,"Description":"Tumblr","Note":null},{"Discipline":"GEN","Code_Entity":"SocialMedia","Code":"TWITTER","Order":null,"Description":"Twitter","Note":null},{"Discipline":"GEN","Code_Entity":"SocialMedia","Code":"TWITTER_TEAM","Order":null,"Description":"Twitter Team Profile","Note":null},{"Discipline":"GEN","Code_Entity":"SocialMedia","Code":"TWITTER2","Order":null,"Description":"Twitter Profile 2","Note":null},{"Discipline":"GEN","Code_Entity":"SocialMedia","Code":"VIMEO","Order":null,"Description":"Vimeo","Note":null},{"Discipline":"GEN","Code_Entity":"SocialMedia","Code":"VINE","Order":null,"Description":"Vine","Note":null},{"Discipline":"GEN","Code_Entity":"SocialMedia","Code":"VK_PAGE","Order":null,"Description":"VK Page","Note":null},{"Discipline":"GEN","Code_Entity":"SocialMedia","Code":"VK_PROFILE","Order":null,"Description":"VK Profile","Note":null},{"Discipline":"GEN","Code_Entity":"SocialMedia","Code":"WEBSITE","Order":null,"Description":"Athlete Website","Note":null},{"Discipline":"GEN","Code_Entity":"SocialMedia","Code":"WEBSITE_STABLE","Order":null,"Description":"EQ Stable Website","Note":null},{"Discipline":"GEN","Code_Entity":"SocialMedia","Code":"WEBSITE_TEAM","Order":null,"Description":"Team Website","Note":null},{"Discipline":"GEN","Code_Entity":"SocialMedia","Code":"WEBSITE2","Order":null,"Description":"Athlete Website 2","Note":null},{"Discipline":"GEN","Code_Entity":"SocialMedia","Code":"WEIBO","Order":null,"Description":"Weibo","Note":null},{"Discipline":"GEN","Code_Entity":"SocialMedia","Code":"YOUTUBE","Order":null,"Description":"YouTube","Note":null},{"Discipline":"GEN","Code_Entity":"Source","Code":"xxxxx","Order":null,"Description":"Origin for messages generated by OVR at xxx","Note":null},{"Discipline":"GEN","Code_Entity":"TemperatureType","Code":"MAX","Order":null,"Description":"Maximum temperature","Note":null},{"Discipline":"GEN","Code_Entity":"TemperatureType","Code":"MIN","Order":null,"Description":"Minimum temperature","Note":null},{"Discipline":"GEN","Code_Entity":"TemperatureUnit","Code":"C","Order":null,"Description":"Celsius","Note":null},{"Discipline":"GEN","Code_Entity":"TemperatureUnit","Code":"F","Order":null,"Description":"Fahrenheit","Note":null},{"Discipline":"GEN","Code_Entity":"UnitMedalType","Code":0,"Order":null,"Description":"No medal event unit","Note":null},{"Discipline":"GEN","Code_Entity":"UnitMedalType","Code":1,"Order":null,"Description":"Gold medal event unit","Note":null},{"Discipline":"GEN","Code_Entity":"UnitMedalType","Code":2,"Order":null,"Description":"Bronze medal event unit","Note":null},{"Discipline":"GEN","Code_Entity":"WeatherPeriod","Code":"HO","Order":null,"Description":"Hourly","Note":null},{"Discipline":"GEN","Code_Entity":"WeatherPeriod","Code":"MD","Order":null,"Description":"Midday","Note":null},{"Discipline":"GEN","Code_Entity":"WeatherPeriod","Code":"TN","Order":null,"Description":"Tonight","Note":null},{"Discipline":"GEN","Code_Entity":"WeatherPoint","Code":"FINISH","Order":null,"Description":"Finish of the event unit","Note":null},{"Discipline":"GEN","Code_Entity":"WeatherPoint","Code":"GEN","Order":null,"Description":"General","Note":null},{"Discipline":"GEN","Code_Entity":"WeatherPoint","Code":"START","Order":null,"Description":"Start of the event unit","Note":null},{"Discipline":"GEN","Code_Entity":"WeatherPoints","Code":"HIGH","Order":null,"Description":"High","Note":null},{"Discipline":"GEN","Code_Entity":"WeatherPoints","Code":"LOW","Order":null,"Description":"Low","Note":null},{"Discipline":"GEN","Code_Entity":"WindUnit","Code":"KMH","Order":null,"Description":"Kilometres per hour","Note":null},{"Discipline":"GEN","Code_Entity":"WindUnit","Code":"MPH","Order":null,"Description":"Miles per hour","Note":null},{"Discipline":"GEN","Code_Entity":"WindUnit","Code":"MS","Order":null,"Description":"Metres per second","Note":null},{"Discipline":"IHO","Code_Entity":"Action","Code":"GK","Order":null,"Description":"Goalkeeper change","Note":null},{"Discipline":"IHO","Code_Entity":"Action","Code":"GOAL","Order":null,"Description":"Goal","Note":null},{"Discipline":"IHO","Code_Entity":"Action","Code":"GWG","Order":null,"Description":"Game winning goal only for @code (in period) GWS","Note":null},{"Discipline":"IHO","Code_Entity":"Action","Code":"GWS","Order":null,"Description":"Game winning shot only for @code (in period) GWS","Note":null},{"Discipline":"IHO","Code_Entity":"Action","Code":"P","Order":null,"Description":"Penalty","Note":null},{"Discipline":"IHO","Code_Entity":"Action","Code":"PTY","Order":null,"Description":"Penalty shot","Note":null},{"Discipline":"IHO","Code_Entity":"Action","Code":"TOUT","Order":null,"Description":"Time-out","Note":null},{"Discipline":"IHO","Code_Entity":"ActionRole","Code":"ASSIST1","Order":null,"Description":"Assistant 1 (in goal action, if assistant 1 is awarded)","Note":null},{"Discipline":"IHO","Code_Entity":"ActionRole","Code":"ASSIST2","Order":null,"Description":"Assistant 2 (in goal action, if 2 assistants are awarded)","Note":null},{"Discipline":"IHO","Code_Entity":"ActionRole","Code":"GK","Order":null,"Description":"Goalkeeper (in penalty shot, GWS and GWG actions)","Note":null},{"Discipline":"IHO","Code_Entity":"ActionRole","Code":"IN","Order":null,"Description":"Goalkeeper in (in GK action)","Note":null},{"Discipline":"IHO","Code_Entity":"ActionRole","Code":"OUT","Order":null,"Description":"Goalkeeper out (in GK action)","Note":null},{"Discipline":"IHO","Code_Entity":"ActionRole","Code":"PTY_SERVE","Order":null,"Description":"Person serving the penalty (only use if different to person receiving the penalty)","Note":null},{"Discipline":"IHO","Code_Entity":"ActionRole","Code":"SCR","Order":null,"Description":"Goal scorer (in goal action)","Note":null},{"Discipline":"IHO","Code_Entity":"ActionRole","Code":"SHOT","Order":null,"Description":"Penalty shooter, in penalty shot, GWS and GWG actions","Note":null},{"Discipline":"IHO","Code_Entity":"Assignment","Code":1,"Order":null,"Description":"Line 1","Note":null},{"Discipline":"IHO","Code_Entity":"Assignment","Code":2,"Order":null,"Description":"Line 2","Note":null},{"Discipline":"IHO","Code_Entity":"Assignment","Code":3,"Order":null,"Description":"Line 3","Note":null},{"Discipline":"IHO","Code_Entity":"Assignment","Code":4,"Order":null,"Description":"Line 4","Note":null},{"Discipline":"IHO","Code_Entity":"Assignment","Code":"GK","Order":null,"Description":"Line up goalkeeper","Note":null},{"Discipline":"IHO","Code_Entity":"AthleteStatus","Code":"DQB","Order":null,"Description":"Disqualified (Behaviour)","Note":null},{"Discipline":"IHO","Code_Entity":"AthleteStatus","Code":"DSQ","Order":null,"Description":"Disqualified","Note":null},{"Discipline":"IHO","Code_Entity":"AthleteStatus","Code":"NU","Order":null,"Description":"Not in Uniform (Not Dressed)","Note":null},{"Discipline":"IHO","Code_Entity":"AthleteStatus","Code":"SUSPEND","Order":null,"Description":"Suspended","Note":null},{"Discipline":"IHO","Code_Entity":"Bracket","Code":"5_8","Order":null,"Description":"5-8","Note":null},{"Discipline":"IHO","Code_Entity":"Bracket","Code":"7_8","Order":null,"Description":"7-8","Note":null},{"Discipline":"IHO","Code_Entity":"Bracket","Code":"BRN","Order":null,"Description":"Bronze","Note":null},{"Discipline":"IHO","Code_Entity":"Bracket","Code":"FNL","Order":null,"Description":"Finals","Note":null},{"Discipline":"IHO","Code_Entity":"BracketItems","Code":"8FNL","Order":null,"Description":"Qualification play-off (Olympic in men’s competition only)","Note":null},{"Discipline":"IHO","Code_Entity":"BracketItems","Code":"FNL","Order":null,"Description":"Finals","Note":null},{"Discipline":"IHO","Code_Entity":"BracketItems","Code":"QFNL","Order":null,"Description":"Quarterfinals (Olympic only)","Note":null},{"Discipline":"IHO","Code_Entity":"BracketItems","Code":"SFNL","Order":null,"Description":"Semifinals","Note":null},{"Discipline":"IHO","Code_Entity":"Hand","Code":"L","Order":null,"Description":"Left","Note":null},{"Discipline":"IHO","Code_Entity":"Hand","Code":"R","Order":null,"Description":"Right","Note":null},{"Discipline":"IHO","Code_Entity":"IRM","Code":"DQB","Order":null,"Description":"Disqualified (Behaviour)","Note":null},{"Discipline":"IHO","Code_Entity":"IRM","Code":"DSQ","Order":null,"Description":"Disqualified","Note":null},{"Discipline":"IHO","Code_Entity":"IRM","Code":"FORFEIT","Order":null,"Description":"Forfeit for just the team including this code","Note":null},{"Discipline":"IHO","Code_Entity":"IRM","Code":"FORFEIT_2","Order":null,"Description":"Forfeit for the two teams, to indicate the both teams lost","Note":null},{"Discipline":"IHO","Code_Entity":"PenaltyDesc","Code":"ABUSE","Order":null,"Description":"Abuse of Officials","Note":null},{"Discipline":"IHO","Code_Entity":"PenaltyDesc","Code":"BENCH","Order":null,"Description":"Bench Minor Penalty","Note":null},{"Discipline":"IHO","Code_Entity":"PenaltyDesc","Code":"BITE","Order":null,"Description":"Biting","Note":null},{"Discipline":"IHO","Code_Entity":"PenaltyDesc","Code":"BOARD","Order":null,"Description":"Boarding","Note":null},{"Discipline":"IHO","Code_Entity":"PenaltyDesc","Code":"BR-ST","Order":null,"Description":"Broken Stick","Note":null},{"Discipline":"IHO","Code_Entity":"PenaltyDesc","Code":"BUT-E","Order":null,"Description":"Butt-Ending","Note":null},{"Discipline":"IHO","Code_Entity":"PenaltyDesc","Code":"CHARG","Order":null,"Description":"Charging","Note":null},{"Discipline":"IHO","Code_Entity":"PenaltyDesc","Code":"CHE-B","Order":null,"Description":"Checking from Behind","Note":null},{"Discipline":"IHO","Code_Entity":"PenaltyDesc","Code":"CHE-H","Order":null,"Description":"Checking to the Head and Neck Area","Note":null},{"Discipline":"IHO","Code_Entity":"PenaltyDesc","Code":"CLIPP","Order":null,"Description":"Clipping","Note":null},{"Discipline":"IHO","Code_Entity":"PenaltyDesc","Code":"CLOS","Order":null,"Description":"Closing hand on puck","Note":null},{"Discipline":"IHO","Code_Entity":"PenaltyDesc","Code":"CROSS","Order":null,"Description":"Cross-Checking","Note":null},{"Discipline":"IHO","Code_Entity":"PenaltyDesc","Code":"DANG","Order":null,"Description":"Dangerous equipment","Note":null},{"Discipline":"IHO","Code_Entity":"PenaltyDesc","Code":"DELAY","Order":null,"Description":"Delaying the Game","Note":null},{"Discipline":"IHO","Code_Entity":"PenaltyDesc","Code":"ELBOW","Order":null,"Description":"Elbowing","Note":null},{"Discipline":"IHO","Code_Entity":"PenaltyDesc","Code":"EMBEL","Order":null,"Description":"Embellishment","Note":null},{"Discipline":"IHO","Code_Entity":"PenaltyDesc","Code":"ENG-S","Order":null,"Description":"Engaging with Spectators","Note":null},{"Discipline":"IHO","Code_Entity":"PenaltyDesc","Code":"FIGHT","Order":null,"Description":"Fighting","Note":null},{"Discipline":"IHO","Code_Entity":"PenaltyDesc","Code":"GK-INT","Order":null,"Description":"Interference on a Goalkeeper","Note":null},{"Discipline":"IHO","Code_Entity":"PenaltyDesc","Code":"GK-PEN","Order":null,"Description":"Goalkeeper Penalties","Note":null},{"Discipline":"IHO","Code_Entity":"PenaltyDesc","Code":"H-BUT","Order":null,"Description":"Head-Butting","Note":null},{"Discipline":"IHO","Code_Entity":"PenaltyDesc","Code":"HELM","Order":null,"Description":"Playing without helmet","Note":null},{"Discipline":"IHO","Code_Entity":"PenaltyDesc","Code":"HI-ST","Order":null,"Description":"High Sticking","Note":null},{"Discipline":"IHO","Code_Entity":"PenaltyDesc","Code":"HOLD","Order":null,"Description":"Holding an opponent","Note":null},{"Discipline":"IHO","Code_Entity":"PenaltyDesc","Code":"HOOK","Order":null,"Description":"Hooking","Note":null},{"Discipline":"IHO","Code_Entity":"PenaltyDesc","Code":"HO-ST","Order":null,"Description":"Holding the Stick","Note":null},{"Discipline":"IHO","Code_Entity":"PenaltyDesc","Code":"ILL-H","Order":null,"Description":"Illegal Hit","Note":null},{"Discipline":"IHO","Code_Entity":"PenaltyDesc","Code":"ILL-ST","Order":null,"Description":"Illegal Stick - Stick Measurement","Note":null},{"Discipline":"IHO","Code_Entity":"PenaltyDesc","Code":"INCAC","Order":null,"Description":"Incorrect Access to or From Penalty Box","Note":null},{"Discipline":"IHO","Code_Entity":"PenaltyDesc","Code":"INJUR","Order":null,"Description":"Injured Skater Refusing to Leave the Ice","Note":null},{"Discipline":"IHO","Code_Entity":"PenaltyDesc","Code":"INTRF","Order":null,"Description":"Interference","Note":null},{"Discipline":"IHO","Code_Entity":"PenaltyDesc","Code":"KICK","Order":null,"Description":"Kicking","Note":null},{"Discipline":"IHO","Code_Entity":"PenaltyDesc","Code":"KNEE","Order":null,"Description":"Kneeing","Note":null},{"Discipline":"IHO","Code_Entity":"PenaltyDesc","Code":"L-BCH","Order":null,"Description":"Leaving the Bench","Note":null},{"Discipline":"IHO","Code_Entity":"PenaltyDesc","Code":"OTHER","Order":null,"Description":"Other Penalties","Note":null},{"Discipline":"IHO","Code_Entity":"PenaltyDesc","Code":"PULL","Order":null,"Description":"Pulling Hair, Helmet, Cage","Note":null},{"Discipline":"IHO","Code_Entity":"PenaltyDesc","Code":"REFUSE","Order":null,"Description":"Refusing to Start Play - Team on / Not on the Ice","Note":null},{"Discipline":"IHO","Code_Entity":"PenaltyDesc","Code":"ROUGH","Order":null,"Description":"Roughing","Note":null},{"Discipline":"IHO","Code_Entity":"PenaltyDesc","Code":"SLASH","Order":null,"Description":"Slashing","Note":null},{"Discipline":"IHO","Code_Entity":"PenaltyDesc","Code":"SLEW","Order":null,"Description":"Slew-footing","Note":null},{"Discipline":"IHO","Code_Entity":"PenaltyDesc","Code":"SPEAR","Order":null,"Description":"Spearing","Note":null},{"Discipline":"IHO","Code_Entity":"PenaltyDesc","Code":"SPIT","Order":null,"Description":"Spitting","Note":null},{"Discipline":"IHO","Code_Entity":"PenaltyDesc","Code":"TAUNT","Order":null,"Description":"Taunting","Note":null},{"Discipline":"IHO","Code_Entity":"PenaltyDesc","Code":"T-BCH","Order":null,"Description":"Team Officials Leaving the Players Bench","Note":null},{"Discipline":"IHO","Code_Entity":"PenaltyDesc","Code":"TEE","Order":null,"Description":"Teeing","Note":null},{"Discipline":"IHO","Code_Entity":"PenaltyDesc","Code":"THR-ST","Order":null,"Description":"Throwing a Stick or any Object","Note":null},{"Discipline":"IHO","Code_Entity":"PenaltyDesc","Code":"TOO-M","Order":null,"Description":"Too Many Men","Note":null},{"Discipline":"IHO","Code_Entity":"PenaltyDesc","Code":"TRIP","Order":null,"Description":"Tripping","Note":null},{"Discipline":"IHO","Code_Entity":"PenaltyDesc","Code":"UN-SP","Order":null,"Description":"Unsportsmanlike Conduct","Note":null},{"Discipline":"IHO","Code_Entity":"Period","Code":"OT","Order":null,"Description":"Overtime","Note":null},{"Discipline":"IHO","Code_Entity":"Period","Code":"P1","Order":null,"Description":"1st Period","Note":null},{"Discipline":"IHO","Code_Entity":"Period","Code":"P2","Order":null,"Description":"2nd Period","Note":null},{"Discipline":"IHO","Code_Entity":"Period","Code":"P3","Order":null,"Description":"3rd Period","Note":null},{"Discipline":"IHO","Code_Entity":"Period","Code":"PSS","Order":null,"Description":"Game Winning Shot","Note":null},{"Discipline":"IHO","Code_Entity":"Period","Code":"TOT","Order":null,"Description":"Total","Note":null},{"Discipline":"IHO","Code_Entity":"PS_Desc","Code":"LOST_PCK","Order":null,"Description":"Lost the puck - Only for penalty shot for PSS","Note":null},{"Discipline":"IHO","Code_Entity":"PS_Desc","Code":"MISS","Order":null,"Description":"Only for penalty shot during the game","Note":null},{"Discipline":"IHO","Code_Entity":"PS_Desc","Code":"MISS_GP","Order":null,"Description":"Missed (goal post) - Only for penalty shot for PSS","Note":null},{"Discipline":"IHO","Code_Entity":"PS_Desc","Code":"MISS_H","Order":null,"Description":"Missed (height) - Only for penalty shot for PSS","Note":null},{"Discipline":"IHO","Code_Entity":"PS_Desc","Code":"MISS_L","Order":null,"Description":"Missed (left) - Only for penalty shot for PSS","Note":null},{"Discipline":"IHO","Code_Entity":"PS_Desc","Code":"MISS_R","Order":null,"Description":"Missed (right) - Only for penalty shot for PSS","Note":null},{"Discipline":"IHO","Code_Entity":"PS_Desc","Code":"SCRD","Order":null,"Description":"Scored - Only for penalty shot for PSS","Note":null},{"Discipline":"IHO","Code_Entity":"PS_Desc","Code":"SVD_GOL","Order":null,"Description":"Saved by Goalie - Only for penalty shot for PSS","Note":null},{"Discipline":"IHO","Code_Entity":"ResActionGoal","Code":"AG","Order":null,"Description":"Awarded goal","Note":null},{"Discipline":"IHO","Code_Entity":"ResActionGoal","Code":"EA","Order":null,"Description":"Extra attacker","Note":null},{"Discipline":"IHO","Code_Entity":"ResActionGoal","Code":"ENG","Order":null,"Description":"Empty net goal","Note":null},{"Discipline":"IHO","Code_Entity":"ResActionGoal","Code":"EQ","Order":null,"Description":"Equal strength","Note":null},{"Discipline":"IHO","Code_Entity":"ResActionGoal","Code":"EQ-EA","Order":null,"Description":"Equal with extra attacker","Note":null},{"Discipline":"IHO","Code_Entity":"ResActionGoal","Code":"PP1","Order":null,"Description":"Power play - 1 player","Note":null},{"Discipline":"IHO","Code_Entity":"ResActionGoal","Code":"PP1-EA","Order":null,"Description":"Power play 1 player with extra attacker","Note":null},{"Discipline":"IHO","Code_Entity":"ResActionGoal","Code":"PP1-ENG","Order":null,"Description":"Empty net goal while in Power play 1 player","Note":null},{"Discipline":"IHO","Code_Entity":"ResActionGoal","Code":"PP2","Order":null,"Description":"Power play - 2 players","Note":null},{"Discipline":"IHO","Code_Entity":"ResActionGoal","Code":"PP2-EA","Order":null,"Description":"Power play 2 players with extra attacker","Note":null},{"Discipline":"IHO","Code_Entity":"ResActionGoal","Code":"PP2-ENG","Order":null,"Description":"Empty net goal while in Power play 2 players","Note":null},{"Discipline":"IHO","Code_Entity":"ResActionGoal","Code":"PS","Order":null,"Description":"Penalty Shot","Note":null},{"Discipline":"IHO","Code_Entity":"ResActionGoal","Code":"SH1","Order":null,"Description":"Shorthanded - 1 player","Note":null},{"Discipline":"IHO","Code_Entity":"ResActionGoal","Code":"SH1-EA","Order":null,"Description":"Shorthanded 1 player with extra attacker","Note":null},{"Discipline":"IHO","Code_Entity":"ResActionGoal","Code":"SH1-ENG","Order":null,"Description":"Empty net goal while in Shorthanded 1 player ","Note":null},{"Discipline":"IHO","Code_Entity":"ResActionGoal","Code":"SH2","Order":null,"Description":"Shorthanded - 2 players","Note":null},{"Discipline":"IHO","Code_Entity":"ResActionGoal","Code":"SH2-EA","Order":null,"Description":"Shorthanded 2 players with extra attacker","Note":null},{"Discipline":"IHO","Code_Entity":"ResActionGoal","Code":"SH2-ENG","Order":null,"Description":"Empty net goal while in Shorthanded 2 players","Note":null},{"Discipline":"IHO","Code_Entity":"ResultType","Code":"IRM","Order":null,"Description":"Invalid Result Mark","Note":null},{"Discipline":"IHO","Code_Entity":"ResultType","Code":"IRM_POINTS","Order":null,"Description":"IRM with Points","Note":null},{"Discipline":"IHO","Code_Entity":"ResultType","Code":"POINTS","Order":null,"Description":"Points (or Goals)","Note":null},{"Discipline":"IHO","Code_Entity":"Statistics","Code":"CUM","Order":null,"Description":"Cumulative Statistics of team and individual","Note":null},{"Discipline":"IHO","Code_Entity":"Statistics","Code":"IND_RANKING","Order":null,"Description":"Ranking of Individual tournament statistics","Note":null},{"Discipline":"IHO","Code_Entity":"Statistics","Code":"TEAM_RANKING","Order":null,"Description":"Ranking of Team tournament statistics","Note":null},{"Discipline":"IHO","Code_Entity":"Statistics","Code":"TOU","Order":null,"Description":"Tournament Statistics","Note":null},{"Discipline":"IHO","Code_Entity":"WLT","Code":"L","Order":null,"Description":"Lost","Note":null},{"Discipline":"IHO","Code_Entity":"WLT","Code":"T","Order":null,"Description":"Tie","Note":null},{"Discipline":"IHO","Code_Entity":"WLT","Code":"W","Order":null,"Description":"Won","Note":null},{"Discipline":"LUG","Code_Entity":"IRM","Code":"DNF","Order":null,"Description":"Did not Finish","Note":null},{"Discipline":"LUG","Code_Entity":"IRM","Code":"DNS","Order":null,"Description":"Did not Start","Note":null},{"Discipline":"LUG","Code_Entity":"IRM","Code":"DQB","Order":null,"Description":"Disqualified (Behaviour)","Note":null},{"Discipline":"LUG","Code_Entity":"IRM","Code":"DSQ","Order":null,"Description":"Disqualified","Note":null},{"Discipline":"LUG","Code_Entity":"ResultType","Code":"IRM","Order":null,"Description":"Invalid Result Mark","Note":null},{"Discipline":"LUG","Code_Entity":"ResultType","Code":"TIME","Order":null,"Description":"Time","Note":null},{"Discipline":"LUG","Code_Entity":"StartText","Code":"After Heat 1","Order":null,"Description":null,"Note":null},{"Discipline":"LUG","Code_Entity":"StartText","Code":"After Heat 3","Order":null,"Description":null,"Note":null},{"Discipline":"LUG","Code_Entity":"StartText","Code":"After Training 1","Order":null,"Description":null,"Note":null},{"Discipline":"LUG","Code_Entity":"StartText","Code":"After Training 3","Order":null,"Description":null,"Note":null},{"Discipline":"LUG","Code_Entity":"StartText","Code":"After Training 5","Order":null,"Description":null,"Note":null},{"Discipline":"LUG","Code_Entity":"StartText","Code":"Followed by","Order":null,"Description":null,"Note":null},{"Discipline":"NCB","Code_Entity":"HillType","Code":"LH","Order":null,"Description":"Large Hill (SJP)","Note":null},{"Discipline":"NCB","Code_Entity":"HillType","Code":"NH","Order":null,"Description":"Normal Hill (SJP)","Note":null},{"Discipline":"NCB","Code_Entity":"IRM","Code":"DNF","Order":null,"Description":"Did not finish (CCS)","Note":null},{"Discipline":"NCB","Code_Entity":"IRM","Code":"DNS","Order":null,"Description":"Did not Start (SJP, CCS)","Note":null},{"Discipline":"NCB","Code_Entity":"IRM","Code":"DQB","Order":null,"Description":"Disqualified (Behaviour) (SJP, CCS)","Note":null},{"Discipline":"NCB","Code_Entity":"IRM","Code":"DSQ","Order":null,"Description":"Disqualified (SJP, CCS)","Note":null},{"Discipline":"NCB","Code_Entity":"IRM","Code":"LAP","Order":null,"Description":"Lapped (CCS)","Note":null},{"Discipline":"NCB","Code_Entity":"ResultType","Code":"IRM","Order":null,"Description":"Invalid Result Mark (SJP, CCS)","Note":null},{"Discipline":"NCB","Code_Entity":"ResultType","Code":"POINTS","Order":null,"Description":"Points (SJP)","Note":null},{"Discipline":"NCB","Code_Entity":"ResultType","Code":"TIME","Order":null,"Description":"Time (CCS)","Note":null},{"Discipline":"NCB","Code_Entity":"StartText","Code":"After Jump 1","Order":null,"Description":null,"Note":null},{"Discipline":"NCB","Code_Entity":"StartText","Code":"After Jump 2","Order":null,"Description":null,"Note":null},{"Discipline":"SBD","Code_Entity":"BibColour","Code":"BLACK","Order":null,"Description":"Black","Note":null},{"Discipline":"SBD","Code_Entity":"BibColour","Code":"BLUE","Order":null,"Description":"Blue","Note":null},{"Discipline":"SBD","Code_Entity":"BibColour","Code":"GREEN","Order":null,"Description":"Green","Note":null},{"Discipline":"SBD","Code_Entity":"BibColour","Code":"RED","Order":null,"Description":"Red","Note":null},{"Discipline":"SBD","Code_Entity":"BibColour","Code":"WHITE","Order":null,"Description":"White","Note":null},{"Discipline":"SBD","Code_Entity":"BibColour","Code":"YELLOW","Order":null,"Description":"Yellow","Note":null},{"Discipline":"SBD","Code_Entity":"Bracket","Code":"BRN","Order":null,"Description":"Bronze (Small final in Parallel)","Note":null},{"Discipline":"SBD","Code_Entity":"Bracket","Code":"CFNL","Order":null,"Description":"Final (Small Final in SBX)","Note":null},{"Discipline":"SBD","Code_Entity":"Bracket","Code":"FNL","Order":null,"Description":"Final","Note":null},{"Discipline":"SBD","Code_Entity":"BracketItems","Code":"8FNL","Order":null,"Description":"Eight Finals (Round of 16)","Note":null},{"Discipline":"SBD","Code_Entity":"BracketItems","Code":"FNL","Order":null,"Description":"Final","Note":null},{"Discipline":"SBD","Code_Entity":"BracketItems","Code":"QFNL","Order":null,"Description":"Quarterfinal","Note":null},{"Discipline":"SBD","Code_Entity":"BracketItems","Code":"SFNL","Order":null,"Description":"Semifinal","Note":null},{"Discipline":"SBD","Code_Entity":"Foot","Code":"G","Order":null,"Description":"Goofy","Note":null},{"Discipline":"SBD","Code_Entity":"Foot","Code":"R","Order":null,"Description":"Regular","Note":null},{"Discipline":"SBD","Code_Entity":"IRM","Code":"DNF","Order":null,"Description":"Did not Finish","Note":null},{"Discipline":"SBD","Code_Entity":"IRM","Code":"DNS","Order":null,"Description":"Did not Start","Note":null},{"Discipline":"SBD","Code_Entity":"IRM","Code":"DQB","Order":null,"Description":"Disqualified (Behaviour)","Note":null},{"Discipline":"SBD","Code_Entity":"IRM","Code":"DSQ","Order":null,"Description":"Disqualified","Note":null},{"Discipline":"SBD","Code_Entity":"IRM","Code":"JNS","Order":null,"Description":"Jump not Scored ???? (used in cumulative only)","Note":null},{"Discipline":"SBD","Code_Entity":"IRM","Code":"REL","Order":null,"Description":"Relegated","Note":null},{"Discipline":"SBD","Code_Entity":"JudgeType","Code":"OVER","Order":null,"Description":"Overall","Note":null},{"Discipline":"SBD","Code_Entity":"JudgeType","Code":"P1","Order":null,"Description":"Panel 1","Note":null},{"Discipline":"SBD","Code_Entity":"JudgeType","Code":"P2","Order":null,"Description":"Panel 2","Note":null},{"Discipline":"SBD","Code_Entity":"QualificationMark","Code":"FA","Order":null,"Description":"Qualified for Big Final","Note":null},{"Discipline":"SBD","Code_Entity":"QualificationMark","Code":"FB","Order":null,"Description":"Qualified for Small Final","Note":null},{"Discipline":"SBD","Code_Entity":"QualificationMark","Code":"Q","Order":null,"Description":"Qualified","Note":null},{"Discipline":"SBD","Code_Entity":"QualificationMark","Code":"QF","Order":null,"Description":"Qualified for Final","Note":null},{"Discipline":"SBD","Code_Entity":"QualificationMark","Code":"QS","Order":null,"Description":"Qualified for Semifinal","Note":null},{"Discipline":"SBD","Code_Entity":"ResultType","Code":"CODE","Order":null,"Description":"Code (used in event final ranking)","Note":null},{"Discipline":"SBD","Code_Entity":"ResultType","Code":"IRM","Order":null,"Description":"Invalid Result Mark","Note":null},{"Discipline":"SBD","Code_Entity":"ResultType","Code":"POINTS","Order":null,"Description":"Points","Note":null},{"Discipline":"SBD","Code_Entity":"ResultType","Code":"RANK","Order":null,"Description":"Rank-only result used in all SBX Finals phases","Note":null},{"Discipline":"SBD","Code_Entity":"ResultType","Code":"TIME","Order":null,"Description":"Time","Note":null},{"Discipline":"SBD","Code_Entity":"StartText","Code":"After Heat 1 Run 1","Order":null,"Description":null,"Note":null},{"Discipline":"SBD","Code_Entity":"StartText","Code":"After Heat 2 Run 1","Order":null,"Description":null,"Note":null},{"Discipline":"SBD","Code_Entity":"StartText","Code":"After Qualif. Run","Order":null,"Description":null,"Note":null},{"Discipline":"SBD","Code_Entity":"StartText","Code":"After Run 1","Order":null,"Description":null,"Note":null},{"Discipline":"SJP","Code_Entity":"HillType","Code":"LH","Order":null,"Description":"Large Hill","Note":null},{"Discipline":"SJP","Code_Entity":"HillType","Code":"NH","Order":null,"Description":"Normal Hill","Note":null},{"Discipline":"SJP","Code_Entity":"IRM","Code":"DNS","Order":null,"Description":"Did not Start","Note":null},{"Discipline":"SJP","Code_Entity":"IRM","Code":"DQB","Order":null,"Description":"Disqualified (Behaviour)","Note":null},{"Discipline":"SJP","Code_Entity":"IRM","Code":"DSQ","Order":null,"Description":"Disqualified","Note":null},{"Discipline":"SJP","Code_Entity":"QualificationMark","Code":"PQ","Order":null,"Description":"Prequalified","Note":null},{"Discipline":"SJP","Code_Entity":"QualificationMark","Code":"Q","Order":null,"Description":"Qualified","Note":null},{"Discipline":"SJP","Code_Entity":"QualificationMark","Code":"q","Order":null,"Description":"Qualified by rule","Note":null},{"Discipline":"SJP","Code_Entity":"ResultType","Code":"IRM","Order":null,"Description":"Invalid Result Mark","Note":null},{"Discipline":"SJP","Code_Entity":"ResultType","Code":"POINTS","Order":null,"Description":"Points","Note":null},{"Discipline":"SJP","Code_Entity":"ResultType","Code":"PREQUALIFIED","Order":null,"Description":"Pre-qualified jumpers in the Qualification, which will not get points+rank","Note":null},{"Discipline":"SJP","Code_Entity":"StartText","Code":"Followed by","Order":null,"Description":null,"Note":null},{"Discipline":"SKN","Code_Entity":"IRM","Code":"DNF","Order":null,"Description":"Did not Finish","Note":null},{"Discipline":"SKN","Code_Entity":"IRM","Code":"DNS","Order":null,"Description":"Did not Start","Note":null},{"Discipline":"SKN","Code_Entity":"IRM","Code":"DQB","Order":null,"Description":"Disqualified (Behaviour)","Note":null},{"Discipline":"SKN","Code_Entity":"IRM","Code":"DSQ","Order":null,"Description":"Disqualified","Note":null},{"Discipline":"SKN","Code_Entity":"QualificationMark","Code":"Q","Order":null,"Description":"Qualified (to participate in the last heat)","Note":null},{"Discipline":"SKN","Code_Entity":"ResultType","Code":"IRM","Order":null,"Description":"Invalid Result Mark","Note":null},{"Discipline":"SKN","Code_Entity":"ResultType","Code":"TIME","Order":null,"Description":"Time","Note":null},{"Discipline":"SKN","Code_Entity":"StartText","Code":"After Heat 1","Order":null,"Description":null,"Note":null},{"Discipline":"SKN","Code_Entity":"StartText","Code":"After Heat 3","Order":null,"Description":null,"Note":null},{"Discipline":"SKN","Code_Entity":"StartText","Code":"After Training 1","Order":null,"Description":null,"Note":null},{"Discipline":"SKN","Code_Entity":"StartText","Code":"After Training 3","Order":null,"Description":null,"Note":null},{"Discipline":"SKN","Code_Entity":"StartText","Code":"After Training 5","Order":null,"Description":null,"Note":null},{"Discipline":"SKN","Code_Entity":"StartText","Code":"Followed by","Order":null,"Description":null,"Note":null},{"Discipline":"SSK","Code_Entity":"Bracket","Code":"BRN","Order":null,"Description":"Bronze (Final B))","Note":null},{"Discipline":"SSK","Code_Entity":"Bracket","Code":"FNL","Order":null,"Description":"Finals","Note":null},{"Discipline":"SSK","Code_Entity":"Bracket","Code":"FNLC","Order":null,"Description":"Final C","Note":null},{"Discipline":"SSK","Code_Entity":"Bracket","Code":"FNLD","Order":null,"Description":"Final D","Note":null},{"Discipline":"SSK","Code_Entity":"BracketItems","Code":"FNL","Order":null,"Description":"Final","Note":null},{"Discipline":"SSK","Code_Entity":"BracketItems","Code":"QFNL","Order":null,"Description":"Quarterfinal","Note":null},{"Discipline":"SSK","Code_Entity":"BracketItems","Code":"SFNL","Order":null,"Description":"Semifinal","Note":null},{"Discipline":"SSK","Code_Entity":"IRM","Code":"DNF","Order":null,"Description":"Did not finish","Note":null},{"Discipline":"SSK","Code_Entity":"IRM","Code":"DNS","Order":null,"Description":"Did not start","Note":null},{"Discipline":"SSK","Code_Entity":"IRM","Code":"DQB","Order":null,"Description":"Disqualified (Behaviour)","Note":null},{"Discipline":"SSK","Code_Entity":"IRM","Code":"DSQ","Order":null,"Description":"Disqualified","Note":null},{"Discipline":"SSK","Code_Entity":"IRM","Code":"LOT","Order":null,"Description":"Loser by being Overtaken by the other Team. Used just in the Pursuit event","Note":null},{"Discipline":"SSK","Code_Entity":"IRM","Code":"WDR","Order":null,"Description":"Withdrawn","Note":null},{"Discipline":"SSK","Code_Entity":"IRM","Code":"WO","Order":null,"Description":"Walkover (opponent doesn't show). Used just in the Pursuit event","Note":null},{"Discipline":"SSK","Code_Entity":"IRM","Code":"WOT","Order":null,"Description":"Winner by Overtaking the other Team. Used just in the Pursuit event.","Note":null},{"Discipline":"SSK","Code_Entity":"QualificationMark","Code":"FA","Order":null,"Description":"Qualified for Final A","Note":null},{"Discipline":"SSK","Code_Entity":"QualificationMark","Code":"FB","Order":null,"Description":"Qualified for Final B","Note":null},{"Discipline":"SSK","Code_Entity":"QualificationMark","Code":"FC","Order":null,"Description":"Qualified for Final C","Note":null},{"Discipline":"SSK","Code_Entity":"QualificationMark","Code":"FD","Order":null,"Description":"Qualified for Final D","Note":null},{"Discipline":"SSK","Code_Entity":"QualificationMark","Code":"SF1","Order":null,"Description":"Qualified for Semifinal 1","Note":null},{"Discipline":"SSK","Code_Entity":"QualificationMark","Code":"SF2","Order":null,"Description":"Qualified for Semifinal 2","Note":null},{"Discipline":"SSK","Code_Entity":"ResultType","Code":"IRM","Order":null,"Description":"Invalid Result Mark","Note":null},{"Discipline":"SSK","Code_Entity":"ResultType","Code":"POINTS","Order":null,"Description":"Points","Note":null},{"Discipline":"SSK","Code_Entity":"ResultType","Code":"TIME","Order":null,"Description":"Time","Note":null},{"Discipline":"STK","Code_Entity":"IRM","Code":"DNF","Order":null,"Description":"Did not Finish","Note":null},{"Discipline":"STK","Code_Entity":"IRM","Code":"DNS","Order":null,"Description":"Did not Start","Note":null},{"Discipline":"STK","Code_Entity":"IRM","Code":"DQB","Order":null,"Description":"Disqualified (Behaviour)","Note":null},{"Discipline":"STK","Code_Entity":"IRM","Code":"DSQ","Order":null,"Description":"Disqualified","Note":null},{"Discipline":"STK","Code_Entity":"IRM","Code":"PEN","Order":null,"Description":"Penalty","Note":null},{"Discipline":"STK","Code_Entity":"IRM","Code":"RC","Order":null,"Description":"Red Card","Note":null},{"Discipline":"STK","Code_Entity":"IRM","Code":"YC","Order":null,"Description":"Yellow Card","Note":null},{"Discipline":"STK","Code_Entity":"QualificationMark","Code":"ADV","Order":null,"Description":"Advanced","Note":null},{"Discipline":"STK","Code_Entity":"QualificationMark","Code":"ADVA","Order":null,"Description":"Advanced to final A (for semi-final results only)","Note":null},{"Discipline":"STK","Code_Entity":"QualificationMark","Code":"ADVB","Order":null,"Description":"Advanced to final B (for semi-final results only)","Note":null},{"Discipline":"STK","Code_Entity":"QualificationMark","Code":"Q","Order":null,"Description":"Qualified (for all phases before semi-final results only)","Note":null},{"Discipline":"STK","Code_Entity":"QualificationMark","Code":"QA","Order":null,"Description":"Qualified for Final A","Note":null},{"Discipline":"STK","Code_Entity":"QualificationMark","Code":"QB","Order":null,"Description":"Qualified for Final B","Note":null},{"Discipline":"STK","Code_Entity":"QualificationMark","Code":"QT","Order":null,"Description":"Qualified by time (Qualified as a fastest third place skater)","Note":null},{"Discipline":"STK","Code_Entity":"ResultPhase","Code":"FNL","Order":null,"Description":"Finals","Note":null},{"Discipline":"STK","Code_Entity":"ResultPhase","Code":"HEAT","Order":null,"Description":"Heats","Note":null},{"Discipline":"STK","Code_Entity":"ResultPhase","Code":"QFNL","Order":null,"Description":"Quarterfinals","Note":null},{"Discipline":"STK","Code_Entity":"ResultPhase","Code":"SFNL","Order":null,"Description":"Semifinals","Note":null},{"Discipline":"STK","Code_Entity":"ResultType","Code":"IRM","Order":null,"Description":"Invalid Result Mark","Note":null},{"Discipline":"STK","Code_Entity":"ResultType","Code":"NO_TIME","Order":null,"Description":"No Time","Note":null},{"Discipline":"STK","Code_Entity":"ResultType","Code":"TIME","Order":null,"Description":"Time","Note":null}]