[{"Id":"FOC","ENG Description":"Future Organizing Committees","FRA Description":"Futurs comités d'organisation","KOR Description":"향후 조직위원회"},{"Id":"GOV","ENG Description":"Korean Government","FRA Description":"Gouvernement coréen","KOR Description":"대한민국 정부"},{"Id":"IF","ENG Description":"International Federations","FRA Description":"Fédérations Internationales","KOR Description":"국제연맹"},{"Id":"IOC","ENG Description":"Int. Olympic Committee","FRA Description":"Comité International Olympique","KOR Description":"국제 올림픽 위원회"},{"Id":"IPC","ENG Description":"Int. Paralympic Committee","FRA Description":"C. International Paralympique","KOR Description":"국제 장애인올림픽 위원회 "},{"Id":"NGB","ENG Description":"National Governing Body","FRA Description":"Autorité régulatrice nationale","KOR Description":"국가 관리기구"},{"Id":"NOC","ENG Description":"National Olympic Committees","FRA Description":"Comités Nationaux Olympiques","KOR Description":"국가별 올림픽 위원회 "},{"Id":"NPC","ENG Description":"National Paralympic Committees","FRA Description":"Comt. Nationaux Paralympiques","KOR Description":"국가별 장애인올림픽 위원회 "},{"Id":"OC","ENG Description":"Organizing Committee","FRA Description":"Comité d'organisation","KOR Description":"조직 위원회"},{"Id":"ORG","ENG Description":"Korean Organisation","FRA Description":"Organisation coréenne","KOR Description":"한국 조직위"}]