[{"Code":"AIBA","Type":"IF","ENG Name":"Int. Boxing Assoc.","ENG Short Name":"AIBA"},{"Code":"BWF","Type":"IF","ENG Name":"Badminton World Federation","ENG Short Name":"BWF"},{"Code":"FEI","Type":"IF","ENG Name":"Int. Equestrian Federation","ENG Short Name":"FEI"},{"Code":"FIBA","Type":"IF","ENG Name":"International Basketball Fed.","ENG Short Name":"FIBA"},{"Code":"FIE","Type":"IF","ENG Name":"Fed. Int. d'Escrime","ENG Short Name":"FIE"},{"Code":"FIFA","Type":"IF","ENG Name":"Fed. Int. de Football Ass.","ENG Short Name":"FIFA"},{"Code":"FIG","Type":"IF","ENG Name":"Int. Gymnastics Federation","ENG Short Name":"FIG"},{"Code":"FIH","Type":"IF","ENG Name":"Int. Hockey Federation","ENG Short Name":"FIH"},{"Code":"FILA","Type":"IF","ENG Name":"Int.Fed Ass. Wrestling Styles","ENG Short Name":"FILA"},{"Code":"FINA","Type":"IF","ENG Name":"Fed. Int. de Natation","ENG Short Name":"FINA"},{"Code":"FISA","Type":"IF","ENG Name":"Int. Rowing Federation","ENG Short Name":"FISA"},{"Code":"WA","Type":"IF","ENG Name":"World Archery Fed.","ENG Short Name":"WA"},{"Code":"FIVB","Type":"IF","ENG Name":"Int. Volleyball Federation","ENG Short Name":"FIVB"},{"Code":"IAAF","Type":"IF","ENG Name":"Int.Ass.of Athletic Fed.","ENG Short Name":"IAAF"},{"Code":"ICF","Type":"IF","ENG Name":"International Canoe Federation","ENG Short Name":"ICF"},{"Code":"IHF","Type":"IF","ENG Name":"Int. Handball Federation","ENG Short Name":"IHF"},{"Code":"IJF","Type":"IF","ENG Name":"Int. Judo Federation","ENG Short Name":"IJF"},{"Code":"ISAF","Type":"IF","ENG Name":"Int. Sailing Federation","ENG Short Name":"ISAF"},{"Code":"ISSF","Type":"IF","ENG Name":"Int. Shooting Sport Fed.","ENG Short Name":"ISSF"},{"Code":"ITF","Type":"IF","ENG Name":"Int. Tennis Federation","ENG Short Name":"ITF"},{"Code":"ITTF","Type":"IF","ENG Name":"Int. Table Tennis Federation","ENG Short Name":"ITTF"},{"Code":"ITU","Type":"IF","ENG Name":"Int. Triathlon Union","ENG Short Name":"ITU"},{"Code":"IWF","Type":"IF","ENG Name":"Int. Weightlifting Federation","ENG Short Name":"IWF"},{"Code":"UCI","Type":"IF","ENG Name":"International Cycling Union","ENG Short Name":"UCI"},{"Code":"UIPM","Type":"IF","ENG Name":"International Modern Pentathlon Union","ENG Short Name":"UIPM"},{"Code":"WTF","Type":"IF","ENG Name":"The World Taekwondo Federation","ENG Short Name":"WTF"},{"Code":"WAE","Type":"EF","ENG Name":"World Archery Europe","ENG Short Name":"WAE"},{"Code":"LEN","Type":"EF","ENG Name":"Ligue Européenne de Natation","ENG Short Name":"LEN"},{"Code":"BEC","Type":"EF","ENG Name":"Badminton Europe Confederation","ENG Short Name":"BEC"},{"Code":"FIBAE","Type":"EF","ENG Name":"FIBA Europe","ENG Short Name":"FIBAE"},{"Code":"FBSSL","Type":"EF","ENG Name":"Beach Soccer Worldwide","ENG Short Name":"FBSSL"},{"Code":"EUBC","Type":"EF","ENG Name":"European Boxing Confederation","ENG Short Name":"EUBC"},{"Code":"ECA","Type":"EF","ENG Name":"European Canoeing Association","ENG Short Name":"ECA"},{"Code":"UEC","Type":"EF","ENG Name":"European Cycling Union","ENG Short Name":"UEC"},{"Code":"EFC","Type":"EF","ENG Name":"European Fencing Confederation","ENG Short Name":"EFC"},{"Code":"UEG","Type":"EF","ENG Name":"The European Union of Gymnastics","ENG Short Name":"UEG"},{"Code":"EJU","Type":"EF","ENG Name":"European Judo Union","ENG Short Name":"EJU"},{"Code":"EKF","Type":"EF","ENG Name":"European Karate Federation","ENG Short Name":"EKF"},{"Code":"ESC","Type":"EF","ENG Name":"European Shooting Confederation","ENG Short Name":"ESC"},{"Code":"ETTU","Type":"EF","ENG Name":"European Table Tennis Union","ENG Short Name":"ETTU"},{"Code":"ETUTK","Type":"EF","ENG Name":"European Taekwondo Union","ENG Short Name":"ETUTK"},{"Code":"ETUTR","Type":"EF","ENG Name":"European Triathlon Union","ENG Short Name":"ETUTR"},{"Code":"CEV","Type":"EF","ENG Name":"European Volleyball Confederation","ENG Short Name":"CEV"},{"Code":"FILA","Type":"EF","ENG Name":"Int.Fed Ass. Wrestling Styles","ENG Short Name":"FILA"}]