[{"Class":"ST","Discipline":"AR","ENG Description":"Standing","POR Description":"Em pé","SPA Description":"De pie"},{"Class":"W1","Discipline":"AR","ENG Description":"W1","POR Description":"W1","SPA Description":"W1"},{"Class":"W2","Discipline":"AR","ENG Description":"W2","POR Description":"W2","SPA Description":"W2"},{"Class":"F11","Discipline":"AT","ENG Description":"F11","POR Description":"F11","SPA Description":"F11"},{"Class":"F12","Discipline":"AT","ENG Description":"F12","POR Description":"F12","SPA Description":"F12"},{"Class":"F13","Discipline":"AT","ENG Description":"F13","POR Description":"F13","SPA Description":"F13"},{"Class":"F20","Discipline":"AT","ENG Description":"F20","POR Description":"F20","SPA Description":"F20"},{"Class":"F31","Discipline":"AT","ENG Description":"F31","POR Description":"F31","SPA Description":"F31"},{"Class":"F32","Discipline":"AT","ENG Description":"F32","POR Description":"F32","SPA Description":"F32"},{"Class":"F33","Discipline":"AT","ENG Description":"F33","POR Description":"F33","SPA Description":"F33"},{"Class":"F34","Discipline":"AT","ENG Description":"F34","POR Description":"F34","SPA Description":"F34"},{"Class":"F35","Discipline":"AT","ENG Description":"F35","POR Description":"F35","SPA Description":"F35"},{"Class":"F36","Discipline":"AT","ENG Description":"F36","POR Description":"F36","SPA Description":"F36"},{"Class":"F37","Discipline":"AT","ENG Description":"F37","POR Description":"F37","SPA Description":"F37"},{"Class":"F38","Discipline":"AT","ENG Description":"F38","POR Description":"F38","SPA Description":"F38"},{"Class":"F40","Discipline":"AT","ENG Description":"F40","POR Description":"F40","SPA Description":"F40"},{"Class":"F41","Discipline":"AT","ENG Description":"F41","POR Description":"F41","SPA Description":"F41"},{"Class":"F42","Discipline":"AT","ENG Description":"F42","POR Description":"F42","SPA Description":"F42"},{"Class":"F43","Discipline":"AT","ENG Description":"F43","POR Description":"F43","SPA Description":"F43"},{"Class":"F44","Discipline":"AT","ENG Description":"F44","POR Description":"F44","SPA Description":"F44"},{"Class":"F45","Discipline":"AT","ENG Description":"F45","POR Description":"F45","SPA Description":"F45"},{"Class":"F46","Discipline":"AT","ENG Description":"F46","POR Description":"F46","SPA Description":"F46"},{"Class":"F51","Discipline":"AT","ENG Description":"F51","POR Description":"F51","SPA Description":"F51"},{"Class":"F52","Discipline":"AT","ENG Description":"F52","POR Description":"F52","SPA Description":"F52"},{"Class":"F53","Discipline":"AT","ENG Description":"F53","POR Description":"F53","SPA Description":"F53"},{"Class":"F54","Discipline":"AT","ENG Description":"F54","POR Description":"F54","SPA Description":"F54"},{"Class":"F55","Discipline":"AT","ENG Description":"F55","POR Description":"F55","SPA Description":"F55"},{"Class":"F56","Discipline":"AT","ENG Description":"F56","POR Description":"F56","SPA Description":"F56"},{"Class":"F57","Discipline":"AT","ENG Description":"F57","POR Description":"F57","SPA Description":"F57"},{"Class":"GUI","Discipline":"AT","ENG Description":"Guide","POR Description":"Guia","SPA Description":"Guía"},{"Class":"T11","Discipline":"AT","ENG Description":"T11","POR Description":"T11","SPA Description":"T11"},{"Class":"T12","Discipline":"AT","ENG Description":"T12","POR Description":"T12","SPA Description":"T12"},{"Class":"T13","Discipline":"AT","ENG Description":"T13","POR Description":"T13","SPA Description":"T13"},{"Class":"T20","Discipline":"AT","ENG Description":"T20","POR Description":"T20","SPA Description":"T20"},{"Class":"T33","Discipline":"AT","ENG Description":"T33","POR Description":"T33","SPA Description":"T33"},{"Class":"T34","Discipline":"AT","ENG Description":"T34","POR Description":"T34","SPA Description":"T34"},{"Class":"T35","Discipline":"AT","ENG Description":"T35","POR Description":"T35","SPA Description":"T35"},{"Class":"T36","Discipline":"AT","ENG Description":"T36","POR Description":"T36","SPA Description":"T36"},{"Class":"T37","Discipline":"AT","ENG Description":"T37","POR Description":"T37","SPA Description":"T37"},{"Class":"T38","Discipline":"AT","ENG Description":"T38","POR Description":"T38","SPA Description":"T38"},{"Class":"T42","Discipline":"AT","ENG Description":"T42","POR Description":"T42","SPA Description":"T42"},{"Class":"T43","Discipline":"AT","ENG Description":"T43","POR Description":"T43","SPA Description":"T43"},{"Class":"T44","Discipline":"AT","ENG Description":"T44","POR Description":"T44","SPA Description":"T44"},{"Class":"T45","Discipline":"AT","ENG Description":"T45","POR Description":"T45","SPA Description":"T45"},{"Class":"T46","Discipline":"AT","ENG Description":"T46","POR Description":"T46","SPA Description":"T46"},{"Class":"T47","Discipline":"AT","ENG Description":"T47","POR Description":"T47","SPA Description":"T47"},{"Class":"T51","Discipline":"AT","ENG Description":"T51","POR Description":"T51","SPA Description":"T51"},{"Class":"T52","Discipline":"AT","ENG Description":"T52","POR Description":"T52","SPA Description":"T52"},{"Class":"T53","Discipline":"AT","ENG Description":"T53","POR Description":"T53","SPA Description":"T53"},{"Class":"T54","Discipline":"AT","ENG Description":"T54","POR Description":"T54","SPA Description":"T54"},{"Class":"BC1","Discipline":"BO","ENG Description":"BC1","POR Description":"BC1","SPA Description":"BC1"},{"Class":"BC2","Discipline":"BO","ENG Description":"BC2","POR Description":"BC2","SPA Description":"BC2"},{"Class":"BC3","Discipline":"BO","ENG Description":"BC3","POR Description":"BC3","SPA Description":"BC3"},{"Class":"BC4","Discipline":"BO","ENG Description":"BC4","POR Description":"BC4","SPA Description":"BC4"},{"Class":"KL1","Discipline":"CF","ENG Description":"KL1","POR Description":"KL1","SPA Description":"KL1"},{"Class":"KL2","Discipline":"CF","ENG Description":"KL2","POR Description":"KL2","SPA Description":"KL2"},{"Class":"KL3","Discipline":"CF","ENG Description":"KL3","POR Description":"KL3","SPA Description":"KL3"},{"Class":"B","Discipline":"CR","ENG Description":"B","POR Description":"B","SPA Description":"B"},{"Class":"B1","Discipline":"CR","ENG Description":"B1","POR Description":"B1","SPA Description":"B1"},{"Class":"B2","Discipline":"CR","ENG Description":"B2","POR Description":"B2","SPA Description":"B2"},{"Class":"B3","Discipline":"CR","ENG Description":"B3","POR Description":"B3","SPA Description":"B3"},{"Class":"C1","Discipline":"CR","ENG Description":"C1","POR Description":"C1","SPA Description":"C1"},{"Class":"C2","Discipline":"CR","ENG Description":"C2","POR Description":"C2","SPA Description":"C2"},{"Class":"C3","Discipline":"CR","ENG Description":"C3","POR Description":"C3","SPA Description":"C3"},{"Class":"C4","Discipline":"CR","ENG Description":"C4","POR Description":"C4","SPA Description":"C4"},{"Class":"C5","Discipline":"CR","ENG Description":"C5","POR Description":"C5","SPA Description":"C5"},{"Class":"H1","Discipline":"CR","ENG Description":"H1","POR Description":"H1","SPA Description":"H1"},{"Class":"H2","Discipline":"CR","ENG Description":"H2","POR Description":"H2","SPA Description":"H2"},{"Class":"H3","Discipline":"CR","ENG Description":"H3","POR Description":"H3","SPA Description":"H3"},{"Class":"H4","Discipline":"CR","ENG Description":"H4","POR Description":"H4","SPA Description":"H4"},{"Class":"H5","Discipline":"CR","ENG Description":"H5","POR Description":"H5","SPA Description":"H5"},{"Class":"PLT","Discipline":"CR","ENG Description":"Pilot","POR Description":"Piloto","SPA Description":"Piloto"},{"Class":"T1","Discipline":"CR","ENG Description":"T1","POR Description":"T1","SPA Description":"T1"},{"Class":"T2","Discipline":"CR","ENG Description":"T2","POR Description":"T2","SPA Description":"T2"},{"Class":"B","Discipline":"CT","ENG Description":"B","POR Description":"B","SPA Description":"B"},{"Class":"B1","Discipline":"CT","ENG Description":"B1","POR Description":"B1","SPA Description":"B1"},{"Class":"B2","Discipline":"CT","ENG Description":"B2","POR Description":"B2","SPA Description":"B2"},{"Class":"B3","Discipline":"CT","ENG Description":"B3","POR Description":"B3","SPA Description":"B3"},{"Class":"C1","Discipline":"CT","ENG Description":"C1","POR Description":"C1","SPA Description":"C1"},{"Class":"C2","Discipline":"CT","ENG Description":"C2","POR Description":"C2","SPA Description":"C2"},{"Class":"C3","Discipline":"CT","ENG Description":"C3","POR Description":"C3","SPA Description":"C3"},{"Class":"C4","Discipline":"CT","ENG Description":"C4","POR Description":"C4","SPA Description":"C4"},{"Class":"C5","Discipline":"CT","ENG Description":"C5","POR Description":"C5","SPA Description":"C5"},{"Class":"PLT","Discipline":"CT","ENG Description":"Pilot","POR Description":"Piloto","SPA Description":"Piloto"},{"Class":"GIA","Discipline":"EQ","ENG Description":"Grade I","POR Description":"Grau I","SPA Description":"Grado I"},{"Class":"GIB","Discipline":"EQ","ENG Description":"Grade Ib","POR Description":"Grau Ib","SPA Description":"Grado Ib"},{"Class":"GII","Discipline":"EQ","ENG Description":"Grade II","POR Description":"Grau II","SPA Description":"Grado II"},{"Class":"GIII","Discipline":"EQ","ENG Description":"Grade III","POR Description":"Grau III","SPA Description":"Grado III"},{"Class":"GIV","Discipline":"EQ","ENG Description":"Grade IV","POR Description":"Grau IV","SPA Description":"Grado IV"},{"Class":"B1","Discipline":"FB","ENG Description":"B1","POR Description":"B1","SPA Description":"B1"},{"Class":"B2","Discipline":"FB","ENG Description":"B2","POR Description":"B2","SPA Description":"B2"},{"Class":"B3","Discipline":"FB","ENG Description":"B3","POR Description":"B3","SPA Description":"B3"},{"Class":"GK","Discipline":"FB","ENG Description":"Goalkeeper","POR Description":"Goleiro","SPA Description":"Portero"},{"Class":"FT5","Discipline":"FT","ENG Description":"FT5","POR Description":"FT5","SPA Description":"FT5"},{"Class":"FT6","Discipline":"FT","ENG Description":"FT6","POR Description":"FT6","SPA Description":"FT6"},{"Class":"FT7","Discipline":"FT","ENG Description":"FT7","POR Description":"FT7","SPA Description":"FT7"},{"Class":"FT8","Discipline":"FT","ENG Description":"FT8","POR Description":"FT8","SPA Description":"FT8"},{"Class":"B1","Discipline":"GB","ENG Description":"B1","POR Description":"B1","SPA Description":"B1"},{"Class":"B2","Discipline":"GB","ENG Description":"B2","POR Description":"B2","SPA Description":"B2"},{"Class":"B3","Discipline":"GB","ENG Description":"B3","POR Description":"B3","SPA Description":"B3"},{"Class":"B1","Discipline":"JU","ENG Description":"B1","POR Description":"B1","SPA Description":"B1"},{"Class":"B1D","Discipline":"JU","ENG Description":"Blind 1 and Deaf","POR Description":"B1D","SPA Description":"B1D"},{"Class":"B2","Discipline":"JU","ENG Description":"B2","POR Description":"B2","SPA Description":"B2"},{"Class":"B2D","Discipline":"JU","ENG Description":"Blind 2 and Deaf","POR Description":"B2D","SPA Description":"B2D"},{"Class":"B3","Discipline":"JU","ENG Description":"B3","POR Description":"B3","SPA Description":"B3"},{"Class":"B3D","Discipline":"JU","ENG Description":"Blind 3 and Deaf","POR Description":"B3D","SPA Description":"B3D"},{"Class":"PO","Discipline":"PO","ENG Description":"PO","POR Description":"PO","SPA Description":"PO"},{"Class":"AS","Discipline":"RO","ENG Description":"AS","POR Description":"AS","SPA Description":"AS"},{"Class":"CXW","Discipline":"RO","ENG Description":"Coxswain","POR Description":"Timoneiro","SPA Description":"Timonel"},{"Class":"LTAB1","Discipline":"RO","ENG Description":"LTA B1","POR Description":"LTA B1","SPA Description":"LTA B1"},{"Class":"LTAB2","Discipline":"RO","ENG Description":"LTA B2","POR Description":"LTA B2","SPA Description":"LTA B2"},{"Class":"LTAB3","Discipline":"RO","ENG Description":"LTA B3","POR Description":"LTA B3","SPA Description":"LTA B3"},{"Class":"LTAID","Discipline":"RO","ENG Description":"LTA Intellectual Disability","POR Description":"LTA Deficiência Intelectual","SPA Description":"LTA Discapacidad Intelectual"},{"Class":"LTAPD","Discipline":"RO","ENG Description":"LTA Physical Disability","POR Description":"LTA Deficiência Física","SPA Description":"LTA Discapacidad Física"},{"Class":"TA","Discipline":"RO","ENG Description":"TA","POR Description":"TA","SPA Description":"TA"},{"Class":"1","Discipline":"SA","ENG Description":"1 point","POR Description":"1 ponto","SPA Description":"1 punto"},{"Class":"2","Discipline":"SA","ENG Description":"2 points","POR Description":"2 pontos","SPA Description":"2 puntos"},{"Class":"3","Discipline":"SA","ENG Description":"3 points","POR Description":"3 pontos","SPA Description":"3 puntos"},{"Class":"4","Discipline":"SA","ENG Description":"4 points","POR Description":"4 pontos","SPA Description":"4 puntos"},{"Class":"5","Discipline":"SA","ENG Description":"5 points","POR Description":"5 pontos","SPA Description":"5 puntos"},{"Class":"6","Discipline":"SA","ENG Description":"6 points","POR Description":"6 pontos","SPA Description":"6 puntos"},{"Class":"7","Discipline":"SA","ENG Description":"7 points","POR Description":"7 pontos","SPA Description":"7 puntos"},{"Class":"MD","Discipline":"SA","ENG Description":"Minimal Disability","POR Description":"Deficiência Mínima","SPA Description":"Discapacidad mínima"},{"Class":"TPA","Discipline":"SA","ENG Description":"2-Person format Classificat. A","POR Description":"TPA","SPA Description":"TPA"},{"Class":"TPB","Discipline":"SA","ENG Description":"2-Person format Classificat. B","POR Description":"TPB","SPA Description":"TPB"},{"Class":"SH1","Discipline":"SH","ENG Description":"SH1","POR Description":"SH1","SPA Description":"SH1"},{"Class":"SH2","Discipline":"SH","ENG Description":"SH2","POR Description":"SH2","SPA Description":"SH2"},{"Class":"S1","Discipline":"SW","ENG Description":"S1","POR Description":"S1","SPA Description":"S1"},{"Class":"S10","Discipline":"SW","ENG Description":"S10","POR Description":"S10","SPA Description":"S10"},{"Class":"S11","Discipline":"SW","ENG Description":"S11","POR Description":"S11","SPA Description":"S11"},{"Class":"S12","Discipline":"SW","ENG Description":"S12","POR Description":"S12","SPA Description":"S12"},{"Class":"S13","Discipline":"SW","ENG Description":"S13","POR Description":"S13","SPA Description":"S13"},{"Class":"S14","Discipline":"SW","ENG Description":"S14","POR Description":"S14","SPA Description":"S14"},{"Class":"S2","Discipline":"SW","ENG Description":"S2","POR Description":"S2","SPA Description":"S2"},{"Class":"S3","Discipline":"SW","ENG Description":"S3","POR Description":"S3","SPA Description":"S3"},{"Class":"S4","Discipline":"SW","ENG Description":"S4","POR Description":"S4","SPA Description":"S4"},{"Class":"S5","Discipline":"SW","ENG Description":"S5","POR Description":"S5","SPA Description":"S5"},{"Class":"S6","Discipline":"SW","ENG Description":"S6","POR Description":"S6","SPA Description":"S6"},{"Class":"S7","Discipline":"SW","ENG Description":"S7","POR Description":"S7","SPA Description":"S7"},{"Class":"S8","Discipline":"SW","ENG Description":"S8","POR Description":"S8","SPA Description":"S8"},{"Class":"S9","Discipline":"SW","ENG Description":"S9","POR Description":"S9","SPA Description":"S9"},{"Class":"SB1","Discipline":"SW","ENG Description":"SB1","POR Description":"SB1","SPA Description":"SB1"},{"Class":"SB11","Discipline":"SW","ENG Description":"SB11","POR Description":"SB11","SPA Description":"SB11"},{"Class":"SB12","Discipline":"SW","ENG Description":"SB12","POR Description":"SB12","SPA Description":"SB12"},{"Class":"SB13","Discipline":"SW","ENG Description":"SB13","POR Description":"SB13","SPA Description":"SB13"},{"Class":"SB14","Discipline":"SW","ENG Description":"SB14","POR Description":"SB14","SPA Description":"SB14"},{"Class":"SB2","Discipline":"SW","ENG Description":"SB2","POR Description":"SB2","SPA Description":"SB2"},{"Class":"SB3","Discipline":"SW","ENG Description":"SB3","POR Description":"SB3","SPA Description":"SB3"},{"Class":"SB4","Discipline":"SW","ENG Description":"SB4","POR Description":"SB4","SPA Description":"SB4"},{"Class":"SB5","Discipline":"SW","ENG Description":"SB5","POR Description":"SB5","SPA Description":"SB5"},{"Class":"SB6","Discipline":"SW","ENG Description":"SB6","POR Description":"SB6","SPA Description":"SB6"},{"Class":"SB7","Discipline":"SW","ENG Description":"SB7","POR Description":"SB7","SPA Description":"SB7"},{"Class":"SB8","Discipline":"SW","ENG Description":"SB8","POR Description":"SB8","SPA Description":"SB8"},{"Class":"SB9","Discipline":"SW","ENG Description":"SB9","POR Description":"SB9","SPA Description":"SB9"},{"Class":"SM1","Discipline":"SW","ENG Description":"SM1","POR Description":"SM1","SPA Description":"SM1"},{"Class":"SM10","Discipline":"SW","ENG Description":"SM10","POR Description":"SM10","SPA Description":"SM10"},{"Class":"SM11","Discipline":"SW","ENG Description":"SM11","POR Description":"SM11","SPA Description":"SM11"},{"Class":"SM12","Discipline":"SW","ENG Description":"SM12","POR Description":"SM12","SPA Description":"SM12"},{"Class":"SM13","Discipline":"SW","ENG Description":"SM13","POR Description":"SM13","SPA Description":"SM13"},{"Class":"SM14","Discipline":"SW","ENG Description":"SM14","POR Description":"SM14","SPA Description":"SM14"},{"Class":"SM2","Discipline":"SW","ENG Description":"SM2","POR Description":"SM2","SPA Description":"SM2"},{"Class":"SM3","Discipline":"SW","ENG Description":"SM3","POR Description":"SM3","SPA Description":"SM3"},{"Class":"SM4","Discipline":"SW","ENG Description":"SM4","POR Description":"SM4","SPA Description":"SM4"},{"Class":"SM5","Discipline":"SW","ENG Description":"SM5","POR Description":"SM5","SPA Description":"SM5"},{"Class":"SM6","Discipline":"SW","ENG Description":"SM6","POR Description":"SM6","SPA Description":"SM6"},{"Class":"SM7","Discipline":"SW","ENG Description":"SM7","POR Description":"SM7","SPA Description":"SM7"},{"Class":"SM8","Discipline":"SW","ENG Description":"SM8","POR Description":"SM8","SPA Description":"SM8"},{"Class":"SM9","Discipline":"SW","ENG Description":"SM9","POR Description":"SM9","SPA Description":"SM9"},{"Class":"GUI","Discipline":"TR","ENG Description":"Guide","POR Description":"Guia","SPA Description":"Guía"},{"Class":"PT1M","Discipline":"TR","ENG Description":"PT1M","POR Description":"PT1M","SPA Description":"PT1M"},{"Class":"PT2M","Discipline":"TR","ENG Description":"PT2M","POR Description":"PT2M","SPA Description":"PT2M"},{"Class":"PT2W","Discipline":"TR","ENG Description":"PT2W","POR Description":"PT2W","SPA Description":"PT2W"},{"Class":"PT4M","Discipline":"TR","ENG Description":"PT4M","POR Description":"PT4M","SPA Description":"PT4M"},{"Class":"PT4W","Discipline":"TR","ENG Description":"PT4W","POR Description":"PT4W","SPA Description":"PT4W"},{"Class":"PT5W-B1","Discipline":"TR","ENG Description":"PT5W-B1","POR Description":"PT5W-B1","SPA Description":"PT5W-B1"},{"Class":"PT5W-B2","Discipline":"TR","ENG Description":"PT5W-B2","POR Description":"PT5W-B2","SPA Description":"PT5W-B2"},{"Class":"PT5W-B3","Discipline":"TR","ENG Description":"PT5W-B3","POR Description":"PT5W-B3","SPA Description":"PT5W-B3"},{"Class":"1","Discipline":"TT","ENG Description":"1","POR Description":"1","SPA Description":1},{"Class":"10","Discipline":"TT","ENG Description":"10","POR Description":"10","SPA Description":10},{"Class":"11","Discipline":"TT","ENG Description":"11","POR Description":"11","SPA Description":11},{"Class":"2","Discipline":"TT","ENG Description":"2","POR Description":"2","SPA Description":2},{"Class":"3","Discipline":"TT","ENG Description":"3","POR Description":"3","SPA Description":3},{"Class":"4","Discipline":"TT","ENG Description":"4","POR Description":"4","SPA Description":4},{"Class":"5","Discipline":"TT","ENG Description":"5","POR Description":"5","SPA Description":5},{"Class":"6","Discipline":"TT","ENG Description":"6","POR Description":"6","SPA Description":6},{"Class":"7","Discipline":"TT","ENG Description":"7","POR Description":"7","SPA Description":7},{"Class":"8","Discipline":"TT","ENG Description":"8","POR Description":"8","SPA Description":8},{"Class":"9","Discipline":"TT","ENG Description":"9","POR Description":"9","SPA Description":9},{"Class":"D","Discipline":"VS","ENG Description":"D","POR Description":"D","SPA Description":"D"},{"Class":"MD","Discipline":"VS","ENG Description":"MD","POR Description":"MD","SPA Description":"MD"},{"Class":"1.0","Discipline":"WB","ENG Description":"1.0 points","POR Description":"1,0 ponto","SPA Description":"1,0 puntos"},{"Class":"1.5","Discipline":"WB","ENG Description":"1.5 points","POR Description":"1,5 ponto","SPA Description":"1,5 puntos"},{"Class":"2.0","Discipline":"WB","ENG Description":"2.0 points","POR Description":"2,0 pontos","SPA Description":"2,0 puntos"},{"Class":"2.5","Discipline":"WB","ENG Description":"2.5 points","POR Description":"2,5 pontos","SPA Description":"2,5 puntos"},{"Class":"3.0","Discipline":"WB","ENG Description":"3.0 points","POR Description":"3,0 pontos","SPA Description":"3,0 puntos"},{"Class":"3.5","Discipline":"WB","ENG Description":"3.5 points","POR Description":"3,5 pontos","SPA Description":"3,5 puntos"},{"Class":"4.0","Discipline":"WB","ENG Description":"4.0 points","POR Description":"4,0 pontos","SPA Description":"4,0 puntos"},{"Class":"4.5","Discipline":"WB","ENG Description":"4.5 points","POR Description":"4,5 pontos","SPA Description":"4,5 puntos"},{"Class":"A","Discipline":"WF","ENG Description":"Category A","POR Description":"Categoria A","SPA Description":"Categoría A"},{"Class":"B","Discipline":"WF","ENG Description":"Category B","POR Description":"Categoria B","SPA Description":"Categoría B"},{"Class":"0.5","Discipline":"WR","ENG Description":"0.5 points","POR Description":"0,5 ponto","SPA Description":"0,5 puntos"},{"Class":"1.0","Discipline":"WR","ENG Description":"1.0 points","POR Description":"1,0 ponto","SPA Description":"1,0 puntos"},{"Class":"1.5","Discipline":"WR","ENG Description":"1.5 points","POR Description":"1,5 ponto","SPA Description":"1,5 puntos"},{"Class":"2.0","Discipline":"WR","ENG Description":"2.0 points","POR Description":"2,0 pontos","SPA Description":"2,0 puntos"},{"Class":"2.5","Discipline":"WR","ENG Description":"2.5 points","POR Description":"2,5 pontos","SPA Description":"2,5 puntos"},{"Class":"3.0","Discipline":"WR","ENG Description":"3.0 points","POR Description":"3,0 pontos","SPA Description":"3,0 puntos"},{"Class":"3.5","Discipline":"WR","ENG Description":"3.5 points","POR Description":"3,5 pontos","SPA Description":"3,5 puntos"},{"Class":"Q","Discipline":"WT","ENG Description":"Quad","POR Description":"Quad","SPA Description":"Quad"},{"Class":"WT","Discipline":"WT","ENG Description":"WT","POR Description":"WT","SPA Description":"WT"}]